Workbook

Sheet Dashboard
A1: Bahnpolitik im Deutschen Bundestag
A2: Auswertung der DIP-API des Deutschen Bundestages
N3: Typ | O3: Anzahl
A4: Drucksachen gesamt | B4: =COUNTA(Drucksachen!$D$2:$D$293) | N4: Kleine Anfrage | O4: =COUNTIF(Drucksachen!$E$2:$E$293,N4)
A5: davon Kleine Anfragen | B5: =COUNTIF(Drucksachen!$E$2:$E$293,"Kleine Anfrage") | N5: Antwort | O5: =COUNTIF(Drucksachen!$E$2:$E$293,N5)
A6: davon Antworten der Regierung | B6: =COUNTIF(Drucksachen!$E$2:$E$293,"Antwort") | N6: Antrag | O6: =COUNTIF(Drucksachen!$E$2:$E$293,N6)
A7: Antraege und Gesetzentwuerfe | B7: =COUNTIF(Drucksachen!$E$2:$E$293,"Antrag")+COUNTIF(Drucksachen!$E$2:$E$293,"Gesetzentwurf")+COUNTIF(Drucksachen!$E$2:$E$293,"Entschließungsantrag") | N7: Beschlussempfehlung und Bericht | O7: =COUNTIF(Drucksachen!$E$2:$E$293,N7)
A8: Initiativen der Opposition | B8: =COUNTIF(Drucksachen!$G$2:$G$293,"Opposition") | N8: Unterrichtung | O8: =COUNTIF(Drucksachen!$E$2:$E$293,N8)
A9: Initiativen der Regierungsfraktionen | B9: =COUNTIF(Drucksachen!$G$2:$G$293,"Regierungsfraktion") | N9: Wahlvorschlag | O9: =COUNTIF(Drucksachen!$E$2:$E$293,N9)
A10: Aktivste Fraktion | B10: =INDEX(Initiativen!$A$5:$A$9,MATCH(MAX(Initiativen!$G$5:$G$9),Initiativen!$G$5:$G$9,0)) | N10: Gesetzentwurf | O10: =COUNTIF(Drucksachen!$E$2:$E$293,N10)
A11: Mittlere Antwortzeit (Tage) | B11: =IFERROR(AVERAGEIFS(Drucksachen!$K$2:$K$293,Drucksachen!$K$2:$K$293,">0"),"") | N11: Ergänzende Antwort | O11: =COUNTIF(Drucksachen!$E$2:$E$293,N11)
A12: Erste Drucksache | B12: =MIN(Drucksachen!$A$2:$A$293) | N12: Entschließungsantrag | O12: =COUNTIF(Drucksachen!$E$2:$E$293,N12)
A13: Letzte Drucksache | B13: =MAX(Drucksachen!$A$2:$A$293)
N14: Rolle | O14: Anzahl
A15: Lesehinweise und Datenqualitaet | N15: Regierung | O15: =COUNTIF(Drucksachen!$G$2:$G$293,N15)
A16: • Erhebung ueber die Titelsuche der DIP-API. Eine Drucksache wird nur erfasst, wenn einer der Suchbegriffe im Titel steht - Vollstaendigkeit ist damit ausdruecklich nicht gegeben. | N16: Opposition | O16: =COUNTIF(Drucksachen!$G$2:$G$293,N16)
A17: • Suchbegriffe: Schienenverkehr, Schienennetz, Schieneninfrastruktur, Eisenbahn, Deutsche Bahn, Bahnstrecke, Bahnhof, Nahverkehr, Regionalisierungsmittel, Deutschlandtakt, Deutschlandticket | N17: Regierungsfraktion | O17: =COUNTIF(Drucksachen!$G$2:$G$293,N17)
A18: • Die Spalte 'Rolle ab WP 21' beschreibt den heutigen Status. Aeltere Drucksachen derselben Fraktion koennen aus der Oppositionszeit stammen - massgeblich ist die Spalte 'Rolle' auf dem Blatt Drucksachen. | N18: Ausschuss | O18: =COUNTIF(Drucksachen!$G$2:$G$293,N18)
A19: • Der Fraktionsvergleich auf dem Blatt 'Initiativen' zaehlt nur selbst eingebrachte Drucksachen. Antworten der Bundesregierung werden der Regierung zugerechnet, nicht der fragenden Fraktion. | N19: Fraktionsuebergreifend | O19: =COUNTIF(Drucksachen!$G$2:$G$293,N19)
A20: • Regierungsfraktionen stellen praktisch keine Kleinen Anfragen an die eigene Regierung. Hohe Zahlen bei Oppositionsfraktionen sind daher kein Mass fuer bahnpolitisches Engagement, sondern folgen aus der parlamentarischen Rolle. Die Spalte 'Rolle' macht das sichtbar. | N20: Sonstige | O20: =COUNTIF(Drucksachen!$G$2:$G$293,N20)
A21: • Wahlperiode 20 (bis Maerz 2025): Regierung aus SPD, Gruenen und FDP. Wahlperiode 21: Regierung aus CDU/CSU und SPD.
A22: • Gemeinschafts-Drucksachen mehrerer Fraktionen laufen unter 'Mehrere Fraktionen' und werden keiner einzelnen Fraktion zugerechnet.
A23: • Themen werden aus dem Titel abgeleitet, Mehrfachzuordnung ist moeglich und beabsichtigt.
A24: • Erstellt am 11.10.2026 10:58 durch bahnpolitik_dip.py Version 3.

Sheet Drucksachen
A1: Datum | B1: Jahr | C1: Quartal | D1: Nummer | E1: Typ | F1: Urheber | G1: Rolle | H1: WP | I1: Themen | J1: Bezug auf | K1: Antwort nach (Tage) | L1: Antwort in | M1: Titel | N1: Urheber (roh) | O1: PDF | P1: Anfrage von | Q1: Serie | R1: Abgestimmt
A2: 46294 | B2: =IF(A2="","",YEAR(A2)) | C2: =IF(A2="","",YEAR(A2)&"-Q"&ROUNDUP(MONTH(A2)/3,0)) | D2: 21/8263 | E2: Antwort | F2: Bundesregierung | G2: Regierung | H2: 21 | I2: Infrastruktur/Netz | J2: 21/7722 | K2: =IF(OR(J2="",LEFT(E2,7)<>"Antwort"),"",IFERROR(A2-INDEX($A$2:$A$293,MATCH(J2,$D$2:$D$293,0)),"")) | L2: =IF(E2<>"Kleine Anfrage","",IFERROR(INDEX($D$2:$D$293,MATCH(D2,$J$2:$J$293,0)),"offen")) | M2: Schieneninfrastruktur in Ostdeutschland | N2: Bundesregierung | O2: PDF | P2: Linke | R2: =IF(COUNTIF(Abstimmungen!$B$5:$B$2000,D2)-COUNTIFS(Abstimmungen!$B$5:$B$2000,D2,Abstimmungen!$D$5:$D$2000,"*berweisung*")>0,1,0)
A3: 46290 | B3: =IF(A3="","",YEAR(A3)) | C3: =IF(A3="","",YEAR(A3)&"-Q"&ROUNDUP(MONTH(A3)/3,0)) | D3: 21/8225 | E3: Kleine Anfrage | F3: AfD | G3: Opposition | H3: 21 | I3: Bahnhoefe; Kriminalitaet | K3: =IF(OR(J3="",LEFT(E3,7)<>"Antwort"),"",IFERROR(A3-INDEX($A$2:$A$293,MATCH(J3,$D$2:$D$293,0)),"")) | L3: =IF(E3<>"Kleine Anfrage","",IFERROR(INDEX($D$2:$D$293,MATCH(D3,$J$2:$J$293,0)),"offen")) | M3: Kriminalitätsfelder in Bezug auf Bahnhöfe und Züge im ersten Halbjahr 2026 | N3: Fraktion der AfD | O3: PDF | Q3: Bahnhöfe / Kriminalitätsfelder | R3: =IF(COUNTIF(Abstimmungen!$B$5:$B$2000,D3)-COUNTIFS(Abstimmungen!$B$5:$B$2000,D3,Abstimmungen!$D$5:$D$2000,"*berweisung*")>0,1,0)
A4: 46275 | B4: =IF(A4="","",YEAR(A4)) | C4: =IF(A4="","",YEAR(A4)&"-Q"&ROUNDUP(MONTH(A4)/3,0)) | D4: 21/7988 | E4: Antwort | F4: Bundesregierung | G4: Regierung | H4: 21 | I4: Puenktlichkeit/Qualitaet | J4: 21/7607 | K4: =IF(OR(J4="",LEFT(E4,7)<>"Antwort"),"",IFERROR(A4-INDEX($A$2:$A$293,MATCH(J4,$D$2:$D$293,0)),"")) | L4: =IF(E4<>"Kleine Anfrage","",IFERROR(INDEX($D$2:$D$293,MATCH(D4,$J$2:$J$293,0)),"offen")) | M4: Bundesweiter Funkausfall bei der Deutschen Bahn - Ursachen, Auswirkungen und Konsequenzen für die digitale Bahninfrastruktur | N4: Bundesregierung | O4: PDF | P4: AfD | R4: =IF(COUNTIF(Abstimmungen!$B$5:$B$2000,D4)-COUNTIFS(Abstimmungen!$B$5:$B$2000,D4,Abstimmungen!$D$5:$D$2000,"*berweisung*")>0,1,0)
A5: 46275 | B5: =IF(A5="","",YEAR(A5)) | C5: =IF(A5="","",YEAR(A5)&"-Q"&ROUNDUP(MONTH(A5)/3,0)) | D5: 21/8000 | E5: Unterrichtung | F5: Bundesregierung | G5: Regierung | H5: 21 | I5: Nahverkehr/SPNV; Finanzierung | K5: =IF(OR(J5="",LEFT(E5,7)<>"Antwort"),"",IFERROR(A5-INDEX($A$2:$A$293,MATCH(J5,$D$2:$D$293,0)),"")) | L5: =IF(E5<>"Kleine Anfrage","",IFERROR(INDEX($D$2:$D$293,MATCH(D5,$J$2:$J$293,0)),"offen")) | M5: Bericht der Bundesregierung zur Verwendung der Regionalisierungsmittel durch die Länder im Jahr 2020 | N5: Bundesregierung | O5: PDF | R5: =IF(COUNTIF(Abstimmungen!$B$5:$B$2000,D5)-COUNTIFS(Abstimmungen!$B$5:$B$2000,D5,Abstimmungen!$D$5:$D$2000,"*berweisung*")>0,1,0)
A6: 46268 | B6: =IF(A6="","",YEAR(A6)) | C6: =IF(A6="","",YEAR(A6)&"-Q"&ROUNDUP(MONTH(A6)/3,0)) | D6: 21/7838 | E6: Antwort | F6: Bundesregierung | G6: Regierung | H6: 21 | I6: Infrastruktur/Netz | J6: 21/7483 | K6: =IF(OR(J6="",LEFT(E6,7)<>"Antwort"),"",IFERROR(A6-INDEX($A$2:$A$293,MATCH(J6,$D$2:$D$293,0)),"")) | L6: =IF(E6<>"Kleine Anfrage","",IFERROR(INDEX($D$2:$D$293,MATCH(D6,$J$2:$J$293,0)),"offen")) | M6: Ersatz von Brücken auf der Bahnstrecke Köln-Siegen (Siegstrecke) | N6: Bundesregierung | O6: PDF | P6: Gruene | R6: =IF(COUNTIF(Abstimmungen!$B$5:$B$2000,D6)-COUNTIFS(Abstimmungen!$B$5:$B$2000,D6,Abstimmungen!$D$5:$D$2000,"*berweisung*")>0,1,0)
A7: 46261 | B7: =IF(A7="","",YEAR(A7)) | C7: =IF(A7="","",YEAR(A7)&"-Q"&ROUNDUP(MONTH(A7)/3,0)) | D7: 21/7755 | E7: Antwort | F7: Bundesregierung | G7: Regierung | H7: 21 | I7: Bahnhoefe | J7: 21/7468 | K7: =IF(OR(J7="",LEFT(E7,7)<>"Antwort"),"",IFERROR(A7-INDEX($A$2:$A$293,MATCH(J7,$D$2:$D$293,0)),"")) | L7: =IF(E7<>"Kleine Anfrage","",IFERROR(INDEX($D$2:$D$293,MATCH(D7,$J$2:$J$293,0)),"offen")) | M7: Anbindung des zukünftigen Abstellbahnhofs Untertürkheim an den Bahnhof Stuttgart-Bad Cannstatt | N7: Bundesregierung | O7: PDF | P7: Gruene | R7: =IF(COUNTIF(Abstimmungen!$B$5:$B$2000,D7)-COUNTIFS(Abstimmungen!$B$5:$B$2000,D7,Abstimmungen!$D$5:$D$2000,"*berweisung*")>0,1,0)
A8: 46259 | B8: =IF(A8="","",YEAR(A8)) | C8: =IF(A8="","",YEAR(A8)&"-Q"&ROUNDUP(MONTH(A8)/3,0)) | D8: 21/7722 | E8: Kleine Anfrage | F8: Linke | G8: Opposition | H8: 21 | I8: Infrastruktur/Netz | K8: =IF(OR(J8="",LEFT(E8,7)<>"Antwort"),"",IFERROR(A8-INDEX($A$2:$A$293,MATCH(J8,$D$2:$D$293,0)),"")) | L8: =IF(E8<>"Kleine Anfrage","",IFERROR(INDEX($D$2:$D$293,MATCH(D8,$J$2:$J$293,0)),"offen")) | M8: Schieneninfrastruktur in Ostdeutschland | N8: Fraktion DIE LINKE | O8: PDF | R8: =IF(COUNTIF(Abstimmungen!$B$5:$B$2000,D8)-COUNTIFS(Abstimmungen!$B$5:$B$2000,D8,Abstimmungen!$D$5:$D$2000,"*berweisung*")>0,1,0)
A9: 46251 | B9: =IF(A9="","",YEAR(A9)) | C9: =IF(A9="","",YEAR(A9)&"-Q"&ROUNDUP(MONTH(A9)/3,0)) | D9: 21/7607 | E9: Kleine Anfrage | F9: AfD | G9: Opposition | H9: 21 | I9: Puenktlichkeit/Qualitaet | K9: =IF(OR(J9="",LEFT(E9,7)<>"Antwort"),"",IFERROR(A9-INDEX($A$2:$A$293,MATCH(J9,$D$2:$D$293,0)),"")) | L9: =IF(E9<>"Kleine Anfrage","",IFERROR(INDEX($D$2:$D$293,MATCH(D9,$J$2:$J$293,0)),"offen")) | M9: Bundesweiter Funkausfall bei der Deutschen Bahn - Ursachen, Auswirkungen und Konsequenzen für die digitale Bahninfrastruktur | N9: Fraktion der AfD | O9: PDF | R9: =IF(COUNTIF(Abstimmungen!$B$5:$B$2000,D9)-COUNTIFS(Abstimmungen!$B$5:$B$2000,D9,Abstimmungen!$D$5:$D$2000,"*berweisung*")>0,1,0)
A10: 46239 | B10: =IF(A10="","",YEAR(A10)) | C10: =IF(A10="","",YEAR(A10)&"-Q"&ROUNDUP(MONTH(A10)/3,0)) | D10: 21/7483 | E10: Kleine Anfrage | F10: Gruene | G10: Opposition | H10: 21 | I10: Infrastruktur/Netz | K10: =IF(OR(J10="",LEFT(E10,7)<>"Antwort"),"",IFERROR(A10-INDEX($A$2:$A$293,MATCH(J10,$D$2:$D$293,0)),"")) | L10: =IF(E10<>"Kleine Anfrage","",IFERROR(INDEX($D$2:$D$293,MATCH(D10,$J$2:$J$293,0)),"offen")) | M10: Ersatz von Brücken auf der Bahnstrecke Köln-Siegen (Siegstrecke) | N10: Fraktion BÜNDNIS 90/DIE GRÜNEN | O10: PDF | R10: =IF(COUNTIF(Abstimmungen!$B$5:$B$2000,D10)-COUNTIFS(Abstimmungen!$B$5:$B$2000,D10,Abstimmungen!$D$5:$D$2000,"*berweisung*")>0,1,0)
A11: 46238 | B11: =IF(A11="","",YEAR(A11)) | C11: =IF(A11="","",YEAR(A11)&"-Q"&ROUNDUP(MONTH(A11)/3,0)) | D11: 21/7468 | E11: Kleine Anfrage | F11: Gruene | G11: Opposition | H11: 21 | I11: Bahnhoefe | K11: =IF(OR(J11="",LEFT(E11,7)<>"Antwort"),"",IFERROR(A11-INDEX($A$2:$A$293,MATCH(J11,$D$2:$D$293,0)),"")) | L11: =IF(E11<>"Kleine Anfrage","",IFERROR(INDEX($D$2:$D$293,MATCH(D11,$J$2:$J$293,0)),"offen")) | M11: Anbindung des zukünftigen Abstellbahnhofs Untertürkheim an den Bahnhof Stuttgart-Bad Cannstatt | N11: Fraktion BÜNDNIS 90/DIE GRÜNEN | O11: PDF | R11: =IF(COUNTIF(Abstimmungen!$B$5:$B$2000,D11)-COUNTIFS(Abstimmungen!$B$5:$B$2000,D11,Abstimmungen!$D$5:$D$2000,"*berweisung*")>0,1,0)
A12: 46225 | B12: =IF(A12="","",YEAR(A12)) | C12: =IF(A12="","",YEAR(A12)&"-Q"&ROUNDUP(MONTH(A12)/3,0)) | D12: 21/7277 | E12: Antwort | F12: Bundesregierung | G12: Regierung | H12: 21 | I12: Sicherheit | J12: 21/6626 | K12: =IF(OR(J12="",LEFT(E12,7)<>"Antwort"),"",IFERROR(A12-INDEX($A$2:$A$293,MATCH(J12,$D$2:$D$293,0)),"")) | L12: =IF(E12<>"Kleine Anfrage","",IFERROR(INDEX($D$2:$D$293,MATCH(D12,$J$2:$J$293,0)),"offen")) | M12: Risse von Oberleitungen der Deutschen Bahn AG im Jahr 2026, Gefährdungen von Fahrgästen und Krisenmanagement | N12: Bundesregierung | O12: PDF | P12: AfD | R12: =IF(COUNTIF(Abstimmungen!$B$5:$B$2000,D12)-COUNTIFS(Abstimmungen!$B$5:$B$2000,D12,Abstimmungen!$D$5:$D$2000,"*berweisung*")>0,1,0)
A13: 46210 | B13: =IF(A13="","",YEAR(A13)) | C13: =IF(A13="","",YEAR(A13)&"-Q"&ROUNDUP(MONTH(A13)/3,0)) | D13: 21/6922 | E13: Antrag | F13: Gruene | G13: Opposition | H13: 21 | I13: Infrastruktur/Netz; Konzernstruktur/DB AG | K13: =IF(OR(J13="",LEFT(E13,7)<>"Antwort"),"",IFERROR(A13-INDEX($A$2:$A$293,MATCH(J13,$D$2:$D$293,0)),"")) | L13: =IF(E13<>"Kleine Anfrage","",IFERROR(INDEX($D$2:$D$293,MATCH(D13,$J$2:$J$293,0)),"offen")) | M13: Stillstand in der Bahnpolitik überwinden - Strukturreformen umsetzen, Kapazitäten des Schienennetzes verstärken und ein gutes Fernverkehrsangebot sicherstellen | N13: Fraktion BÜNDNIS 90/DIE GRÜNEN | O13: PDF | R13: =IF(COUNTIF(Abstimmungen!$B$5:$B$2000,D13)-COUNTIFS(Abstimmungen!$B$5:$B$2000,D13,Abstimmungen!$D$5:$D$2000,"*berweisung*")>0,1,0)
A14: 46209 | B14: =IF(A14="","",YEAR(A14)) | C14: =IF(A14="","",YEAR(A14)&"-Q"&ROUNDUP(MONTH(A14)/3,0)) | D14: 21/6880 | E14: Beschlussempfehlung und Bericht | F14: Verkehrsausschuss | G14: Ausschuss | H14: 21 | I14: Konzernstruktur/DB AG | J14: 21/6331 | K14: =IF(OR(J14="",LEFT(E14,7)<>"Antwort"),"",IFERROR(A14-INDEX($A$2:$A$293,MATCH(J14,$D$2:$D$293,0)),"")) | L14: =IF(E14<>"Kleine Anfrage","",IFERROR(INDEX($D$2:$D$293,MATCH(D14,$J$2:$J$293,0)),"offen")) | M14: Leistung erbringen, Neutralität wahren - Aufgabenfremde Maßnahmen wie die Regenbogenbeflaggung bei der Deutsche Bahn AG unterlassen | N14: Verkehrsausschuss | O14: PDF | R14: =IF(COUNTIF(Abstimmungen!$B$5:$B$2000,D14)-COUNTIFS(Abstimmungen!$B$5:$B$2000,D14,Abstimmungen!$D$5:$D$2000,"*berweisung*")>0,1,0)
A15: 46204 | B15: =IF(A15="","",YEAR(A15)) | C15: =IF(A15="","",YEAR(A15)&"-Q"&ROUNDUP(MONTH(A15)/3,0)) | D15: 21/6812 | E15: Antwort | F15: Bundesregierung | G15: Regierung | H15: 21 | I15: Infrastruktur/Netz | J15: 21/6517 | K15: =IF(OR(J15="",LEFT(E15,7)<>"Antwort"),"",IFERROR(A15-INDEX($A$2:$A$293,MATCH(J15,$D$2:$D$293,0)),"")) | L15: =IF(E15<>"Kleine Anfrage","",IFERROR(INDEX($D$2:$D$293,MATCH(D15,$J$2:$J$293,0)),"offen")) | M15: Ausbau der Bahnstrecke Berlin-Dresden und mögliche Reduzierung auf 160 km/h | N15: Bundesregierung | O15: PDF | P15: Linke | R15: =IF(COUNTIF(Abstimmungen!$B$5:$B$2000,D15)-COUNTIFS(Abstimmungen!$B$5:$B$2000,D15,Abstimmungen!$D$5:$D$2000,"*berweisung*")>0,1,0)
A16: 46197 | B16: =IF(A16="","",YEAR(A16)) | C16: =IF(A16="","",YEAR(A16)&"-Q"&ROUNDUP(MONTH(A16)/3,0)) | D16: 21/6701 | E16: Beschlussempfehlung und Bericht | F16: Verkehrsausschuss | G16: Ausschuss | H16: 21 | I16: Infrastruktur/Netz | J16: 21/4099 | K16: =IF(OR(J16="",LEFT(E16,7)<>"Antwort"),"",IFERROR(A16-INDEX($A$2:$A$293,MATCH(J16,$D$2:$D$293,0)),"")) | L16: =IF(E16<>"Kleine Anfrage","",IFERROR(INDEX($D$2:$D$293,MATCH(D16,$J$2:$J$293,0)),"offen")) | M16: Entwurf eines Infrastruktur-Zukunftsgesetzes | N16: Verkehrsausschuss | O16: PDF | R16: =IF(COUNTIF(Abstimmungen!$B$5:$B$2000,D16)-COUNTIFS(Abstimmungen!$B$5:$B$2000,D16,Abstimmungen!$D$5:$D$2000,"*berweisung*")>0,1,0)
A17: 46197 | B17: =IF(A17="","",YEAR(A17)) | C17: =IF(A17="","",YEAR(A17)&"-Q"&ROUNDUP(MONTH(A17)/3,0)) | D17: 21/6626 | E17: Kleine Anfrage | F17: AfD | G17: Opposition | H17: 21 | I17: Sicherheit | K17: =IF(OR(J17="",LEFT(E17,7)<>"Antwort"),"",IFERROR(A17-INDEX($A$2:$A$293,MATCH(J17,$D$2:$D$293,0)),"")) | L17: =IF(E17<>"Kleine Anfrage","",IFERROR(INDEX($D$2:$D$293,MATCH(D17,$J$2:$J$293,0)),"offen")) | M17: Risse von Oberleitungen der Deutschen Bahn AG im Jahr 2026, Gefährdungen von Fahrgästen und Krisenmanagement | N17: Fraktion der AfD | O17: PDF | R17: =IF(COUNTIF(Abstimmungen!$B$5:$B$2000,D17)-COUNTIFS(Abstimmungen!$B$5:$B$2000,D17,Abstimmungen!$D$5:$D$2000,"*berweisung*")>0,1,0)
A18: 46195 | B18: =IF(A18="","",YEAR(A18)) | C18: =IF(A18="","",YEAR(A18)&"-Q"&ROUNDUP(MONTH(A18)/3,0)) | D18: 21/6601 | E18: Antwort | F18: Bundesregierung | G18: Regierung | H18: 21 | I18: Bahnhoefe; Kriminalitaet; Sicherheit | J18: 21/6208 | K18: =IF(OR(J18="",LEFT(E18,7)<>"Antwort"),"",IFERROR(A18-INDEX($A$2:$A$293,MATCH(J18,$D$2:$D$293,0)),"")) | L18: =IF(E18<>"Kleine Anfrage","",IFERROR(INDEX($D$2:$D$293,MATCH(D18,$J$2:$J$293,0)),"offen")) | M18: Sicherheit an Bahnhöfen in Bayern - Entwicklung von Sachbeschädigungs-, Körperverletzungs-, Diebstahls- und Raubdelikten sowie Maßnahmen der Bundespolizei | N18: Bundesregierung | O18: PDF | P18: AfD | R18: =IF(COUNTIF(Abstimmungen!$B$5:$B$2000,D18)-COUNTIFS(Abstimmungen!$B$5:$B$2000,D18,Abstimmungen!$D$5:$D$2000,"*berweisung*")>0,1,0)
A19: 46189 | B19: =IF(A19="","",YEAR(A19)) | C19: =IF(A19="","",YEAR(A19)&"-Q"&ROUNDUP(MONTH(A19)/3,0)) | D19: 21/6517 | E19: Kleine Anfrage | F19: Linke | G19: Opposition | H19: 21 | I19: Infrastruktur/Netz | K19: =IF(OR(J19="",LEFT(E19,7)<>"Antwort"),"",IFERROR(A19-INDEX($A$2:$A$293,MATCH(J19,$D$2:$D$293,0)),"")) | L19: =IF(E19<>"Kleine Anfrage","",IFERROR(INDEX($D$2:$D$293,MATCH(D19,$J$2:$J$293,0)),"offen")) | M19: Ausbau der Bahnstrecke Berlin-Dresden und mögliche Reduzierung auf 160 km/h | N19: Fraktion DIE LINKE | O19: PDF | R19: =IF(COUNTIF(Abstimmungen!$B$5:$B$2000,D19)-COUNTIFS(Abstimmungen!$B$5:$B$2000,D19,Abstimmungen!$D$5:$D$2000,"*berweisung*")>0,1,0)
A20: 46182 | B20: =IF(A20="","",YEAR(A20)) | C20: =IF(A20="","",YEAR(A20)&"-Q"&ROUNDUP(MONTH(A20)/3,0)) | D20: 21/6331 | E20: Antrag | F20: AfD | G20: Opposition | H20: 21 | I20: Konzernstruktur/DB AG | K20: =IF(OR(J20="",LEFT(E20,7)<>"Antwort"),"",IFERROR(A20-INDEX($A$2:$A$293,MATCH(J20,$D$2:$D$293,0)),"")) | L20: =IF(E20<>"Kleine Anfrage","",IFERROR(INDEX($D$2:$D$293,MATCH(D20,$J$2:$J$293,0)),"offen")) | M20: Leistung erbringen, Neutralität wahren - Aufgabenfremde Maßnahmen wie die Regenbogenbeflaggung bei der Deutsche Bahn AG unterlassen | N20: Fraktion der AfD | O20: PDF | R20: =IF(COUNTIF(Abstimmungen!$B$5:$B$2000,D20)-COUNTIFS(Abstimmungen!$B$5:$B$2000,D20,Abstimmungen!$D$5:$D$2000,"*berweisung*")>0,1,0)
A21: 46175 | B21: =IF(A21="","",YEAR(A21)) | C21: =IF(A21="","",YEAR(A21)&"-Q"&ROUNDUP(MONTH(A21)/3,0)) | D21: 21/6208 | E21: Kleine Anfrage | F21: AfD | G21: Opposition | H21: 21 | I21: Bahnhoefe; Kriminalitaet; Sicherheit | K21: =IF(OR(J21="",LEFT(E21,7)<>"Antwort"),"",IFERROR(A21-INDEX($A$2:$A$293,MATCH(J21,$D$2:$D$293,0)),"")) | L21: =IF(E21<>"Kleine Anfrage","",IFERROR(INDEX($D$2:$D$293,MATCH(D21,$J$2:$J$293,0)),"offen")) | M21: Sicherheit an Bahnhöfen in Bayern - Entwicklung von Sachbeschädigungs-, Körperverletzungs-, Diebstahls- und Raubdelikten sowie Maßnahmen der Bundespolizei | N21: Fraktion der AfD | O21: PDF | R21: =IF(COUNTIF(Abstimmungen!$B$5:$B$2000,D21)-COUNTIFS(Abstimmungen!$B$5:$B$2000,D21,Abstimmungen!$D$5:$D$2000,"*berweisung*")>0,1,0)
A22: 46168 | B22: =IF(A22="","",YEAR(A22)) | C22: =IF(A22="","",YEAR(A22)&"-Q"&ROUNDUP(MONTH(A22)/3,0)) | D22: 21/6188 | E22: Antwort | F22: Bundesregierung | G22: Regierung | H22: 21 | I22: Bahnhoefe; Kriminalitaet | J22: 21/5940 | K22: =IF(OR(J22="",LEFT(E22,7)<>"Antwort"),"",IFERROR(A22-INDEX($A$2:$A$293,MATCH(J22,$D$2:$D$293,0)),"")) | L22: =IF(E22<>"Kleine Anfrage","",IFERROR(INDEX($D$2:$D$293,MATCH(D22,$J$2:$J$293,0)),"offen")) | M22: Entwicklung der Kriminalität im Bereich des Bahnhofs der Stadt Detmold im Jahr 2025 | N22: Bundesregierung | O22: PDF | P22: AfD | R22: =IF(COUNTIF(Abstimmungen!$B$5:$B$2000,D22)-COUNTIFS(Abstimmungen!$B$5:$B$2000,D22,Abstimmungen!$D$5:$D$2000,"*berweisung*")>0,1,0)
A23: 46168 | B23: =IF(A23="","",YEAR(A23)) | C23: =IF(A23="","",YEAR(A23)&"-Q"&ROUNDUP(MONTH(A23)/3,0)) | D23: 21/6187 | E23: Antwort | F23: Bundesregierung | G23: Regierung | H23: 21 | I23: Bahnhoefe; Kriminalitaet | J23: 21/5938 | K23: =IF(OR(J23="",LEFT(E23,7)<>"Antwort"),"",IFERROR(A23-INDEX($A$2:$A$293,MATCH(J23,$D$2:$D$293,0)),"")) | L23: =IF(E23<>"Kleine Anfrage","",IFERROR(INDEX($D$2:$D$293,MATCH(D23,$J$2:$J$293,0)),"offen")) | M23: Entwicklung der Kriminalität im Bereich des Bahnhofs der Stadt Herford im Jahr 2025 | N23: Bundesregierung | O23: PDF | P23: AfD | R23: =IF(COUNTIF(Abstimmungen!$B$5:$B$2000,D23)-COUNTIFS(Abstimmungen!$B$5:$B$2000,D23,Abstimmungen!$D$5:$D$2000,"*berweisung*")>0,1,0)
A24: 46168 | B24: =IF(A24="","",YEAR(A24)) | C24: =IF(A24="","",YEAR(A24)&"-Q"&ROUNDUP(MONTH(A24)/3,0)) | D24: 21/6186 | E24: Antwort | F24: Bundesregierung | G24: Regierung | H24: 21 | I24: Bahnhoefe; Kriminalitaet | J24: 21/5941 | K24: =IF(OR(J24="",LEFT(E24,7)<>"Antwort"),"",IFERROR(A24-INDEX($A$2:$A$293,MATCH(J24,$D$2:$D$293,0)),"")) | L24: =IF(E24<>"Kleine Anfrage","",IFERROR(INDEX($D$2:$D$293,MATCH(D24,$J$2:$J$293,0)),"offen")) | M24: Entwicklung der Kriminalität im Bereich des Bahnhofs der Stadt Lage im Jahr 2025 | N24: Bundesregierung | O24: PDF | P24: AfD | R24: =IF(COUNTIF(Abstimmungen!$B$5:$B$2000,D24)-COUNTIFS(Abstimmungen!$B$5:$B$2000,D24,Abstimmungen!$D$5:$D$2000,"*berweisung*")>0,1,0)
A25: 46168 | B25: =IF(A25="","",YEAR(A25)) | C25: =IF(A25="","",YEAR(A25)&"-Q"&ROUNDUP(MONTH(A25)/3,0)) | D25: 21/6185 | E25: Antwort | F25: Bundesregierung | G25: Regierung | H25: 21 | I25: Bahnhoefe; Kriminalitaet | J25: 21/5943 | K25: =IF(OR(J25="",LEFT(E25,7)<>"Antwort"),"",IFERROR(A25-INDEX($A$2:$A$293,MATCH(J25,$D$2:$D$293,0)),"")) | L25: =IF(E25<>"Kleine Anfrage","",IFERROR(INDEX($D$2:$D$293,MATCH(D25,$J$2:$J$293,0)),"offen")) | M25: Entwicklung der Kriminalität im Bereich des Bahnhofs der Stadt Löhne im Jahr 2025 | N25: Bundesregierung | O25: PDF | P25: AfD | R25: =IF(COUNTIF(Abstimmungen!$B$5:$B$2000,D25)-COUNTIFS(Abstimmungen!$B$5:$B$2000,D25,Abstimmungen!$D$5:$D$2000,"*berweisung*")>0,1,0)
A26: 46168 | B26: =IF(A26="","",YEAR(A26)) | C26: =IF(A26="","",YEAR(A26)&"-Q"&ROUNDUP(MONTH(A26)/3,0)) | D26: 21/6184 | E26: Antwort | F26: Bundesregierung | G26: Regierung | H26: 21 | I26: Bahnhoefe; Kriminalitaet | J26: 21/5949 | K26: =IF(OR(J26="",LEFT(E26,7)<>"Antwort"),"",IFERROR(A26-INDEX($A$2:$A$293,MATCH(J26,$D$2:$D$293,0)),"")) | L26: =IF(E26<>"Kleine Anfrage","",IFERROR(INDEX($D$2:$D$293,MATCH(D26,$J$2:$J$293,0)),"offen")) | M26: Entwicklung der Kriminalität im Bereich des Bahnhofs der Stadt Bünde im Jahr 2025 | N26: Bundesregierung | O26: PDF | P26: AfD | R26: =IF(COUNTIF(Abstimmungen!$B$5:$B$2000,D26)-COUNTIFS(Abstimmungen!$B$5:$B$2000,D26,Abstimmungen!$D$5:$D$2000,"*berweisung*")>0,1,0)
A27: 46168 | B27: =IF(A27="","",YEAR(A27)) | C27: =IF(A27="","",YEAR(A27)&"-Q"&ROUNDUP(MONTH(A27)/3,0)) | D27: 21/6157 | E27: Antwort | F27: Bundesregierung | G27: Regierung | H27: 21 | I27: Bahnhoefe; Kriminalitaet | J27: 21/5945 | K27: =IF(OR(J27="",LEFT(E27,7)<>"Antwort"),"",IFERROR(A27-INDEX($A$2:$A$293,MATCH(J27,$D$2:$D$293,0)),"")) | L27: =IF(E27<>"Kleine Anfrage","",IFERROR(INDEX($D$2:$D$293,MATCH(D27,$J$2:$J$293,0)),"offen")) | M27: Entwicklung der Kriminalität im Bereich des Bahnhofs der Stadt Warburg im Jahr 2025 | N27: Bundesregierung | O27: PDF | P27: AfD | R27: =IF(COUNTIF(Abstimmungen!$B$5:$B$2000,D27)-COUNTIFS(Abstimmungen!$B$5:$B$2000,D27,Abstimmungen!$D$5:$D$2000,"*berweisung*")>0,1,0)
A28: 46168 | B28: =IF(A28="","",YEAR(A28)) | C28: =IF(A28="","",YEAR(A28)&"-Q"&ROUNDUP(MONTH(A28)/3,0)) | D28: 21/6156 | E28: Antwort | F28: Bundesregierung | G28: Regierung | H28: 21 | I28: Bahnhoefe; Kriminalitaet | J28: 21/5947 | K28: =IF(OR(J28="",LEFT(E28,7)<>"Antwort"),"",IFERROR(A28-INDEX($A$2:$A$293,MATCH(J28,$D$2:$D$293,0)),"")) | L28: =IF(E28<>"Kleine Anfrage","",IFERROR(INDEX($D$2:$D$293,MATCH(D28,$J$2:$J$293,0)),"offen")) | M28: Entwicklung der Kriminalität im Bereich des Bahnhofs der Stadt Bad Oeynhausen im Jahr 2025 | N28: Bundesregierung | O28: PDF | P28: AfD | R28: =IF(COUNTIF(Abstimmungen!$B$5:$B$2000,D28)-COUNTIFS(Abstimmungen!$B$5:$B$2000,D28,Abstimmungen!$D$5:$D$2000,"*berweisung*")>0,1,0)
A29: 46163 | B29: =IF(A29="","",YEAR(A29)) | C29: =IF(A29="","",YEAR(A29)&"-Q"&ROUNDUP(MONTH(A29)/3,0)) | D29: 21/6096 | E29: Antwort | F29: Bundesregierung | G29: Regierung | H29: 21 | I29: Infrastruktur/Netz | J29: 21/5610 | K29: =IF(OR(J29="",LEFT(E29,7)<>"Antwort"),"",IFERROR(A29-INDEX($A$2:$A$293,MATCH(J29,$D$2:$D$293,0)),"")) | L29: =IF(E29<>"Kleine Anfrage","",IFERROR(INDEX($D$2:$D$293,MATCH(D29,$J$2:$J$293,0)),"offen")) | M29: Infrastrukturzustandsnoten Schieneninfrastruktur in Berlin | N29: Bundesregierung | O29: PDF | P29: Gruene | R29: =IF(COUNTIF(Abstimmungen!$B$5:$B$2000,D29)-COUNTIFS(Abstimmungen!$B$5:$B$2000,D29,Abstimmungen!$D$5:$D$2000,"*berweisung*")>0,1,0)
A30: 46157 | B30: =IF(A30="","",YEAR(A30)) | C30: =IF(A30="","",YEAR(A30)&"-Q"&ROUNDUP(MONTH(A30)/3,0)) | D30: 21/5949 | E30: Kleine Anfrage | F30: AfD | G30: Opposition | H30: 21 | I30: Bahnhoefe; Kriminalitaet | K30: =IF(OR(J30="",LEFT(E30,7)<>"Antwort"),"",IFERROR(A30-INDEX($A$2:$A$293,MATCH(J30,$D$2:$D$293,0)),"")) | L30: =IF(E30<>"Kleine Anfrage","",IFERROR(INDEX($D$2:$D$293,MATCH(D30,$J$2:$J$293,0)),"offen")) | M30: Entwicklung der Kriminalität im Bereich des Bahnhofs der Stadt Bünde im Jahr 2025 | N30: Fraktion der AfD | O30: PDF | Q30: Entwicklung / Kriminalität | R30: =IF(COUNTIF(Abstimmungen!$B$5:$B$2000,D30)-COUNTIFS(Abstimmungen!$B$5:$B$2000,D30,Abstimmungen!$D$5:$D$2000,"*berweisung*")>0,1,0)
A31: 46157 | B31: =IF(A31="","",YEAR(A31)) | C31: =IF(A31="","",YEAR(A31)&"-Q"&ROUNDUP(MONTH(A31)/3,0)) | D31: 21/5947 | E31: Kleine Anfrage | F31: AfD | G31: Opposition | H31: 21 | I31: Bahnhoefe; Kriminalitaet | K31: =IF(OR(J31="",LEFT(E31,7)<>"Antwort"),"",IFERROR(A31-INDEX($A$2:$A$293,MATCH(J31,$D$2:$D$293,0)),"")) | L31: =IF(E31<>"Kleine Anfrage","",IFERROR(INDEX($D$2:$D$293,MATCH(D31,$J$2:$J$293,0)),"offen")) | M31: Entwicklung der Kriminalität im Bereich des Bahnhofs der Stadt Bad Oeynhausen im Jahr 2025 | N31: Fraktion der AfD | O31: PDF | Q31: Entwicklung / Kriminalität | R31: =IF(COUNTIF(Abstimmungen!$B$5:$B$2000,D31)-COUNTIFS(Abstimmungen!$B$5:$B$2000,D31,Abstimmungen!$D$5:$D$2000,"*berweisung*")>0,1,0)
A32: 46157 | B32: =IF(A32="","",YEAR(A32)) | C32: =IF(A32="","",YEAR(A32)&"-Q"&ROUNDUP(MONTH(A32)/3,0)) | D32: 21/5945 | E32: Kleine Anfrage | F32: AfD | G32: Opposition | H32: 21 | I32: Bahnhoefe; Kriminalitaet | K32: =IF(OR(J32="",LEFT(E32,7)<>"Antwort"),"",IFERROR(A32-INDEX($A$2:$A$293,MATCH(J32,$D$2:$D$293,0)),"")) | L32: =IF(E32<>"Kleine Anfrage","",IFERROR(INDEX($D$2:$D$293,MATCH(D32,$J$2:$J$293,0)),"offen")) | M32: Entwicklung der Kriminalität im Bereich des Bahnhofs der Stadt Warburg im Jahr 2025 | N32: Fraktion der AfD | O32: PDF | Q32: Entwicklung / Kriminalität | R32: =IF(COUNTIF(Abstimmungen!$B$5:$B$2000,D32)-COUNTIFS(Abstimmungen!$B$5:$B$2000,D32,Abstimmungen!$D$5:$D$2000,"*berweisung*")>0,1,0)
A33: 46157 | B33: =IF(A33="","",YEAR(A33)) | C33: =IF(A33="","",YEAR(A33)&"-Q"&ROUNDUP(MONTH(A33)/3,0)) | D33: 21/5943 | E33: Kleine Anfrage | F33: AfD | G33: Opposition | H33: 21 | I33: Bahnhoefe; Kriminalitaet | K33: =IF(OR(J33="",LEFT(E33,7)<>"Antwort"),"",IFERROR(A33-INDEX($A$2:$A$293,MATCH(J33,$D$2:$D$293,0)),"")) | L33: =IF(E33<>"Kleine Anfrage","",IFERROR(INDEX($D$2:$D$293,MATCH(D33,$J$2:$J$293,0)),"offen")) | M33: Entwicklung der Kriminalität im Bereich des Bahnhofs der Stadt Löhne im Jahr 2025 | N33: Fraktion der AfD | O33: PDF | Q33: Entwicklung / Kriminalität | R33: =IF(COUNTIF(Abstimmungen!$B$5:$B$2000,D33)-COUNTIFS(Abstimmungen!$B$5:$B$2000,D33,Abstimmungen!$D$5:$D$2000,"*berweisung*")>0,1,0)
A34: 46157 | B34: =IF(A34="","",YEAR(A34)) | C34: =IF(A34="","",YEAR(A34)&"-Q"&ROUNDUP(MONTH(A34)/3,0)) | D34: 21/5941 | E34: Kleine Anfrage | F34: AfD | G34: Opposition | H34: 21 | I34: Bahnhoefe; Kriminalitaet | K34: =IF(OR(J34="",LEFT(E34,7)<>"Antwort"),"",IFERROR(A34-INDEX($A$2:$A$293,MATCH(J34,$D$2:$D$293,0)),"")) | L34: =IF(E34<>"Kleine Anfrage","",IFERROR(INDEX($D$2:$D$293,MATCH(D34,$J$2:$J$293,0)),"offen")) | M34: Entwicklung der Kriminalität im Bereich des Bahnhofs der Stadt Lage im Jahr 2025 | N34: Fraktion der AfD | O34: PDF | Q34: Entwicklung / Kriminalität | R34: =IF(COUNTIF(Abstimmungen!$B$5:$B$2000,D34)-COUNTIFS(Abstimmungen!$B$5:$B$2000,D34,Abstimmungen!$D$5:$D$2000,"*berweisung*")>0,1,0)
A35: 46157 | B35: =IF(A35="","",YEAR(A35)) | C35: =IF(A35="","",YEAR(A35)&"-Q"&ROUNDUP(MONTH(A35)/3,0)) | D35: 21/5940 | E35: Kleine Anfrage | F35: AfD | G35: Opposition | H35: 21 | I35: Bahnhoefe; Kriminalitaet | K35: =IF(OR(J35="",LEFT(E35,7)<>"Antwort"),"",IFERROR(A35-INDEX($A$2:$A$293,MATCH(J35,$D$2:$D$293,0)),"")) | L35: =IF(E35<>"Kleine Anfrage","",IFERROR(INDEX($D$2:$D$293,MATCH(D35,$J$2:$J$293,0)),"offen")) | M35: Entwicklung der Kriminalität im Bereich des Bahnhofs der Stadt Detmold im Jahr 2025 | N35: Fraktion der AfD | O35: PDF | Q35: Entwicklung / Kriminalität | R35: =IF(COUNTIF(Abstimmungen!$B$5:$B$2000,D35)-COUNTIFS(Abstimmungen!$B$5:$B$2000,D35,Abstimmungen!$D$5:$D$2000,"*berweisung*")>0,1,0)
A36: 46157 | B36: =IF(A36="","",YEAR(A36)) | C36: =IF(A36="","",YEAR(A36)&"-Q"&ROUNDUP(MONTH(A36)/3,0)) | D36: 21/5938 | E36: Kleine Anfrage | F36: AfD | G36: Opposition | H36: 21 | I36: Bahnhoefe; Kriminalitaet | K36: =IF(OR(J36="",LEFT(E36,7)<>"Antwort"),"",IFERROR(A36-INDEX($A$2:$A$293,MATCH(J36,$D$2:$D$293,0)),"")) | L36: =IF(E36<>"Kleine Anfrage","",IFERROR(INDEX($D$2:$D$293,MATCH(D36,$J$2:$J$293,0)),"offen")) | M36: Entwicklung der Kriminalität im Bereich des Bahnhofs der Stadt Herford im Jahr 2025 | N36: Fraktion der AfD | O36: PDF | Q36: Entwicklung / Kriminalität | R36: =IF(COUNTIF(Abstimmungen!$B$5:$B$2000,D36)-COUNTIFS(Abstimmungen!$B$5:$B$2000,D36,Abstimmungen!$D$5:$D$2000,"*berweisung*")>0,1,0)
A37: 46147 | B37: =IF(A37="","",YEAR(A37)) | C37: =IF(A37="","",YEAR(A37)&"-Q"&ROUNDUP(MONTH(A37)/3,0)) | D37: 21/5732 | E37: Antwort | F37: Bundesregierung | G37: Regierung | H37: 21 | I37: Bahnhoefe; Kriminalitaet | J37: 21/4586 | K37: =IF(OR(J37="",LEFT(E37,7)<>"Antwort"),"",IFERROR(A37-INDEX($A$2:$A$293,MATCH(J37,$D$2:$D$293,0)),"")) | L37: =IF(E37<>"Kleine Anfrage","",IFERROR(INDEX($D$2:$D$293,MATCH(D37,$J$2:$J$293,0)),"offen")) | M37: Straftaten an Thüringer Bahnhöfen und Flughäfen im Jahr 2025 | N37: Bundesregierung | O37: PDF | P37: AfD | R37: =IF(COUNTIF(Abstimmungen!$B$5:$B$2000,D37)-COUNTIFS(Abstimmungen!$B$5:$B$2000,D37,Abstimmungen!$D$5:$D$2000,"*berweisung*")>0,1,0)
A38: 46142 | B38: =IF(A38="","",YEAR(A38)) | C38: =IF(A38="","",YEAR(A38)&"-Q"&ROUNDUP(MONTH(A38)/3,0)) | D38: 21/5700 | E38: Unterrichtung | F38: Bundesregierung | G38: Regierung | H38: 21 | I38: Nahverkehr/SPNV; Finanzierung | K38: =IF(OR(J38="",LEFT(E38,7)<>"Antwort"),"",IFERROR(A38-INDEX($A$2:$A$293,MATCH(J38,$D$2:$D$293,0)),"")) | L38: =IF(E38<>"Kleine Anfrage","",IFERROR(INDEX($D$2:$D$293,MATCH(D38,$J$2:$J$293,0)),"offen")) | M38: Bericht der Bundesregierung zur Verwendung der Regionalisierungsmittel durch die Länder im Jahr 2019 | N38: Bundesregierung | O38: PDF | R38: =IF(COUNTIF(Abstimmungen!$B$5:$B$2000,D38)-COUNTIFS(Abstimmungen!$B$5:$B$2000,D38,Abstimmungen!$D$5:$D$2000,"*berweisung*")>0,1,0)
A39: 46140 | B39: =IF(A39="","",YEAR(A39)) | C39: =IF(A39="","",YEAR(A39)&"-Q"&ROUNDUP(MONTH(A39)/3,0)) | D39: 21/5663 | E39: Antwort | F39: Bundesregierung | G39: Regierung | H39: 21 | I39: Infrastruktur/Netz | J39: 21/4635 | K39: =IF(OR(J39="",LEFT(E39,7)<>"Antwort"),"",IFERROR(A39-INDEX($A$2:$A$293,MATCH(J39,$D$2:$D$293,0)),"")) | L39: =IF(E39<>"Kleine Anfrage","",IFERROR(INDEX($D$2:$D$293,MATCH(D39,$J$2:$J$293,0)),"offen")) | M39: Generalsanierung der Bahnstrecke Troisdorf-Wiesbaden | N39: Bundesregierung | O39: PDF | P39: Gruene | R39: =IF(COUNTIF(Abstimmungen!$B$5:$B$2000,D39)-COUNTIFS(Abstimmungen!$B$5:$B$2000,D39,Abstimmungen!$D$5:$D$2000,"*berweisung*")>0,1,0)
A40: 46139 | B40: =IF(A40="","",YEAR(A40)) | C40: =IF(A40="","",YEAR(A40)&"-Q"&ROUNDUP(MONTH(A40)/3,0)) | D40: 21/5610 | E40: Kleine Anfrage | F40: Gruene | G40: Opposition | H40: 21 | I40: Infrastruktur/Netz | K40: =IF(OR(J40="",LEFT(E40,7)<>"Antwort"),"",IFERROR(A40-INDEX($A$2:$A$293,MATCH(J40,$D$2:$D$293,0)),"")) | L40: =IF(E40<>"Kleine Anfrage","",IFERROR(INDEX($D$2:$D$293,MATCH(D40,$J$2:$J$293,0)),"offen")) | M40: Infrastrukturzustandsnoten Schieneninfrastruktur in Berlin | N40: Fraktion BÜNDNIS 90/DIE GRÜNEN | O40: PDF | R40: =IF(COUNTIF(Abstimmungen!$B$5:$B$2000,D40)-COUNTIFS(Abstimmungen!$B$5:$B$2000,D40,Abstimmungen!$D$5:$D$2000,"*berweisung*")>0,1,0)
A41: 46121 | B41: =IF(A41="","",YEAR(A41)) | C41: =IF(A41="","",YEAR(A41)&"-Q"&ROUNDUP(MONTH(A41)/3,0)) | D41: 21/5307 | E41: Antwort | F41: Bundesregierung | G41: Regierung | H41: 21 | I41: Kriminalitaet | J41: 21/4552 | K41: =IF(OR(J41="",LEFT(E41,7)<>"Antwort"),"",IFERROR(A41-INDEX($A$2:$A$293,MATCH(J41,$D$2:$D$293,0)),"")) | L41: =IF(E41<>"Kleine Anfrage","",IFERROR(INDEX($D$2:$D$293,MATCH(D41,$J$2:$J$293,0)),"offen")) | M41: Übergriffe auf Mitarbeiter der Deutschen Bahn AG seit 2015 und Sachstand Arbeitsschutz | N41: Bundesregierung | O41: PDF | P41: AfD | R41: =IF(COUNTIF(Abstimmungen!$B$5:$B$2000,D41)-COUNTIFS(Abstimmungen!$B$5:$B$2000,D41,Abstimmungen!$D$5:$D$2000,"*berweisung*")>0,1,0)
A42: 46092 | B42: =IF(A42="","",YEAR(A42)) | C42: =IF(A42="","",YEAR(A42)&"-Q"&ROUNDUP(MONTH(A42)/3,0)) | D42: 21/4635 | E42: Kleine Anfrage | F42: Gruene | G42: Opposition | H42: 21 | I42: Infrastruktur/Netz | K42: =IF(OR(J42="",LEFT(E42,7)<>"Antwort"),"",IFERROR(A42-INDEX($A$2:$A$293,MATCH(J42,$D$2:$D$293,0)),"")) | L42: =IF(E42<>"Kleine Anfrage","",IFERROR(INDEX($D$2:$D$293,MATCH(D42,$J$2:$J$293,0)),"offen")) | M42: Generalsanierung der Bahnstrecke Troisdorf-Wiesbaden | N42: Fraktion BÜNDNIS 90/DIE GRÜNEN | O42: PDF | R42: =IF(COUNTIF(Abstimmungen!$B$5:$B$2000,D42)-COUNTIFS(Abstimmungen!$B$5:$B$2000,D42,Abstimmungen!$D$5:$D$2000,"*berweisung*")>0,1,0)
A43: 46087 | B43: =IF(A43="","",YEAR(A43)) | C43: =IF(A43="","",YEAR(A43)&"-Q"&ROUNDUP(MONTH(A43)/3,0)) | D43: 21/4586 | E43: Kleine Anfrage | F43: AfD | G43: Opposition | H43: 21 | I43: Bahnhoefe; Kriminalitaet | K43: =IF(OR(J43="",LEFT(E43,7)<>"Antwort"),"",IFERROR(A43-INDEX($A$2:$A$293,MATCH(J43,$D$2:$D$293,0)),"")) | L43: =IF(E43<>"Kleine Anfrage","",IFERROR(INDEX($D$2:$D$293,MATCH(D43,$J$2:$J$293,0)),"offen")) | M43: Straftaten an Thüringer Bahnhöfen und Flughäfen im Jahr 2025 | N43: Fraktion der AfD | O43: PDF | Q43: Bahnhöfen / Straftaten | R43: =IF(COUNTIF(Abstimmungen!$B$5:$B$2000,D43)-COUNTIFS(Abstimmungen!$B$5:$B$2000,D43,Abstimmungen!$D$5:$D$2000,"*berweisung*")>0,1,0)
A44: 46086 | B44: =IF(A44="","",YEAR(A44)) | C44: =IF(A44="","",YEAR(A44)&"-Q"&ROUNDUP(MONTH(A44)/3,0)) | D44: 21/4552 | E44: Kleine Anfrage | F44: AfD | G44: Opposition | H44: 21 | I44: Kriminalitaet | K44: =IF(OR(J44="",LEFT(E44,7)<>"Antwort"),"",IFERROR(A44-INDEX($A$2:$A$293,MATCH(J44,$D$2:$D$293,0)),"")) | L44: =IF(E44<>"Kleine Anfrage","",IFERROR(INDEX($D$2:$D$293,MATCH(D44,$J$2:$J$293,0)),"offen")) | M44: Übergriffe auf Mitarbeiter der Deutschen Bahn AG seit 2015 und Sachstand Arbeitsschutz | N44: Fraktion der AfD | O44: PDF | R44: =IF(COUNTIF(Abstimmungen!$B$5:$B$2000,D44)-COUNTIFS(Abstimmungen!$B$5:$B$2000,D44,Abstimmungen!$D$5:$D$2000,"*berweisung*")>0,1,0)
A45: 46086 | B45: =IF(A45="","",YEAR(A45)) | C45: =IF(A45="","",YEAR(A45)&"-Q"&ROUNDUP(MONTH(A45)/3,0)) | D45: 21/4578 | E45: Antwort | F45: Bundesregierung | G45: Regierung | H45: 21 | I45: Bahnhoefe; Kriminalitaet | J45: 21/4055 | K45: =IF(OR(J45="",LEFT(E45,7)<>"Antwort"),"",IFERROR(A45-INDEX($A$2:$A$293,MATCH(J45,$D$2:$D$293,0)),"")) | L45: =IF(E45<>"Kleine Anfrage","",IFERROR(INDEX($D$2:$D$293,MATCH(D45,$J$2:$J$293,0)),"offen")) | M45: Kriminalitätsentwicklung am Bahnhof Ludwigsburg im Vergleich der Jahre 2024 und 2025 | N45: Bundesregierung | O45: PDF | P45: AfD | R45: =IF(COUNTIF(Abstimmungen!$B$5:$B$2000,D45)-COUNTIFS(Abstimmungen!$B$5:$B$2000,D45,Abstimmungen!$D$5:$D$2000,"*berweisung*")>0,1,0)
A46: 46085 | B46: =IF(A46="","",YEAR(A46)) | C46: =IF(A46="","",YEAR(A46)&"-Q"&ROUNDUP(MONTH(A46)/3,0)) | D46: 21/4567 | E46: Antwort | F46: Bundesregierung | G46: Regierung | H46: 21 | I46: Sicherheit | J46: 21/3998 | K46: =IF(OR(J46="",LEFT(E46,7)<>"Antwort"),"",IFERROR(A46-INDEX($A$2:$A$293,MATCH(J46,$D$2:$D$293,0)),"")) | L46: =IF(E46<>"Kleine Anfrage","",IFERROR(INDEX($D$2:$D$293,MATCH(D46,$J$2:$J$293,0)),"offen")) | M46: Sicherheit und Sicherheitskosten im Bereich der Deutschen Bahn AG | N46: Bundesregierung | O46: PDF | P46: AfD | R46: =IF(COUNTIF(Abstimmungen!$B$5:$B$2000,D46)-COUNTIFS(Abstimmungen!$B$5:$B$2000,D46,Abstimmungen!$D$5:$D$2000,"*berweisung*")>0,1,0)
A47: 46084 | B47: =IF(A47="","",YEAR(A47)) | C47: =IF(A47="","",YEAR(A47)&"-Q"&ROUNDUP(MONTH(A47)/3,0)) | D47: 21/4458 | E47: Antrag | F47: Gruene | G47: Opposition | H47: 21 | I47: Infrastruktur/Netz | K47: =IF(OR(J47="",LEFT(E47,7)<>"Antwort"),"",IFERROR(A47-INDEX($A$2:$A$293,MATCH(J47,$D$2:$D$293,0)),"")) | L47: =IF(E47<>"Kleine Anfrage","",IFERROR(INDEX($D$2:$D$293,MATCH(D47,$J$2:$J$293,0)),"offen")) | M47: Infrastrukturvorhaben im Schienennetz effektiv beschleunigen | N47: Fraktion BÜNDNIS 90/DIE GRÜNEN | O47: PDF | R47: =IF(COUNTIF(Abstimmungen!$B$5:$B$2000,D47)-COUNTIFS(Abstimmungen!$B$5:$B$2000,D47,Abstimmungen!$D$5:$D$2000,"*berweisung*")>0,1,0)
A48: 46084 | B48: =IF(A48="","",YEAR(A48)) | C48: =IF(A48="","",YEAR(A48)&"-Q"&ROUNDUP(MONTH(A48)/3,0)) | D48: 21/4501 | E48: Antwort | F48: Bundesregierung | G48: Regierung | H48: 21 | I48: Infrastruktur/Netz; Sicherheit | J48: 21/4041 | K48: =IF(OR(J48="",LEFT(E48,7)<>"Antwort"),"",IFERROR(A48-INDEX($A$2:$A$293,MATCH(J48,$D$2:$D$293,0)),"")) | L48: =IF(E48<>"Kleine Anfrage","",IFERROR(INDEX($D$2:$D$293,MATCH(D48,$J$2:$J$293,0)),"offen")) | M48: Arbeits- und Sicherheitsvorgaben Schienenersatzverkehr im Rahmen der Generalsanierung der Bahnstrecke Hamburg-Berlin | N48: Bundesregierung | O48: PDF | P48: Linke | R48: =IF(COUNTIF(Abstimmungen!$B$5:$B$2000,D48)-COUNTIFS(Abstimmungen!$B$5:$B$2000,D48,Abstimmungen!$D$5:$D$2000,"*berweisung*")>0,1,0)
A49: 46084 | B49: =IF(A49="","",YEAR(A49)) | C49: =IF(A49="","",YEAR(A49)&"-Q"&ROUNDUP(MONTH(A49)/3,0)) | D49: 21/4498 | E49: Antwort | F49: Bundesregierung | G49: Regierung | H49: 21 | I49: Deutschlandticket | J49: 21/4034 | K49: =IF(OR(J49="",LEFT(E49,7)<>"Antwort"),"",IFERROR(A49-INDEX($A$2:$A$293,MATCH(J49,$D$2:$D$293,0)),"")) | L49: =IF(E49<>"Kleine Anfrage","",IFERROR(INDEX($D$2:$D$293,MATCH(D49,$J$2:$J$293,0)),"offen")) | M49: Informationen zur Nutzung des Deutschlandtickets | N49: Bundesregierung | O49: PDF | P49: Linke | R49: =IF(COUNTIF(Abstimmungen!$B$5:$B$2000,D49)-COUNTIFS(Abstimmungen!$B$5:$B$2000,D49,Abstimmungen!$D$5:$D$2000,"*berweisung*")>0,1,0)
A50: 46078 | B50: =IF(A50="","",YEAR(A50)) | C50: =IF(A50="","",YEAR(A50)&"-Q"&ROUNDUP(MONTH(A50)/3,0)) | D50: 21/4380 | E50: Antwort | F50: Bundesregierung | G50: Regierung | H50: 21 | I50: Bahnhoefe; Kriminalitaet | J50: 21/3966 | K50: =IF(OR(J50="",LEFT(E50,7)<>"Antwort"),"",IFERROR(A50-INDEX($A$2:$A$293,MATCH(J50,$D$2:$D$293,0)),"")) | L50: =IF(E50<>"Kleine Anfrage","",IFERROR(INDEX($D$2:$D$293,MATCH(D50,$J$2:$J$293,0)),"offen")) | M50: Kriminalitätsfelder in Bezug auf Bahnhöfe und Züge in Baden-Württemberg im Vergleich der Jahre 2024 und 2025 | N50: Bundesregierung | O50: PDF | P50: AfD | R50: =IF(COUNTIF(Abstimmungen!$B$5:$B$2000,D50)-COUNTIFS(Abstimmungen!$B$5:$B$2000,D50,Abstimmungen!$D$5:$D$2000,"*berweisung*")>0,1,0)
A51: 46078 | B51: =IF(A51="","",YEAR(A51)) | C51: =IF(A51="","",YEAR(A51)&"-Q"&ROUNDUP(MONTH(A51)/3,0)) | D51: 21/4378 | E51: Antwort | F51: Bundesregierung | G51: Regierung | H51: 21 | I51: Bahnhoefe; Kriminalitaet | J51: 21/3934 | K51: =IF(OR(J51="",LEFT(E51,7)<>"Antwort"),"",IFERROR(A51-INDEX($A$2:$A$293,MATCH(J51,$D$2:$D$293,0)),"")) | L51: =IF(E51<>"Kleine Anfrage","",IFERROR(INDEX($D$2:$D$293,MATCH(D51,$J$2:$J$293,0)),"offen")) | M51: Kriminalitätsfelder in Bezug auf Bahnhöfe und Züge in Rheinland-Pfalz im Vergleich der Jahre 2024 und 2025 | N51: Bundesregierung | O51: PDF | P51: AfD | R51: =IF(COUNTIF(Abstimmungen!$B$5:$B$2000,D51)-COUNTIFS(Abstimmungen!$B$5:$B$2000,D51,Abstimmungen!$D$5:$D$2000,"*berweisung*")>0,1,0)
A52: 46071 | B52: =IF(A52="","",YEAR(A52)) | C52: =IF(A52="","",YEAR(A52)&"-Q"&ROUNDUP(MONTH(A52)/3,0)) | D52: 21/4233 | E52: Antwort | F52: Bundesregierung | G52: Regierung | H52: 21 | I52: Bahnhoefe; Sicherheit | J52: 21/3744 | K52: =IF(OR(J52="",LEFT(E52,7)<>"Antwort"),"",IFERROR(A52-INDEX($A$2:$A$293,MATCH(J52,$D$2:$D$293,0)),"")) | L52: =IF(E52<>"Kleine Anfrage","",IFERROR(INDEX($D$2:$D$293,MATCH(D52,$J$2:$J$293,0)),"offen")) | M52: Organisierte Bettelbanden auf deutschen Bahnhöfen und deren Bekämpfung durch Bundespolizei und Deutsche Bahn | N52: Bundesregierung | O52: PDF | P52: AfD | R52: =IF(COUNTIF(Abstimmungen!$B$5:$B$2000,D52)-COUNTIFS(Abstimmungen!$B$5:$B$2000,D52,Abstimmungen!$D$5:$D$2000,"*berweisung*")>0,1,0)
A53: 46065 | B53: =IF(A53="","",YEAR(A53)) | C53: =IF(A53="","",YEAR(A53)&"-Q"&ROUNDUP(MONTH(A53)/3,0)) | D53: 21/4141 | E53: Antwort | F53: Bundesregierung | G53: Regierung | H53: 21 | I53: Bahnhoefe; Kriminalitaet | J53: 21/3935 | K53: =IF(OR(J53="",LEFT(E53,7)<>"Antwort"),"",IFERROR(A53-INDEX($A$2:$A$293,MATCH(J53,$D$2:$D$293,0)),"")) | L53: =IF(E53<>"Kleine Anfrage","",IFERROR(INDEX($D$2:$D$293,MATCH(D53,$J$2:$J$293,0)),"offen")) | M53: Kriminalitätsfelder in Bezug auf Bahnhöfe und Züge im Vergleich der Jahre 2024 und 2025 | N53: Bundesregierung | O53: PDF | P53: AfD | R53: =IF(COUNTIF(Abstimmungen!$B$5:$B$2000,D53)-COUNTIFS(Abstimmungen!$B$5:$B$2000,D53,Abstimmungen!$D$5:$D$2000,"*berweisung*")>0,1,0)
A54: 46064 | B54: =IF(A54="","",YEAR(A54)) | C54: =IF(A54="","",YEAR(A54)&"-Q"&ROUNDUP(MONTH(A54)/3,0)) | D54: 21/4102 | E54: Antwort | F54: Bundesregierung | G54: Regierung | H54: 21 | I54: Bahnhoefe | J54: 21/3851 | K54: =IF(OR(J54="",LEFT(E54,7)<>"Antwort"),"",IFERROR(A54-INDEX($A$2:$A$293,MATCH(J54,$D$2:$D$293,0)),"")) | L54: =IF(E54<>"Kleine Anfrage","",IFERROR(INDEX($D$2:$D$293,MATCH(D54,$J$2:$J$293,0)),"offen")) | M54: Öffentliche Toiletten an bayerischen Bahnhöfen | N54: Bundesregierung | O54: PDF | P54: Linke | R54: =IF(COUNTIF(Abstimmungen!$B$5:$B$2000,D54)-COUNTIFS(Abstimmungen!$B$5:$B$2000,D54,Abstimmungen!$D$5:$D$2000,"*berweisung*")>0,1,0)
A55: 46063 | B55: =IF(A55="","",YEAR(A55)) | C55: =IF(A55="","",YEAR(A55)&"-Q"&ROUNDUP(MONTH(A55)/3,0)) | D55: 21/4041 | E55: Kleine Anfrage | F55: Linke | G55: Opposition | H55: 21 | I55: Infrastruktur/Netz; Sicherheit | K55: =IF(OR(J55="",LEFT(E55,7)<>"Antwort"),"",IFERROR(A55-INDEX($A$2:$A$293,MATCH(J55,$D$2:$D$293,0)),"")) | L55: =IF(E55<>"Kleine Anfrage","",IFERROR(INDEX($D$2:$D$293,MATCH(D55,$J$2:$J$293,0)),"offen")) | M55: Arbeits- und Sicherheitsvorgaben Schienenersatzverkehr im Rahmen der Generalsanierung der Bahnstrecke Hamburg-Berlin | N55: Fraktion DIE LINKE | O55: PDF | R55: =IF(COUNTIF(Abstimmungen!$B$5:$B$2000,D55)-COUNTIFS(Abstimmungen!$B$5:$B$2000,D55,Abstimmungen!$D$5:$D$2000,"*berweisung*")>0,1,0)
A56: 46063 | B56: =IF(A56="","",YEAR(A56)) | C56: =IF(A56="","",YEAR(A56)&"-Q"&ROUNDUP(MONTH(A56)/3,0)) | D56: 21/4055 | E56: Kleine Anfrage | F56: AfD | G56: Opposition | H56: 21 | I56: Bahnhoefe; Kriminalitaet | K56: =IF(OR(J56="",LEFT(E56,7)<>"Antwort"),"",IFERROR(A56-INDEX($A$2:$A$293,MATCH(J56,$D$2:$D$293,0)),"")) | L56: =IF(E56<>"Kleine Anfrage","",IFERROR(INDEX($D$2:$D$293,MATCH(D56,$J$2:$J$293,0)),"offen")) | M56: Kriminalitätsentwicklung am Bahnhof Ludwigsburg im Vergleich der Jahre 2024 und 2025 | N56: Fraktion der AfD | O56: PDF | R56: =IF(COUNTIF(Abstimmungen!$B$5:$B$2000,D56)-COUNTIFS(Abstimmungen!$B$5:$B$2000,D56,Abstimmungen!$D$5:$D$2000,"*berweisung*")>0,1,0)
A57: 46062 | B57: =IF(A57="","",YEAR(A57)) | C57: =IF(A57="","",YEAR(A57)&"-Q"&ROUNDUP(MONTH(A57)/3,0)) | D57: 21/4034 | E57: Kleine Anfrage | F57: Linke | G57: Opposition | H57: 21 | I57: Deutschlandticket | K57: =IF(OR(J57="",LEFT(E57,7)<>"Antwort"),"",IFERROR(A57-INDEX($A$2:$A$293,MATCH(J57,$D$2:$D$293,0)),"")) | L57: =IF(E57<>"Kleine Anfrage","",IFERROR(INDEX($D$2:$D$293,MATCH(D57,$J$2:$J$293,0)),"offen")) | M57: Informationen zur Nutzung des Deutschlandtickets | N57: Fraktion DIE LINKE | O57: PDF | R57: =IF(COUNTIF(Abstimmungen!$B$5:$B$2000,D57)-COUNTIFS(Abstimmungen!$B$5:$B$2000,D57,Abstimmungen!$D$5:$D$2000,"*berweisung*")>0,1,0)
A58: 46057 | B58: =IF(A58="","",YEAR(A58)) | C58: =IF(A58="","",YEAR(A58)&"-Q"&ROUNDUP(MONTH(A58)/3,0)) | D58: 21/3998 | E58: Kleine Anfrage | F58: AfD | G58: Opposition | H58: 21 | I58: Sicherheit | K58: =IF(OR(J58="",LEFT(E58,7)<>"Antwort"),"",IFERROR(A58-INDEX($A$2:$A$293,MATCH(J58,$D$2:$D$293,0)),"")) | L58: =IF(E58<>"Kleine Anfrage","",IFERROR(INDEX($D$2:$D$293,MATCH(D58,$J$2:$J$293,0)),"offen")) | M58: Sicherheit und Sicherheitskosten im Bereich der Deutschen Bahn AG | N58: Fraktion der AfD | O58: PDF | R58: =IF(COUNTIF(Abstimmungen!$B$5:$B$2000,D58)-COUNTIFS(Abstimmungen!$B$5:$B$2000,D58,Abstimmungen!$D$5:$D$2000,"*berweisung*")>0,1,0)
A59: 46056 | B59: =IF(A59="","",YEAR(A59)) | C59: =IF(A59="","",YEAR(A59)&"-Q"&ROUNDUP(MONTH(A59)/3,0)) | D59: 21/3966 | E59: Kleine Anfrage | F59: AfD | G59: Opposition | H59: 21 | I59: Bahnhoefe; Kriminalitaet | K59: =IF(OR(J59="",LEFT(E59,7)<>"Antwort"),"",IFERROR(A59-INDEX($A$2:$A$293,MATCH(J59,$D$2:$D$293,0)),"")) | L59: =IF(E59<>"Kleine Anfrage","",IFERROR(INDEX($D$2:$D$293,MATCH(D59,$J$2:$J$293,0)),"offen")) | M59: Kriminalitätsfelder in Bezug auf Bahnhöfe und Züge in Baden-Württemberg im Vergleich der Jahre 2024 und 2025 | N59: Fraktion der AfD | O59: PDF | Q59: Bahnhöfe / Kriminalitätsfelder | R59: =IF(COUNTIF(Abstimmungen!$B$5:$B$2000,D59)-COUNTIFS(Abstimmungen!$B$5:$B$2000,D59,Abstimmungen!$D$5:$D$2000,"*berweisung*")>0,1,0)
A60: 46052 | B60: =IF(A60="","",YEAR(A60)) | C60: =IF(A60="","",YEAR(A60)&"-Q"&ROUNDUP(MONTH(A60)/3,0)) | D60: 21/3935 | E60: Kleine Anfrage | F60: AfD | G60: Opposition | H60: 21 | I60: Bahnhoefe; Kriminalitaet | K60: =IF(OR(J60="",LEFT(E60,7)<>"Antwort"),"",IFERROR(A60-INDEX($A$2:$A$293,MATCH(J60,$D$2:$D$293,0)),"")) | L60: =IF(E60<>"Kleine Anfrage","",IFERROR(INDEX($D$2:$D$293,MATCH(D60,$J$2:$J$293,0)),"offen")) | M60: Kriminalitätsfelder in Bezug auf Bahnhöfe und Züge im Vergleich der Jahre 2024 und 2025 | N60: Fraktion der AfD | O60: PDF | Q60: Bahnhöfe / Kriminalitätsfelder | R60: =IF(COUNTIF(Abstimmungen!$B$5:$B$2000,D60)-COUNTIFS(Abstimmungen!$B$5:$B$2000,D60,Abstimmungen!$D$5:$D$2000,"*berweisung*")>0,1,0)
A61: 46052 | B61: =IF(A61="","",YEAR(A61)) | C61: =IF(A61="","",YEAR(A61)&"-Q"&ROUNDUP(MONTH(A61)/3,0)) | D61: 21/3934 | E61: Kleine Anfrage | F61: AfD | G61: Opposition | H61: 21 | I61: Bahnhoefe; Kriminalitaet | K61: =IF(OR(J61="",LEFT(E61,7)<>"Antwort"),"",IFERROR(A61-INDEX($A$2:$A$293,MATCH(J61,$D$2:$D$293,0)),"")) | L61: =IF(E61<>"Kleine Anfrage","",IFERROR(INDEX($D$2:$D$293,MATCH(D61,$J$2:$J$293,0)),"offen")) | M61: Kriminalitätsfelder in Bezug auf Bahnhöfe und Züge in Rheinland-Pfalz im Vergleich der Jahre 2024 und 2025 | N61: Fraktion der AfD | O61: PDF | Q61: Bahnhöfe / Kriminalitätsfelder | R61: =IF(COUNTIF(Abstimmungen!$B$5:$B$2000,D61)-COUNTIFS(Abstimmungen!$B$5:$B$2000,D61,Abstimmungen!$D$5:$D$2000,"*berweisung*")>0,1,0)
A62: 46050 | B62: =IF(A62="","",YEAR(A62)) | C62: =IF(A62="","",YEAR(A62)&"-Q"&ROUNDUP(MONTH(A62)/3,0)) | D62: 21/3851 | E62: Kleine Anfrage | F62: Linke | G62: Opposition | H62: 21 | I62: Bahnhoefe | K62: =IF(OR(J62="",LEFT(E62,7)<>"Antwort"),"",IFERROR(A62-INDEX($A$2:$A$293,MATCH(J62,$D$2:$D$293,0)),"")) | L62: =IF(E62<>"Kleine Anfrage","",IFERROR(INDEX($D$2:$D$293,MATCH(D62,$J$2:$J$293,0)),"offen")) | M62: Öffentliche Toiletten an bayerischen Bahnhöfen | N62: Fraktion DIE LINKE | O62: PDF | R62: =IF(COUNTIF(Abstimmungen!$B$5:$B$2000,D62)-COUNTIFS(Abstimmungen!$B$5:$B$2000,D62,Abstimmungen!$D$5:$D$2000,"*berweisung*")>0,1,0)
A63: 46043 | B63: =IF(A63="","",YEAR(A63)) | C63: =IF(A63="","",YEAR(A63)&"-Q"&ROUNDUP(MONTH(A63)/3,0)) | D63: 21/3744 | E63: Kleine Anfrage | F63: AfD | G63: Opposition | H63: 21 | I63: Bahnhoefe; Sicherheit | K63: =IF(OR(J63="",LEFT(E63,7)<>"Antwort"),"",IFERROR(A63-INDEX($A$2:$A$293,MATCH(J63,$D$2:$D$293,0)),"")) | L63: =IF(E63<>"Kleine Anfrage","",IFERROR(INDEX($D$2:$D$293,MATCH(D63,$J$2:$J$293,0)),"offen")) | M63: Organisierte Bettelbanden auf deutschen Bahnhöfen und deren Bekämpfung durch Bundespolizei und Deutsche Bahn | N63: Fraktion der AfD | O63: PDF | R63: =IF(COUNTIF(Abstimmungen!$B$5:$B$2000,D63)-COUNTIFS(Abstimmungen!$B$5:$B$2000,D63,Abstimmungen!$D$5:$D$2000,"*berweisung*")>0,1,0)
A64: 46035 | B64: =IF(A64="","",YEAR(A64)) | C64: =IF(A64="","",YEAR(A64)&"-Q"&ROUNDUP(MONTH(A64)/3,0)) | D64: 21/3595 | E64: Antwort | F64: Bundesregierung | G64: Regierung | H64: 21 | I64: Infrastruktur/Netz | J64: 21/3238 | K64: =IF(OR(J64="",LEFT(E64,7)<>"Antwort"),"",IFERROR(A64-INDEX($A$2:$A$293,MATCH(J64,$D$2:$D$293,0)),"")) | L64: =IF(E64<>"Kleine Anfrage","",IFERROR(INDEX($D$2:$D$293,MATCH(D64,$J$2:$J$293,0)),"offen")) | M64: Elektrifizierungsquote und Ausbauvorhaben im Schienennetz Bayerns im Herbst 2025 | N64: Bundesregierung | O64: PDF | P64: Gruene | R64: =IF(COUNTIF(Abstimmungen!$B$5:$B$2000,D64)-COUNTIFS(Abstimmungen!$B$5:$B$2000,D64,Abstimmungen!$D$5:$D$2000,"*berweisung*")>0,1,0)
A65: 46030 | B65: =IF(A65="","",YEAR(A65)) | C65: =IF(A65="","",YEAR(A65)&"-Q"&ROUNDUP(MONTH(A65)/3,0)) | D65: 21/3563 | E65: Antwort | F65: Bundesregierung | G65: Regierung | H65: 21 | I65: Konzernstruktur/DB AG | J65: 21/3018 | K65: =IF(OR(J65="",LEFT(E65,7)<>"Antwort"),"",IFERROR(A65-INDEX($A$2:$A$293,MATCH(J65,$D$2:$D$293,0)),"")) | L65: =IF(E65<>"Kleine Anfrage","",IFERROR(INDEX($D$2:$D$293,MATCH(D65,$J$2:$J$293,0)),"offen")) | M65: Deutsche Bahn AG und die Zukunft des grünen Stahls in Deutschland AG | N65: Bundesregierung | O65: PDF | P65: Gruene | R65: =IF(COUNTIF(Abstimmungen!$B$5:$B$2000,D65)-COUNTIFS(Abstimmungen!$B$5:$B$2000,D65,Abstimmungen!$D$5:$D$2000,"*berweisung*")>0,1,0)
A66: 46030 | B66: =IF(A66="","",YEAR(A66)) | C66: =IF(A66="","",YEAR(A66)&"-Q"&ROUNDUP(MONTH(A66)/3,0)) | D66: 21/3533 | E66: Antwort | F66: Bundesregierung | G66: Regierung | H66: 21 | I66: Konzernstruktur/DB AG | J66: 21/2806 | K66: =IF(OR(J66="",LEFT(E66,7)<>"Antwort"),"",IFERROR(A66-INDEX($A$2:$A$293,MATCH(J66,$D$2:$D$293,0)),"")) | L66: =IF(E66<>"Kleine Anfrage","",IFERROR(INDEX($D$2:$D$293,MATCH(D66,$J$2:$J$293,0)),"offen")) | M66: Boni für Vorstandsmitglieder und Aufsichtsratsmitglieder der Deutsche Bahn Aktiengesellschaft | N66: Bundesregierung | O66: PDF | P66: AfD | R66: =IF(COUNTIF(Abstimmungen!$B$5:$B$2000,D66)-COUNTIFS(Abstimmungen!$B$5:$B$2000,D66,Abstimmungen!$D$5:$D$2000,"*berweisung*")>0,1,0)
A67: 46013 | B67: =IF(A67="","",YEAR(A67)) | C67: =IF(A67="","",YEAR(A67)&"-Q"&ROUNDUP(MONTH(A67)/3,0)) | D67: 21/3468 | E67: Antwort | F67: Bundesregierung | G67: Regierung | H67: 21 | I67: Infrastruktur/Netz | J67: 21/2883 | K67: =IF(OR(J67="",LEFT(E67,7)<>"Antwort"),"",IFERROR(A67-INDEX($A$2:$A$293,MATCH(J67,$D$2:$D$293,0)),"")) | L67: =IF(E67<>"Kleine Anfrage","",IFERROR(INDEX($D$2:$D$293,MATCH(D67,$J$2:$J$293,0)),"offen")) | M67: Umsetzung von kleinen und mittleren Maßnahmen auf überlasteten Schienenwegen im Schienennetz bis 2030 | N67: Bundesregierung | O67: PDF | P67: Gruene | R67: =IF(COUNTIF(Abstimmungen!$B$5:$B$2000,D67)-COUNTIFS(Abstimmungen!$B$5:$B$2000,D67,Abstimmungen!$D$5:$D$2000,"*berweisung*")>0,1,0)
A68: 46002 | B68: =IF(A68="","",YEAR(A68)) | C68: =IF(A68="","",YEAR(A68)&"-Q"&ROUNDUP(MONTH(A68)/3,0)) | D68: 21/3238 | E68: Kleine Anfrage | F68: Gruene | G68: Opposition | H68: 21 | I68: Infrastruktur/Netz | K68: =IF(OR(J68="",LEFT(E68,7)<>"Antwort"),"",IFERROR(A68-INDEX($A$2:$A$293,MATCH(J68,$D$2:$D$293,0)),"")) | L68: =IF(E68<>"Kleine Anfrage","",IFERROR(INDEX($D$2:$D$293,MATCH(D68,$J$2:$J$293,0)),"offen")) | M68: Elektrifizierungsquote und Ausbauvorhaben im Schienennetz Bayerns im Herbst 2025 | N68: Fraktion BÜNDNIS 90/DIE GRÜNEN | O68: PDF | R68: =IF(COUNTIF(Abstimmungen!$B$5:$B$2000,D68)-COUNTIFS(Abstimmungen!$B$5:$B$2000,D68,Abstimmungen!$D$5:$D$2000,"*berweisung*")>0,1,0)
A69: 46002 | B69: =IF(A69="","",YEAR(A69)) | C69: =IF(A69="","",YEAR(A69)&"-Q"&ROUNDUP(MONTH(A69)/3,0)) | D69: 21/3243 | E69: Antwort | F69: Bundesregierung | G69: Regierung | H69: 21 | I69: Infrastruktur/Netz | J69: 21/2644 | K69: =IF(OR(J69="",LEFT(E69,7)<>"Antwort"),"",IFERROR(A69-INDEX($A$2:$A$293,MATCH(J69,$D$2:$D$293,0)),"")) | L69: =IF(E69<>"Kleine Anfrage","",IFERROR(INDEX($D$2:$D$293,MATCH(D69,$J$2:$J$293,0)),"offen")) | M69: Geschwindigkeitsreduzierung auf der Bahnstrecke München-Buchloe und weiterer Strecken | N69: Bundesregierung | O69: PDF | P69: Gruene | R69: =IF(COUNTIF(Abstimmungen!$B$5:$B$2000,D69)-COUNTIFS(Abstimmungen!$B$5:$B$2000,D69,Abstimmungen!$D$5:$D$2000,"*berweisung*")>0,1,0)
A70: 45999 | B70: =IF(A70="","",YEAR(A70)) | C70: =IF(A70="","",YEAR(A70)&"-Q"&ROUNDUP(MONTH(A70)/3,0)) | D70: 21/3163 | E70: Antwort | F70: Bundesregierung | G70: Regierung | H70: 21 | I70: Bahnhoefe | J70: 21/2704 | K70: =IF(OR(J70="",LEFT(E70,7)<>"Antwort"),"",IFERROR(A70-INDEX($A$2:$A$293,MATCH(J70,$D$2:$D$293,0)),"")) | L70: =IF(E70<>"Kleine Anfrage","",IFERROR(INDEX($D$2:$D$293,MATCH(D70,$J$2:$J$293,0)),"offen")) | M70: Toiletten an Bahnhöfen als Teil der öffentlichen Daseinsvorsorge | N70: Bundesregierung | O70: PDF | P70: Linke | R70: =IF(COUNTIF(Abstimmungen!$B$5:$B$2000,D70)-COUNTIFS(Abstimmungen!$B$5:$B$2000,D70,Abstimmungen!$D$5:$D$2000,"*berweisung*")>0,1,0)
A71: 45993 | B71: =IF(A71="","",YEAR(A71)) | C71: =IF(A71="","",YEAR(A71)&"-Q"&ROUNDUP(MONTH(A71)/3,0)) | D71: 21/3018 | E71: Kleine Anfrage | F71: Gruene | G71: Opposition | H71: 21 | I71: Sonstiges | K71: =IF(OR(J71="",LEFT(E71,7)<>"Antwort"),"",IFERROR(A71-INDEX($A$2:$A$293,MATCH(J71,$D$2:$D$293,0)),"")) | L71: =IF(E71<>"Kleine Anfrage","",IFERROR(INDEX($D$2:$D$293,MATCH(D71,$J$2:$J$293,0)),"offen")) | M71: Deutsche Bahn und die Zukunft des grünen Stahls in Deutschland | N71: Fraktion BÜNDNIS 90/DIE GRÜNEN | O71: PDF | R71: =IF(COUNTIF(Abstimmungen!$B$5:$B$2000,D71)-COUNTIFS(Abstimmungen!$B$5:$B$2000,D71,Abstimmungen!$D$5:$D$2000,"*berweisung*")>0,1,0)
A72: 45985 | B72: =IF(A72="","",YEAR(A72)) | C72: =IF(A72="","",YEAR(A72)&"-Q"&ROUNDUP(MONTH(A72)/3,0)) | D72: 21/2883 | E72: Kleine Anfrage | F72: Gruene | G72: Opposition | H72: 21 | I72: Infrastruktur/Netz | K72: =IF(OR(J72="",LEFT(E72,7)<>"Antwort"),"",IFERROR(A72-INDEX($A$2:$A$293,MATCH(J72,$D$2:$D$293,0)),"")) | L72: =IF(E72<>"Kleine Anfrage","",IFERROR(INDEX($D$2:$D$293,MATCH(D72,$J$2:$J$293,0)),"offen")) | M72: Umsetzung von kleinen und mittleren Maßnahmen auf überlasteten Schienenwegen im Schienennetz bis 2030 | N72: Fraktion BÜNDNIS 90/DIE GRÜNEN | O72: PDF | R72: =IF(COUNTIF(Abstimmungen!$B$5:$B$2000,D72)-COUNTIFS(Abstimmungen!$B$5:$B$2000,D72,Abstimmungen!$D$5:$D$2000,"*berweisung*")>0,1,0)
A73: 45980 | B73: =IF(A73="","",YEAR(A73)) | C73: =IF(A73="","",YEAR(A73)&"-Q"&ROUNDUP(MONTH(A73)/3,0)) | D73: 21/2870 | E73: Ergänzende Antwort | F73: Bundesregierung | G73: Regierung | H73: 21 | I73: Konzernstruktur/DB AG | J73: 21/665 | K73: =IF(OR(J73="",LEFT(E73,7)<>"Antwort"),"",IFERROR(A73-INDEX($A$2:$A$293,MATCH(J73,$D$2:$D$293,0)),"")) | L73: =IF(E73<>"Kleine Anfrage","",IFERROR(INDEX($D$2:$D$293,MATCH(D73,$J$2:$J$293,0)),"offen")) | M73: Entwicklung Gesamtwert Infrastruktur-Großprojekte sowie Zeitpläne der Deutschen Bahn InfraGO | N73: Bundesregierung | O73: PDF | R73: =IF(COUNTIF(Abstimmungen!$B$5:$B$2000,D73)-COUNTIFS(Abstimmungen!$B$5:$B$2000,D73,Abstimmungen!$D$5:$D$2000,"*berweisung*")>0,1,0)
A74: 45974 | B74: =IF(A74="","",YEAR(A74)) | C74: =IF(A74="","",YEAR(A74)&"-Q"&ROUNDUP(MONTH(A74)/3,0)) | D74: 21/2806 | E74: Kleine Anfrage | F74: AfD | G74: Opposition | H74: 21 | I74: Konzernstruktur/DB AG | K74: =IF(OR(J74="",LEFT(E74,7)<>"Antwort"),"",IFERROR(A74-INDEX($A$2:$A$293,MATCH(J74,$D$2:$D$293,0)),"")) | L74: =IF(E74<>"Kleine Anfrage","",IFERROR(INDEX($D$2:$D$293,MATCH(D74,$J$2:$J$293,0)),"offen")) | M74: Boni für Vorstandsmitglieder und Aufsichtsratsmitglieder der Deutsche Bahn Aktiengesellschaft | N74: Fraktion der AfD | O74: PDF | R74: =IF(COUNTIF(Abstimmungen!$B$5:$B$2000,D74)-COUNTIFS(Abstimmungen!$B$5:$B$2000,D74,Abstimmungen!$D$5:$D$2000,"*berweisung*")>0,1,0)
A75: 45973 | B75: =IF(A75="","",YEAR(A75)) | C75: =IF(A75="","",YEAR(A75)&"-Q"&ROUNDUP(MONTH(A75)/3,0)) | D75: 21/2736 | E75: Gesetzentwurf | F75: Bundesrat | G75: Sonstige | H75: 21 | I75: Infrastruktur/Netz | K75: =IF(OR(J75="",LEFT(E75,7)<>"Antwort"),"",IFERROR(A75-INDEX($A$2:$A$293,MATCH(J75,$D$2:$D$293,0)),"")) | L75: =IF(E75<>"Kleine Anfrage","",IFERROR(INDEX($D$2:$D$293,MATCH(D75,$J$2:$J$293,0)),"offen")) | M75: Entwurf eines Gesetzes zur Stärkung des Klimaschutzes durch eine Beschleunigung des Ausbaus der Schieneninfrastruktur - Klimaschutzbeschleunigungsgesetz Schiene* | N75: Bundesrat | O75: PDF | R75: =IF(COUNTIF(Abstimmungen!$B$5:$B$2000,D75)-COUNTIFS(Abstimmungen!$B$5:$B$2000,D75,Abstimmungen!$D$5:$D$2000,"*berweisung*")>0,1,0)
A76: 45973 | B76: =IF(A76="","",YEAR(A76)) | C76: =IF(A76="","",YEAR(A76)&"-Q"&ROUNDUP(MONTH(A76)/3,0)) | D76: 21/2790 | E76: Entschließungsantrag | F76: Gruene | G76: Opposition | H76: 21 | I76: Sonstiges | J76: 21/1499 | K76: =IF(OR(J76="",LEFT(E76,7)<>"Antwort"),"",IFERROR(A76-INDEX($A$2:$A$293,MATCH(J76,$D$2:$D$293,0)),"")) | L76: =IF(E76<>"Kleine Anfrage","",IFERROR(INDEX($D$2:$D$293,MATCH(D76,$J$2:$J$293,0)),"offen")) | M76: zu der dritten Beratung des Gesetzentwurfs der Bundesregierung | N76: Fraktion BÜNDNIS 90/DIE GRÜNEN | O76: PDF | R76: =IF(COUNTIF(Abstimmungen!$B$5:$B$2000,D76)-COUNTIFS(Abstimmungen!$B$5:$B$2000,D76,Abstimmungen!$D$5:$D$2000,"*berweisung*")>0,1,0)
A77: 45973 | B77: =IF(A77="","",YEAR(A77)) | C77: =IF(A77="","",YEAR(A77)&"-Q"&ROUNDUP(MONTH(A77)/3,0)) | D77: 21/2787 | E77: Beschlussempfehlung und Bericht | F77: Verkehrsausschuss | G77: Ausschuss | H77: 21 | I77: Sonstiges | J77: 21/1499 | K77: =IF(OR(J77="",LEFT(E77,7)<>"Antwort"),"",IFERROR(A77-INDEX($A$2:$A$293,MATCH(J77,$D$2:$D$293,0)),"")) | L77: =IF(E77<>"Kleine Anfrage","",IFERROR(INDEX($D$2:$D$293,MATCH(D77,$J$2:$J$293,0)),"offen")) | M77: Entwurf eines Gesetzes zur Abmilderung des Trassenentgeltanstiegs bei den Eisenbahnen des Bundes | N77: Verkehrsausschuss | O77: PDF | R77: =IF(COUNTIF(Abstimmungen!$B$5:$B$2000,D77)-COUNTIFS(Abstimmungen!$B$5:$B$2000,D77,Abstimmungen!$D$5:$D$2000,"*berweisung*")>0,1,0)
A78: 45972 | B78: =IF(A78="","",YEAR(A78)) | C78: =IF(A78="","",YEAR(A78)&"-Q"&ROUNDUP(MONTH(A78)/3,0)) | D78: 21/2704 | E78: Kleine Anfrage | F78: Linke | G78: Opposition | H78: 21 | I78: Bahnhoefe | K78: =IF(OR(J78="",LEFT(E78,7)<>"Antwort"),"",IFERROR(A78-INDEX($A$2:$A$293,MATCH(J78,$D$2:$D$293,0)),"")) | L78: =IF(E78<>"Kleine Anfrage","",IFERROR(INDEX($D$2:$D$293,MATCH(D78,$J$2:$J$293,0)),"offen")) | M78: Toiletten an Bahnhöfen als Teil der öffentlichen Daseinsvorsorge | N78: Fraktion DIE LINKE | O78: PDF | R78: =IF(COUNTIF(Abstimmungen!$B$5:$B$2000,D78)-COUNTIFS(Abstimmungen!$B$5:$B$2000,D78,Abstimmungen!$D$5:$D$2000,"*berweisung*")>0,1,0)
A79: 45967 | B79: =IF(A79="","",YEAR(A79)) | C79: =IF(A79="","",YEAR(A79)&"-Q"&ROUNDUP(MONTH(A79)/3,0)) | D79: 21/2644 | E79: Kleine Anfrage | F79: Gruene | G79: Opposition | H79: 21 | I79: Infrastruktur/Netz | K79: =IF(OR(J79="",LEFT(E79,7)<>"Antwort"),"",IFERROR(A79-INDEX($A$2:$A$293,MATCH(J79,$D$2:$D$293,0)),"")) | L79: =IF(E79<>"Kleine Anfrage","",IFERROR(INDEX($D$2:$D$293,MATCH(D79,$J$2:$J$293,0)),"offen")) | M79: Geschwindigkeitsreduzierung auf der Bahnstrecke München - Buchloe und weiterer Strecken | N79: Fraktion BÜNDNIS 90/DIE GRÜNEN | O79: PDF | R79: =IF(COUNTIF(Abstimmungen!$B$5:$B$2000,D79)-COUNTIFS(Abstimmungen!$B$5:$B$2000,D79,Abstimmungen!$D$5:$D$2000,"*berweisung*")>0,1,0)
A80: 45966 | B80: =IF(A80="","",YEAR(A80)) | C80: =IF(A80="","",YEAR(A80)&"-Q"&ROUNDUP(MONTH(A80)/3,0)) | D80: 21/2591 | E80: Antwort | F80: Bundesregierung | G80: Regierung | H80: 21 | I80: Bahnhoefe; Kriminalitaet | J80: 21/2410 | K80: =IF(OR(J80="",LEFT(E80,7)<>"Antwort"),"",IFERROR(A80-INDEX($A$2:$A$293,MATCH(J80,$D$2:$D$293,0)),"")) | L80: =IF(E80<>"Kleine Anfrage","",IFERROR(INDEX($D$2:$D$293,MATCH(D80,$J$2:$J$293,0)),"offen")) | M80: Kriminalitätsfelder in Bezug auf Bahnhöfe und Züge in Sachsen in den ersten Halbjahren 2024 und 2025 | N80: Bundesregierung | O80: PDF | P80: AfD | R80: =IF(COUNTIF(Abstimmungen!$B$5:$B$2000,D80)-COUNTIFS(Abstimmungen!$B$5:$B$2000,D80,Abstimmungen!$D$5:$D$2000,"*berweisung*")>0,1,0)
A81: 45966 | B81: =IF(A81="","",YEAR(A81)) | C81: =IF(A81="","",YEAR(A81)&"-Q"&ROUNDUP(MONTH(A81)/3,0)) | D81: 21/2628 | E81: Beschlussempfehlung und Bericht | F81: Verkehrsausschuss | G81: Ausschuss | H81: 21 | I81: Deutschlandticket | J81: 21/1543 | K81: =IF(OR(J81="",LEFT(E81,7)<>"Antwort"),"",IFERROR(A81-INDEX($A$2:$A$293,MATCH(J81,$D$2:$D$293,0)),"")) | L81: =IF(E81<>"Kleine Anfrage","",IFERROR(INDEX($D$2:$D$293,MATCH(D81,$J$2:$J$293,0)),"offen")) | M81: Deutschlandticket weiterentwickeln und langfristig sichern | N81: Verkehrsausschuss | O81: PDF | R81: =IF(COUNTIF(Abstimmungen!$B$5:$B$2000,D81)-COUNTIFS(Abstimmungen!$B$5:$B$2000,D81,Abstimmungen!$D$5:$D$2000,"*berweisung*")>0,1,0)
A82: 45957 | B82: =IF(A82="","",YEAR(A82)) | C82: =IF(A82="","",YEAR(A82)&"-Q"&ROUNDUP(MONTH(A82)/3,0)) | D82: 21/2410 | E82: Kleine Anfrage | F82: AfD | G82: Opposition | H82: 21 | I82: Bahnhoefe; Kriminalitaet | K82: =IF(OR(J82="",LEFT(E82,7)<>"Antwort"),"",IFERROR(A82-INDEX($A$2:$A$293,MATCH(J82,$D$2:$D$293,0)),"")) | L82: =IF(E82<>"Kleine Anfrage","",IFERROR(INDEX($D$2:$D$293,MATCH(D82,$J$2:$J$293,0)),"offen")) | M82: Kriminalitätsfelder in Bezug auf Bahnhöfe und Züge in Sachsen in den ersten Halbjahren 2024 und 2025 | N82: Fraktion der AfD | O82: PDF | R82: =IF(COUNTIF(Abstimmungen!$B$5:$B$2000,D82)-COUNTIFS(Abstimmungen!$B$5:$B$2000,D82,Abstimmungen!$D$5:$D$2000,"*berweisung*")>0,1,0)
A83: 45947 | B83: =IF(A83="","",YEAR(A83)) | C83: =IF(A83="","",YEAR(A83)&"-Q"&ROUNDUP(MONTH(A83)/3,0)) | D83: 21/2295 | E83: Beschlussempfehlung und Bericht | F83: Verkehrsausschuss | G83: Ausschuss | H83: 21 | I83: Sonstiges | J83: 21/1754 | K83: =IF(OR(J83="",LEFT(E83,7)<>"Antwort"),"",IFERROR(A83-INDEX($A$2:$A$293,MATCH(J83,$D$2:$D$293,0)),"")) | L83: =IF(E83<>"Kleine Anfrage","",IFERROR(INDEX($D$2:$D$293,MATCH(D83,$J$2:$J$293,0)),"offen")) | M83: Mitglieder des Deutschen Bundestages aus Aufsichtsräten bei der Deutschen Bahn AG und der Autobahn GmbH des Bundes dauerhaft abberufen | N83: Verkehrsausschuss | O83: PDF | R83: =IF(COUNTIF(Abstimmungen!$B$5:$B$2000,D83)-COUNTIFS(Abstimmungen!$B$5:$B$2000,D83,Abstimmungen!$D$5:$D$2000,"*berweisung*")>0,1,0)
A84: 45939 | B84: =IF(A84="","",YEAR(A84)) | C84: =IF(A84="","",YEAR(A84)&"-Q"&ROUNDUP(MONTH(A84)/3,0)) | D84: 21/2143 | E84: Antwort | F84: Bundesregierung | G84: Regierung | H84: 21 | I84: Puenktlichkeit/Qualitaet; Sicherheit | J84: 21/1015 | K84: =IF(OR(J84="",LEFT(E84,7)<>"Antwort"),"",IFERROR(A84-INDEX($A$2:$A$293,MATCH(J84,$D$2:$D$293,0)),"")) | L84: =IF(E84<>"Kleine Anfrage","",IFERROR(INDEX($D$2:$D$293,MATCH(D84,$J$2:$J$293,0)),"offen")) | M84: Störungen im Betriebsablauf bei der Deutschen Bahn AG und deren Auswirkungen auf Sicherheit und Pünktlichkeit | N84: Bundesregierung | O84: PDF | P84: AfD | R84: =IF(COUNTIF(Abstimmungen!$B$5:$B$2000,D84)-COUNTIFS(Abstimmungen!$B$5:$B$2000,D84,Abstimmungen!$D$5:$D$2000,"*berweisung*")>0,1,0)
A85: 45938 | B85: =IF(A85="","",YEAR(A85)) | C85: =IF(A85="","",YEAR(A85)&"-Q"&ROUNDUP(MONTH(A85)/3,0)) | D85: 21/2108 | E85: Beschlussempfehlung und Bericht | F85: Verkehrsausschuss | G85: Ausschuss | H85: 21 | I85: Infrastruktur/Netz; Deutschlandtakt/Fahrplan; Finanzierung | J85: 21/581 | K85: =IF(OR(J85="",LEFT(E85,7)<>"Antwort"),"",IFERROR(A85-INDEX($A$2:$A$293,MATCH(J85,$D$2:$D$293,0)),"")) | L85: =IF(E85<>"Kleine Anfrage","",IFERROR(INDEX($D$2:$D$293,MATCH(D85,$J$2:$J$293,0)),"offen")) | M85: Die Bahn zum Rückgrat klima- und familienfreundlicher Mobilität machen | N85: Verkehrsausschuss | O85: PDF | R85: =IF(COUNTIF(Abstimmungen!$B$5:$B$2000,D85)-COUNTIFS(Abstimmungen!$B$5:$B$2000,D85,Abstimmungen!$D$5:$D$2000,"*berweisung*")>0,1,0)
A86: 45931 | B86: =IF(A86="","",YEAR(A86)) | C86: =IF(A86="","",YEAR(A86)&"-Q"&ROUNDUP(MONTH(A86)/3,0)) | D86: 21/1939 | E86: Unterrichtung | F86: Bundesregierung | G86: Regierung | H86: 21 | I86: Sonstiges | J86: 21/1499 | K86: =IF(OR(J86="",LEFT(E86,7)<>"Antwort"),"",IFERROR(A86-INDEX($A$2:$A$293,MATCH(J86,$D$2:$D$293,0)),"")) | L86: =IF(E86<>"Kleine Anfrage","",IFERROR(INDEX($D$2:$D$293,MATCH(D86,$J$2:$J$293,0)),"offen")) | M86: Entwurf eines Gesetzes zur Abmilderung des Trassenentgeltanstiegs bei den Eisenbahnen des Bundes | N86: Bundesregierung | O86: PDF | R86: =IF(COUNTIF(Abstimmungen!$B$5:$B$2000,D86)-COUNTIFS(Abstimmungen!$B$5:$B$2000,D86,Abstimmungen!$D$5:$D$2000,"*berweisung*")>0,1,0)
A87: 45922 | B87: =IF(A87="","",YEAR(A87)) | C87: =IF(A87="","",YEAR(A87)&"-Q"&ROUNDUP(MONTH(A87)/3,0)) | D87: 21/1754 | E87: Antrag | F87: AfD | G87: Opposition | H87: 21 | I87: Sonstiges | K87: =IF(OR(J87="",LEFT(E87,7)<>"Antwort"),"",IFERROR(A87-INDEX($A$2:$A$293,MATCH(J87,$D$2:$D$293,0)),"")) | L87: =IF(E87<>"Kleine Anfrage","",IFERROR(INDEX($D$2:$D$293,MATCH(D87,$J$2:$J$293,0)),"offen")) | M87: Mitglieder des Deutschen Bundestages aus Aufsichtsräten bei der Deutschen Bahn AG und der Autobahn GmbH des Bundes dauerhaft abberufen | N87: Fraktion der AfD | O87: PDF | R87: =IF(COUNTIF(Abstimmungen!$B$5:$B$2000,D87)-COUNTIFS(Abstimmungen!$B$5:$B$2000,D87,Abstimmungen!$D$5:$D$2000,"*berweisung*")>0,1,0)
A88: 45917 | B88: =IF(A88="","",YEAR(A88)) | C88: =IF(A88="","",YEAR(A88)&"-Q"&ROUNDUP(MONTH(A88)/3,0)) | D88: 21/1651 | E88: Wahlvorschlag | F88: Mehrere Fraktionen | G88: Fraktionsuebergreifend | H88: 21 | I88: Sonstiges | K88: =IF(OR(J88="",LEFT(E88,7)<>"Antwort"),"",IFERROR(A88-INDEX($A$2:$A$293,MATCH(J88,$D$2:$D$293,0)),"")) | L88: =IF(E88<>"Kleine Anfrage","",IFERROR(INDEX($D$2:$D$293,MATCH(D88,$J$2:$J$293,0)),"offen")) | M88: Wahl von Mitgliedern des Beirats bei der Bundesnetzagentur für Elektrizität, Gas, Telekommunikation, Post und Eisenbahnen | N88: Fraktion der AfD; Fraktion der CDU/CSU; Fraktion der SPD | O88: PDF | R88: =IF(COUNTIF(Abstimmungen!$B$5:$B$2000,D88)-COUNTIFS(Abstimmungen!$B$5:$B$2000,D88,Abstimmungen!$D$5:$D$2000,"*berweisung*")>0,1,0)
A89: 45915 | B89: =IF(A89="","",YEAR(A89)) | C89: =IF(A89="","",YEAR(A89)&"-Q"&ROUNDUP(MONTH(A89)/3,0)) | D89: 21/1678 | E89: Wahlvorschlag | F89: Gruene | G89: Opposition | H89: 21 | I89: Sonstiges | K89: =IF(OR(J89="",LEFT(E89,7)<>"Antwort"),"",IFERROR(A89-INDEX($A$2:$A$293,MATCH(J89,$D$2:$D$293,0)),"")) | L89: =IF(E89<>"Kleine Anfrage","",IFERROR(INDEX($D$2:$D$293,MATCH(D89,$J$2:$J$293,0)),"offen")) | M89: Wahl von Mitgliedern des Beirats bei der Bundesnetzagentur für Elektrizität, Gas, Telekommunikation, Post und Eisenbahnen | N89: Fraktion BÜNDNIS 90/DIE GRÜNEN | O89: PDF | R89: =IF(COUNTIF(Abstimmungen!$B$5:$B$2000,D89)-COUNTIFS(Abstimmungen!$B$5:$B$2000,D89,Abstimmungen!$D$5:$D$2000,"*berweisung*")>0,1,0)
A90: 45915 | B90: =IF(A90="","",YEAR(A90)) | C90: =IF(A90="","",YEAR(A90)&"-Q"&ROUNDUP(MONTH(A90)/3,0)) | D90: 21/1679 | E90: Wahlvorschlag | F90: Linke | G90: Opposition | H90: 21 | I90: Sonstiges | K90: =IF(OR(J90="",LEFT(E90,7)<>"Antwort"),"",IFERROR(A90-INDEX($A$2:$A$293,MATCH(J90,$D$2:$D$293,0)),"")) | L90: =IF(E90<>"Kleine Anfrage","",IFERROR(INDEX($D$2:$D$293,MATCH(D90,$J$2:$J$293,0)),"offen")) | M90: Wahl eines Mitglieds des Beirats bei der Bundesnetzagentur für Elektrizität, Gas, Telekommunikation, Post und Eisenbahnen | N90: Fraktion DIE LINKE | O90: PDF | R90: =IF(COUNTIF(Abstimmungen!$B$5:$B$2000,D90)-COUNTIFS(Abstimmungen!$B$5:$B$2000,D90,Abstimmungen!$D$5:$D$2000,"*berweisung*")>0,1,0)
A91: 45910 | B91: =IF(A91="","",YEAR(A91)) | C91: =IF(A91="","",YEAR(A91)&"-Q"&ROUNDUP(MONTH(A91)/3,0)) | D91: 21/1581 | E91: Antwort | F91: Bundesregierung | G91: Regierung | H91: 21 | I91: Bahnhoefe; Kriminalitaet | J91: 21/1342 | K91: =IF(OR(J91="",LEFT(E91,7)<>"Antwort"),"",IFERROR(A91-INDEX($A$2:$A$293,MATCH(J91,$D$2:$D$293,0)),"")) | L91: =IF(E91<>"Kleine Anfrage","",IFERROR(INDEX($D$2:$D$293,MATCH(D91,$J$2:$J$293,0)),"offen")) | M91: Kriminalitätsfelder in Bezug auf Bahnhöfe und Züge in Baden-Württemberg im ersten Halbjahr 2025 | N91: Bundesregierung | O91: PDF | P91: AfD | R91: =IF(COUNTIF(Abstimmungen!$B$5:$B$2000,D91)-COUNTIFS(Abstimmungen!$B$5:$B$2000,D91,Abstimmungen!$D$5:$D$2000,"*berweisung*")>0,1,0)
A92: 45909 | B92: =IF(A92="","",YEAR(A92)) | C92: =IF(A92="","",YEAR(A92)&"-Q"&ROUNDUP(MONTH(A92)/3,0)) | D92: 21/1544 | E92: Antrag | F92: Gruene | G92: Opposition | H92: 21 | I92: Infrastruktur/Netz; Deutschlandtakt/Fahrplan; Finanzierung | K92: =IF(OR(J92="",LEFT(E92,7)<>"Antwort"),"",IFERROR(A92-INDEX($A$2:$A$293,MATCH(J92,$D$2:$D$293,0)),"")) | L92: =IF(E92<>"Kleine Anfrage","",IFERROR(INDEX($D$2:$D$293,MATCH(D92,$J$2:$J$293,0)),"offen")) | M92: Investitionen in die Erweiterung des Schienennetzes sicherstellen - Deutschlandtakt auf den Weg bringen | N92: Fraktion BÜNDNIS 90/DIE GRÜNEN | O92: PDF | R92: =IF(COUNTIF(Abstimmungen!$B$5:$B$2000,D92)-COUNTIFS(Abstimmungen!$B$5:$B$2000,D92,Abstimmungen!$D$5:$D$2000,"*berweisung*")>0,1,0)
A93: 45909 | B93: =IF(A93="","",YEAR(A93)) | C93: =IF(A93="","",YEAR(A93)&"-Q"&ROUNDUP(MONTH(A93)/3,0)) | D93: 21/1543 | E93: Antrag | F93: Gruene | G93: Opposition | H93: 21 | I93: Deutschlandticket | K93: =IF(OR(J93="",LEFT(E93,7)<>"Antwort"),"",IFERROR(A93-INDEX($A$2:$A$293,MATCH(J93,$D$2:$D$293,0)),"")) | L93: =IF(E93<>"Kleine Anfrage","",IFERROR(INDEX($D$2:$D$293,MATCH(D93,$J$2:$J$293,0)),"offen")) | M93: Deutschlandticket weiterentwickeln und langfristig sichern | N93: Fraktion BÜNDNIS 90/DIE GRÜNEN | O93: PDF | R93: =IF(COUNTIF(Abstimmungen!$B$5:$B$2000,D93)-COUNTIFS(Abstimmungen!$B$5:$B$2000,D93,Abstimmungen!$D$5:$D$2000,"*berweisung*")>0,1,0)
A94: 45908 | B94: =IF(A94="","",YEAR(A94)) | C94: =IF(A94="","",YEAR(A94)&"-Q"&ROUNDUP(MONTH(A94)/3,0)) | D94: 21/1499 | E94: Gesetzentwurf | F94: Bundesregierung | G94: Regierung | H94: 21 | I94: Sonstiges | K94: =IF(OR(J94="",LEFT(E94,7)<>"Antwort"),"",IFERROR(A94-INDEX($A$2:$A$293,MATCH(J94,$D$2:$D$293,0)),"")) | L94: =IF(E94<>"Kleine Anfrage","",IFERROR(INDEX($D$2:$D$293,MATCH(D94,$J$2:$J$293,0)),"offen")) | M94: Entwurf eines Gesetzes zur Abmilderung des Trassenentgeltanstiegs bei den Eisenbahnen des Bundes | N94: Bundesregierung | O94: PDF | R94: =IF(COUNTIF(Abstimmungen!$B$5:$B$2000,D94)-COUNTIFS(Abstimmungen!$B$5:$B$2000,D94,Abstimmungen!$D$5:$D$2000,"*berweisung*")>0,1,0)
A95: 45905 | B95: =IF(A95="","",YEAR(A95)) | C95: =IF(A95="","",YEAR(A95)&"-Q"&ROUNDUP(MONTH(A95)/3,0)) | D95: 21/1512 | E95: Antwort | F95: Bundesregierung | G95: Regierung | H95: 21 | I95: Sonstiges | J95: 21/1329 | K95: =IF(OR(J95="",LEFT(E95,7)<>"Antwort"),"",IFERROR(A95-INDEX($A$2:$A$293,MATCH(J95,$D$2:$D$293,0)),"")) | L95: =IF(E95<>"Kleine Anfrage","",IFERROR(INDEX($D$2:$D$293,MATCH(D95,$J$2:$J$293,0)),"offen")) | M95: Neues Werk der Deutschen Bahn in Cottbus | N95: Bundesregierung | O95: PDF | P95: Linke | R95: =IF(COUNTIF(Abstimmungen!$B$5:$B$2000,D95)-COUNTIFS(Abstimmungen!$B$5:$B$2000,D95,Abstimmungen!$D$5:$D$2000,"*berweisung*")>0,1,0)
A96: 45905 | B96: =IF(A96="","",YEAR(A96)) | C96: =IF(A96="","",YEAR(A96)&"-Q"&ROUNDUP(MONTH(A96)/3,0)) | D96: 21/1015 | E96: Kleine Anfrage | F96: AfD | G96: Opposition | H96: 21 | I96: Puenktlichkeit/Qualitaet; Sicherheit | K96: =IF(OR(J96="",LEFT(E96,7)<>"Antwort"),"",IFERROR(A96-INDEX($A$2:$A$293,MATCH(J96,$D$2:$D$293,0)),"")) | L96: =IF(E96<>"Kleine Anfrage","",IFERROR(INDEX($D$2:$D$293,MATCH(D96,$J$2:$J$293,0)),"offen")) | M96: Störungen im Betriebsablauf bei der Deutschen Bahn AG und deren Auswirkungen auf Sicherheit und Pünktlichkeit | N96: Fraktion der AfD | O96: PDF | R96: =IF(COUNTIF(Abstimmungen!$B$5:$B$2000,D96)-COUNTIFS(Abstimmungen!$B$5:$B$2000,D96,Abstimmungen!$D$5:$D$2000,"*berweisung*")>0,1,0)
A97: 45894 | B97: =IF(A97="","",YEAR(A97)) | C97: =IF(A97="","",YEAR(A97)&"-Q"&ROUNDUP(MONTH(A97)/3,0)) | D97: 21/1342 | E97: Kleine Anfrage | F97: AfD | G97: Opposition | H97: 21 | I97: Bahnhoefe; Kriminalitaet | K97: =IF(OR(J97="",LEFT(E97,7)<>"Antwort"),"",IFERROR(A97-INDEX($A$2:$A$293,MATCH(J97,$D$2:$D$293,0)),"")) | L97: =IF(E97<>"Kleine Anfrage","",IFERROR(INDEX($D$2:$D$293,MATCH(D97,$J$2:$J$293,0)),"offen")) | M97: Kriminalitätsfelder in Bezug auf Bahnhöfe und Züge in Baden-Württemberg im ersten Halbjahr 2025 | N97: Fraktion der AfD | O97: PDF | Q97: Bahnhöfe / Kriminalitätsfelder | R97: =IF(COUNTIF(Abstimmungen!$B$5:$B$2000,D97)-COUNTIFS(Abstimmungen!$B$5:$B$2000,D97,Abstimmungen!$D$5:$D$2000,"*berweisung*")>0,1,0)
A98: 45891 | B98: =IF(A98="","",YEAR(A98)) | C98: =IF(A98="","",YEAR(A98)&"-Q"&ROUNDUP(MONTH(A98)/3,0)) | D98: 21/1329 | E98: Kleine Anfrage | F98: Linke | G98: Opposition | H98: 21 | I98: Sonstiges | K98: =IF(OR(J98="",LEFT(E98,7)<>"Antwort"),"",IFERROR(A98-INDEX($A$2:$A$293,MATCH(J98,$D$2:$D$293,0)),"")) | L98: =IF(E98<>"Kleine Anfrage","",IFERROR(INDEX($D$2:$D$293,MATCH(D98,$J$2:$J$293,0)),"offen")) | M98: Neues Werk der Deutschen Bahn in Cottbus | N98: Fraktion DIE LINKE | O98: PDF | R98: =IF(COUNTIF(Abstimmungen!$B$5:$B$2000,D98)-COUNTIFS(Abstimmungen!$B$5:$B$2000,D98,Abstimmungen!$D$5:$D$2000,"*berweisung*")>0,1,0)
A99: 45867 | B99: =IF(A99="","",YEAR(A99)) | C99: =IF(A99="","",YEAR(A99)&"-Q"&ROUNDUP(MONTH(A99)/3,0)) | D99: 21/1066 | E99: Unterrichtung | F99: Bundesnetzagentur für Elektrizität, Gas, Telekommunikation, Post und Eisenbahnen | G99: Sonstige | H99: 21 | I99: Sonstiges | K99: =IF(OR(J99="",LEFT(E99,7)<>"Antwort"),"",IFERROR(A99-INDEX($A$2:$A$293,MATCH(J99,$D$2:$D$293,0)),"")) | L99: =IF(E99<>"Kleine Anfrage","",IFERROR(INDEX($D$2:$D$293,MATCH(D99,$J$2:$J$293,0)),"offen")) | M99: Tätigkeitsbericht der Bundesnetzagentur - Eisenbahnen 2023/2024 | N99: Bundesnetzagentur für Elektrizität, Gas, Telekommunikation, Post und Eisenbahnen | O99: PDF | R99: =IF(COUNTIF(Abstimmungen!$B$5:$B$2000,D99)-COUNTIFS(Abstimmungen!$B$5:$B$2000,D99,Abstimmungen!$D$5:$D$2000,"*berweisung*")>0,1,0)
A100: 45867 | B100: =IF(A100="","",YEAR(A100)) | C100: =IF(A100="","",YEAR(A100)&"-Q"&ROUNDUP(MONTH(A100)/3,0)) | D100: 21/1095 | E100: Antwort | F100: Bundesregierung | G100: Regierung | H100: 21 | I100: Bahnhoefe; Kriminalitaet | J100: 21/884 | K100: =IF(OR(J100="",LEFT(E100,7)<>"Antwort"),"",IFERROR(A100-INDEX($A$2:$A$293,MATCH(J100,$D$2:$D$293,0)),"")) | L100: =IF(E100<>"Kleine Anfrage","",IFERROR(INDEX($D$2:$D$293,MATCH(D100,$J$2:$J$293,0)),"offen")) | M100: Kriminalitätsfelder in Bezug auf Bahnhöfe und Züge im ersten Halbjahr 2025 | N100: Bundesregierung | O100: PDF | P100: AfD | R100: =IF(COUNTIF(Abstimmungen!$B$5:$B$2000,D100)-COUNTIFS(Abstimmungen!$B$5:$B$2000,D100,Abstimmungen!$D$5:$D$2000,"*berweisung*")>0,1,0)
...

Sheet Initiativen
A1: Eigene Initiativen je Fraktion
A2: Nur selbst eingebrachte Drucksachen. Antworten der Bundesregierung und Beschlussempfehlungen der Ausschuesse sind Reaktionen und hier bewusst nicht enthalten.
A4: Fraktion | B4: Rolle ab WP 21 | C4: Kleine Anfrage | D4: Antrag | E4: Entschließungsantrag | F4: Gesetzentwurf | G4: Gesamt | H4: Anteil
A5: CDU/CSU | B5: Regierungsfraktion | C5: =COUNTIFS(Drucksachen!$F$2:$F$293,$A5,Drucksachen!$E$2:$E$293,C$4) | D5: =COUNTIFS(Drucksachen!$F$2:$F$293,$A5,Drucksachen!$E$2:$E$293,D$4) | E5: =COUNTIFS(Drucksachen!$F$2:$F$293,$A5,Drucksachen!$E$2:$E$293,E$4) | F5: =COUNTIFS(Drucksachen!$F$2:$F$293,$A5,Drucksachen!$E$2:$E$293,F$4) | G5: =SUM(C5:F5) | H5: =IFERROR(G5/G$10,0)
A6: Gruene | B6: Opposition | C6: =COUNTIFS(Drucksachen!$F$2:$F$293,$A6,Drucksachen!$E$2:$E$293,C$4) | D6: =COUNTIFS(Drucksachen!$F$2:$F$293,$A6,Drucksachen!$E$2:$E$293,D$4) | E6: =COUNTIFS(Drucksachen!$F$2:$F$293,$A6,Drucksachen!$E$2:$E$293,E$4) | F6: =COUNTIFS(Drucksachen!$F$2:$F$293,$A6,Drucksachen!$E$2:$E$293,F$4) | G6: =SUM(C6:F6) | H6: =IFERROR(G6/G$10,0)
A7: AfD | B7: Opposition | C7: =COUNTIFS(Drucksachen!$F$2:$F$293,$A7,Drucksachen!$E$2:$E$293,C$4) | D7: =COUNTIFS(Drucksachen!$F$2:$F$293,$A7,Drucksachen!$E$2:$E$293,D$4) | E7: =COUNTIFS(Drucksachen!$F$2:$F$293,$A7,Drucksachen!$E$2:$E$293,E$4) | F7: =COUNTIFS(Drucksachen!$F$2:$F$293,$A7,Drucksachen!$E$2:$E$293,F$4) | G7: =SUM(C7:F7) | H7: =IFERROR(G7/G$10,0)
A8: Linke | B8: Opposition | C8: =COUNTIFS(Drucksachen!$F$2:$F$293,$A8,Drucksachen!$E$2:$E$293,C$4) | D8: =COUNTIFS(Drucksachen!$F$2:$F$293,$A8,Drucksachen!$E$2:$E$293,D$4) | E8: =COUNTIFS(Drucksachen!$F$2:$F$293,$A8,Drucksachen!$E$2:$E$293,E$4) | F8: =COUNTIFS(Drucksachen!$F$2:$F$293,$A8,Drucksachen!$E$2:$E$293,F$4) | G8: =SUM(C8:F8) | H8: =IFERROR(G8/G$10,0)
A9: Mehrere Fraktionen | B9: Fraktionsuebergreifend | C9: =COUNTIFS(Drucksachen!$F$2:$F$293,$A9,Drucksachen!$E$2:$E$293,C$4) | D9: =COUNTIFS(Drucksachen!$F$2:$F$293,$A9,Drucksachen!$E$2:$E$293,D$4) | E9: =COUNTIFS(Drucksachen!$F$2:$F$293,$A9,Drucksachen!$E$2:$E$293,E$4) | F9: =COUNTIFS(Drucksachen!$F$2:$F$293,$A9,Drucksachen!$E$2:$E$293,F$4) | G9: =SUM(C9:F9) | H9: =IFERROR(G9/G$10,0)
A10: Gesamt | C10: =SUM(C5:C9) | D10: =SUM(D5:D9) | E10: =SUM(E5:E9) | F10: =SUM(F5:F9) | G10: =SUM(G5:G9)

Sheet Zeitverlauf
A1: Drucksachen je Quartal
A3: Quartal | B3: CDU/CSU | C3: Gruene | D3: AfD | E3: Linke | F3: Mehrere Fraktionen | G3: Bundesregierung | H3: Ausschuesse | I3: Gesamt
A4: 2021-Q4 | B4: =COUNTIFS(Drucksachen!$C$2:$C$293,$A4,Drucksachen!$F$2:$F$293,B$3) | C4: =COUNTIFS(Drucksachen!$C$2:$C$293,$A4,Drucksachen!$F$2:$F$293,C$3) | D4: =COUNTIFS(Drucksachen!$C$2:$C$293,$A4,Drucksachen!$F$2:$F$293,D$3) | E4: =COUNTIFS(Drucksachen!$C$2:$C$293,$A4,Drucksachen!$F$2:$F$293,E$3) | F4: =COUNTIFS(Drucksachen!$C$2:$C$293,$A4,Drucksachen!$F$2:$F$293,F$3) | G4: =COUNTIFS(Drucksachen!$C$2:$C$293,$A4,Drucksachen!$F$2:$F$293,"Bundesregierung") | H4: =COUNTIFS(Drucksachen!$C$2:$C$293,$A4,Drucksachen!$G$2:$G$293,"Ausschuss") | I4: =COUNTIFS(Drucksachen!$C$2:$C$293,$A4)
A5: 2022-Q1 | B5: =COUNTIFS(Drucksachen!$C$2:$C$293,$A5,Drucksachen!$F$2:$F$293,B$3) | C5: =COUNTIFS(Drucksachen!$C$2:$C$293,$A5,Drucksachen!$F$2:$F$293,C$3) | D5: =COUNTIFS(Drucksachen!$C$2:$C$293,$A5,Drucksachen!$F$2:$F$293,D$3) | E5: =COUNTIFS(Drucksachen!$C$2:$C$293,$A5,Drucksachen!$F$2:$F$293,E$3) | F5: =COUNTIFS(Drucksachen!$C$2:$C$293,$A5,Drucksachen!$F$2:$F$293,F$3) | G5: =COUNTIFS(Drucksachen!$C$2:$C$293,$A5,Drucksachen!$F$2:$F$293,"Bundesregierung") | H5: =COUNTIFS(Drucksachen!$C$2:$C$293,$A5,Drucksachen!$G$2:$G$293,"Ausschuss") | I5: =COUNTIFS(Drucksachen!$C$2:$C$293,$A5)
A6: 2022-Q2 | B6: =COUNTIFS(Drucksachen!$C$2:$C$293,$A6,Drucksachen!$F$2:$F$293,B$3) | C6: =COUNTIFS(Drucksachen!$C$2:$C$293,$A6,Drucksachen!$F$2:$F$293,C$3) | D6: =COUNTIFS(Drucksachen!$C$2:$C$293,$A6,Drucksachen!$F$2:$F$293,D$3) | E6: =COUNTIFS(Drucksachen!$C$2:$C$293,$A6,Drucksachen!$F$2:$F$293,E$3) | F6: =COUNTIFS(Drucksachen!$C$2:$C$293,$A6,Drucksachen!$F$2:$F$293,F$3) | G6: =COUNTIFS(Drucksachen!$C$2:$C$293,$A6,Drucksachen!$F$2:$F$293,"Bundesregierung") | H6: =COUNTIFS(Drucksachen!$C$2:$C$293,$A6,Drucksachen!$G$2:$G$293,"Ausschuss") | I6: =COUNTIFS(Drucksachen!$C$2:$C$293,$A6)
A7: 2022-Q3 | B7: =COUNTIFS(Drucksachen!$C$2:$C$293,$A7,Drucksachen!$F$2:$F$293,B$3) | C7: =COUNTIFS(Drucksachen!$C$2:$C$293,$A7,Drucksachen!$F$2:$F$293,C$3) | D7: =COUNTIFS(Drucksachen!$C$2:$C$293,$A7,Drucksachen!$F$2:$F$293,D$3) | E7: =COUNTIFS(Drucksachen!$C$2:$C$293,$A7,Drucksachen!$F$2:$F$293,E$3) | F7: =COUNTIFS(Drucksachen!$C$2:$C$293,$A7,Drucksachen!$F$2:$F$293,F$3) | G7: =COUNTIFS(Drucksachen!$C$2:$C$293,$A7,Drucksachen!$F$2:$F$293,"Bundesregierung") | H7: =COUNTIFS(Drucksachen!$C$2:$C$293,$A7,Drucksachen!$G$2:$G$293,"Ausschuss") | I7: =COUNTIFS(Drucksachen!$C$2:$C$293,$A7)
A8: 2022-Q4 | B8: =COUNTIFS(Drucksachen!$C$2:$C$293,$A8,Drucksachen!$F$2:$F$293,B$3) | C8: =COUNTIFS(Drucksachen!$C$2:$C$293,$A8,Drucksachen!$F$2:$F$293,C$3) | D8: =COUNTIFS(Drucksachen!$C$2:$C$293,$A8,Drucksachen!$F$2:$F$293,D$3) | E8: =COUNTIFS(Drucksachen!$C$2:$C$293,$A8,Drucksachen!$F$2:$F$293,E$3) | F8: =COUNTIFS(Drucksachen!$C$2:$C$293,$A8,Drucksachen!$F$2:$F$293,F$3) | G8: =COUNTIFS(Drucksachen!$C$2:$C$293,$A8,Drucksachen!$F$2:$F$293,"Bundesregierung") | H8: =COUNTIFS(Drucksachen!$C$2:$C$293,$A8,Drucksachen!$G$2:$G$293,"Ausschuss") | I8: =COUNTIFS(Drucksachen!$C$2:$C$293,$A8)
A9: 2023-Q1 | B9: =COUNTIFS(Drucksachen!$C$2:$C$293,$A9,Drucksachen!$F$2:$F$293,B$3) | C9: =COUNTIFS(Drucksachen!$C$2:$C$293,$A9,Drucksachen!$F$2:$F$293,C$3) | D9: =COUNTIFS(Drucksachen!$C$2:$C$293,$A9,Drucksachen!$F$2:$F$293,D$3) | E9: =COUNTIFS(Drucksachen!$C$2:$C$293,$A9,Drucksachen!$F$2:$F$293,E$3) | F9: =COUNTIFS(Drucksachen!$C$2:$C$293,$A9,Drucksachen!$F$2:$F$293,F$3) | G9: =COUNTIFS(Drucksachen!$C$2:$C$293,$A9,Drucksachen!$F$2:$F$293,"Bundesregierung") | H9: =COUNTIFS(Drucksachen!$C$2:$C$293,$A9,Drucksachen!$G$2:$G$293,"Ausschuss") | I9: =COUNTIFS(Drucksachen!$C$2:$C$293,$A9)
A10: 2023-Q2 | B10: =COUNTIFS(Drucksachen!$C$2:$C$293,$A10,Drucksachen!$F$2:$F$293,B$3) | C10: =COUNTIFS(Drucksachen!$C$2:$C$293,$A10,Drucksachen!$F$2:$F$293,C$3) | D10: =COUNTIFS(Drucksachen!$C$2:$C$293,$A10,Drucksachen!$F$2:$F$293,D$3) | E10: =COUNTIFS(Drucksachen!$C$2:$C$293,$A10,Drucksachen!$F$2:$F$293,E$3) | F10: =COUNTIFS(Drucksachen!$C$2:$C$293,$A10,Drucksachen!$F$2:$F$293,F$3) | G10: =COUNTIFS(Drucksachen!$C$2:$C$293,$A10,Drucksachen!$F$2:$F$293,"Bundesregierung") | H10: =COUNTIFS(Drucksachen!$C$2:$C$293,$A10,Drucksachen!$G$2:$G$293,"Ausschuss") | I10: =COUNTIFS(Drucksachen!$C$2:$C$293,$A10)
A11: 2023-Q3 | B11: =COUNTIFS(Drucksachen!$C$2:$C$293,$A11,Drucksachen!$F$2:$F$293,B$3) | C11: =COUNTIFS(Drucksachen!$C$2:$C$293,$A11,Drucksachen!$F$2:$F$293,C$3) | D11: =COUNTIFS(Drucksachen!$C$2:$C$293,$A11,Drucksachen!$F$2:$F$293,D$3) | E11: =COUNTIFS(Drucksachen!$C$2:$C$293,$A11,Drucksachen!$F$2:$F$293,E$3) | F11: =COUNTIFS(Drucksachen!$C$2:$C$293,$A11,Drucksachen!$F$2:$F$293,F$3) | G11: =COUNTIFS(Drucksachen!$C$2:$C$293,$A11,Drucksachen!$F$2:$F$293,"Bundesregierung") | H11: =COUNTIFS(Drucksachen!$C$2:$C$293,$A11,Drucksachen!$G$2:$G$293,"Ausschuss") | I11: =COUNTIFS(Drucksachen!$C$2:$C$293,$A11)
A12: 2023-Q4 | B12: =COUNTIFS(Drucksachen!$C$2:$C$293,$A12,Drucksachen!$F$2:$F$293,B$3) | C12: =COUNTIFS(Drucksachen!$C$2:$C$293,$A12,Drucksachen!$F$2:$F$293,C$3) | D12: =COUNTIFS(Drucksachen!$C$2:$C$293,$A12,Drucksachen!$F$2:$F$293,D$3) | E12: =COUNTIFS(Drucksachen!$C$2:$C$293,$A12,Drucksachen!$F$2:$F$293,E$3) | F12: =COUNTIFS(Drucksachen!$C$2:$C$293,$A12,Drucksachen!$F$2:$F$293,F$3) | G12: =COUNTIFS(Drucksachen!$C$2:$C$293,$A12,Drucksachen!$F$2:$F$293,"Bundesregierung") | H12: =COUNTIFS(Drucksachen!$C$2:$C$293,$A12,Drucksachen!$G$2:$G$293,"Ausschuss") | I12: =COUNTIFS(Drucksachen!$C$2:$C$293,$A12)
A13: 2024-Q1 | B13: =COUNTIFS(Drucksachen!$C$2:$C$293,$A13,Drucksachen!$F$2:$F$293,B$3) | C13: =COUNTIFS(Drucksachen!$C$2:$C$293,$A13,Drucksachen!$F$2:$F$293,C$3) | D13: =COUNTIFS(Drucksachen!$C$2:$C$293,$A13,Drucksachen!$F$2:$F$293,D$3) | E13: =COUNTIFS(Drucksachen!$C$2:$C$293,$A13,Drucksachen!$F$2:$F$293,E$3) | F13: =COUNTIFS(Drucksachen!$C$2:$C$293,$A13,Drucksachen!$F$2:$F$293,F$3) | G13: =COUNTIFS(Drucksachen!$C$2:$C$293,$A13,Drucksachen!$F$2:$F$293,"Bundesregierung") | H13: =COUNTIFS(Drucksachen!$C$2:$C$293,$A13,Drucksachen!$G$2:$G$293,"Ausschuss") | I13: =COUNTIFS(Drucksachen!$C$2:$C$293,$A13)
A14: 2024-Q2 | B14: =COUNTIFS(Drucksachen!$C$2:$C$293,$A14,Drucksachen!$F$2:$F$293,B$3) | C14: =COUNTIFS(Drucksachen!$C$2:$C$293,$A14,Drucksachen!$F$2:$F$293,C$3) | D14: =COUNTIFS(Drucksachen!$C$2:$C$293,$A14,Drucksachen!$F$2:$F$293,D$3) | E14: =COUNTIFS(Drucksachen!$C$2:$C$293,$A14,Drucksachen!$F$2:$F$293,E$3) | F14: =COUNTIFS(Drucksachen!$C$2:$C$293,$A14,Drucksachen!$F$2:$F$293,F$3) | G14: =COUNTIFS(Drucksachen!$C$2:$C$293,$A14,Drucksachen!$F$2:$F$293,"Bundesregierung") | H14: =COUNTIFS(Drucksachen!$C$2:$C$293,$A14,Drucksachen!$G$2:$G$293,"Ausschuss") | I14: =COUNTIFS(Drucksachen!$C$2:$C$293,$A14)
A15: 2024-Q3 | B15: =COUNTIFS(Drucksachen!$C$2:$C$293,$A15,Drucksachen!$F$2:$F$293,B$3) | C15: =COUNTIFS(Drucksachen!$C$2:$C$293,$A15,Drucksachen!$F$2:$F$293,C$3) | D15: =COUNTIFS(Drucksachen!$C$2:$C$293,$A15,Drucksachen!$F$2:$F$293,D$3) | E15: =COUNTIFS(Drucksachen!$C$2:$C$293,$A15,Drucksachen!$F$2:$F$293,E$3) | F15: =COUNTIFS(Drucksachen!$C$2:$C$293,$A15,Drucksachen!$F$2:$F$293,F$3) | G15: =COUNTIFS(Drucksachen!$C$2:$C$293,$A15,Drucksachen!$F$2:$F$293,"Bundesregierung") | H15: =COUNTIFS(Drucksachen!$C$2:$C$293,$A15,Drucksachen!$G$2:$G$293,"Ausschuss") | I15: =COUNTIFS(Drucksachen!$C$2:$C$293,$A15)
... A23: 2026-Q3 | B23: =COUNTIFS(Drucksachen!$C$2:$C$293,$A23,Drucksachen!$F$2:$F$293,B$3) | C23: =COUNTIFS(Drucksachen!$C$2:$C$293,$A23,Drucksachen!$F$2:$F$293,C$3) | D23: =COUNTIFS(Drucksachen!$C$2:$C$293,$A23,Drucksachen!$F$2:$F$293,D$3) | E23: =COUNTIFS(Drucksachen!$C$2:$C$293,$A23,Drucksachen!$F$2:$F$293,E$3) | F23: =COUNTIFS(Drucksachen!$C$2:$C$293,$A23,Drucksachen!$F$2:$F$293,F$3) | G23: =COUNTIFS(Drucksachen!$C$2:$C$293,$A23,Drucksachen!$F$2:$F$293,"Bundesregierung") | H23: =COUNTIFS(Drucksachen!$C$2:$C$293,$A23,Drucksachen!$G$2:$G$293,"Ausschuss") | I23: =COUNTIFS(Drucksachen!$C$2:$C$293,$A23)

Sheet Themen
A1: Themen im Zeitverlauf
A2: Mehrfachnennung moeglich: eine Drucksache kann mehreren Themen zugeordnet sein, die Spaltensummen uebersteigen daher die Zahl der Drucksachen.
A4: Thema | B4: 2021 | C4: 2022 | D4: 2023 | E4: 2024 | F4: 2025 | G4: 2026 | H4: Gesamt | I4: davon Opposition | K4: Hilfsbereich Initiativtypen
A5: Bahnhoefe | B5: =SUMPRODUCT(ISNUMBER(SEARCH($A5,Drucksachen!$I$2:$I$293))*(Drucksachen!$B$2:$B$293=B$4)) | C5: =SUMPRODUCT(ISNUMBER(SEARCH($A5,Drucksachen!$I$2:$I$293))*(Drucksachen!$B$2:$B$293=C$4)) | D5: =SUMPRODUCT(ISNUMBER(SEARCH($A5,Drucksachen!$I$2:$I$293))*(Drucksachen!$B$2:$B$293=D$4)) | E5: =SUMPRODUCT(ISNUMBER(SEARCH($A5,Drucksachen!$I$2:$I$293))*(Drucksachen!$B$2:$B$293=E$4)) | F5: =SUMPRODUCT(ISNUMBER(SEARCH($A5,Drucksachen!$I$2:$I$293))*(Drucksachen!$B$2:$B$293=F$4)) | G5: =SUMPRODUCT(ISNUMBER(SEARCH($A5,Drucksachen!$I$2:$I$293))*(Drucksachen!$B$2:$B$293=G$4)) | H5: =SUM(B5:G5) | I5: =SUMPRODUCT(ISNUMBER(SEARCH($A5,Drucksachen!$I$2:$I$293))*(Drucksachen!$G$2:$G$293="Opposition")) | K5: Kleine Anfrage
A6: Kriminalitaet | B6: =SUMPRODUCT(ISNUMBER(SEARCH($A6,Drucksachen!$I$2:$I$293))*(Drucksachen!$B$2:$B$293=B$4)) | C6: =SUMPRODUCT(ISNUMBER(SEARCH($A6,Drucksachen!$I$2:$I$293))*(Drucksachen!$B$2:$B$293=C$4)) | D6: =SUMPRODUCT(ISNUMBER(SEARCH($A6,Drucksachen!$I$2:$I$293))*(Drucksachen!$B$2:$B$293=D$4)) | E6: =SUMPRODUCT(ISNUMBER(SEARCH($A6,Drucksachen!$I$2:$I$293))*(Drucksachen!$B$2:$B$293=E$4)) | F6: =SUMPRODUCT(ISNUMBER(SEARCH($A6,Drucksachen!$I$2:$I$293))*(Drucksachen!$B$2:$B$293=F$4)) | G6: =SUMPRODUCT(ISNUMBER(SEARCH($A6,Drucksachen!$I$2:$I$293))*(Drucksachen!$B$2:$B$293=G$4)) | H6: =SUM(B6:G6) | I6: =SUMPRODUCT(ISNUMBER(SEARCH($A6,Drucksachen!$I$2:$I$293))*(Drucksachen!$G$2:$G$293="Opposition")) | K6: Antrag
A7: Sonstiges | B7: =SUMPRODUCT(ISNUMBER(SEARCH($A7,Drucksachen!$I$2:$I$293))*(Drucksachen!$B$2:$B$293=B$4)) | C7: =SUMPRODUCT(ISNUMBER(SEARCH($A7,Drucksachen!$I$2:$I$293))*(Drucksachen!$B$2:$B$293=C$4)) | D7: =SUMPRODUCT(ISNUMBER(SEARCH($A7,Drucksachen!$I$2:$I$293))*(Drucksachen!$B$2:$B$293=D$4)) | E7: =SUMPRODUCT(ISNUMBER(SEARCH($A7,Drucksachen!$I$2:$I$293))*(Drucksachen!$B$2:$B$293=E$4)) | F7: =SUMPRODUCT(ISNUMBER(SEARCH($A7,Drucksachen!$I$2:$I$293))*(Drucksachen!$B$2:$B$293=F$4)) | G7: =SUMPRODUCT(ISNUMBER(SEARCH($A7,Drucksachen!$I$2:$I$293))*(Drucksachen!$B$2:$B$293=G$4)) | H7: =SUM(B7:G7) | I7: =SUMPRODUCT(ISNUMBER(SEARCH($A7,Drucksachen!$I$2:$I$293))*(Drucksachen!$G$2:$G$293="Opposition")) | K7: Entschließungsantrag
A8: Infrastruktur/Netz | B8: =SUMPRODUCT(ISNUMBER(SEARCH($A8,Drucksachen!$I$2:$I$293))*(Drucksachen!$B$2:$B$293=B$4)) | C8: =SUMPRODUCT(ISNUMBER(SEARCH($A8,Drucksachen!$I$2:$I$293))*(Drucksachen!$B$2:$B$293=C$4)) | D8: =SUMPRODUCT(ISNUMBER(SEARCH($A8,Drucksachen!$I$2:$I$293))*(Drucksachen!$B$2:$B$293=D$4)) | E8: =SUMPRODUCT(ISNUMBER(SEARCH($A8,Drucksachen!$I$2:$I$293))*(Drucksachen!$B$2:$B$293=E$4)) | F8: =SUMPRODUCT(ISNUMBER(SEARCH($A8,Drucksachen!$I$2:$I$293))*(Drucksachen!$B$2:$B$293=F$4)) | G8: =SUMPRODUCT(ISNUMBER(SEARCH($A8,Drucksachen!$I$2:$I$293))*(Drucksachen!$B$2:$B$293=G$4)) | H8: =SUM(B8:G8) | I8: =SUMPRODUCT(ISNUMBER(SEARCH($A8,Drucksachen!$I$2:$I$293))*(Drucksachen!$G$2:$G$293="Opposition")) | K8: Gesetzentwurf
A9: Konzernstruktur/DB AG | B9: =SUMPRODUCT(ISNUMBER(SEARCH($A9,Drucksachen!$I$2:$I$293))*(Drucksachen!$B$2:$B$293=B$4)) | C9: =SUMPRODUCT(ISNUMBER(SEARCH($A9,Drucksachen!$I$2:$I$293))*(Drucksachen!$B$2:$B$293=C$4)) | D9: =SUMPRODUCT(ISNUMBER(SEARCH($A9,Drucksachen!$I$2:$I$293))*(Drucksachen!$B$2:$B$293=D$4)) | E9: =SUMPRODUCT(ISNUMBER(SEARCH($A9,Drucksachen!$I$2:$I$293))*(Drucksachen!$B$2:$B$293=E$4)) | F9: =SUMPRODUCT(ISNUMBER(SEARCH($A9,Drucksachen!$I$2:$I$293))*(Drucksachen!$B$2:$B$293=F$4)) | G9: =SUMPRODUCT(ISNUMBER(SEARCH($A9,Drucksachen!$I$2:$I$293))*(Drucksachen!$B$2:$B$293=G$4)) | H9: =SUM(B9:G9) | I9: =SUMPRODUCT(ISNUMBER(SEARCH($A9,Drucksachen!$I$2:$I$293))*(Drucksachen!$G$2:$G$293="Opposition"))
A10: Sicherheit | B10: =SUMPRODUCT(ISNUMBER(SEARCH($A10,Drucksachen!$I$2:$I$293))*(Drucksachen!$B$2:$B$293=B$4)) | C10: =SUMPRODUCT(ISNUMBER(SEARCH($A10,Drucksachen!$I$2:$I$293))*(Drucksachen!$B$2:$B$293=C$4)) | D10: =SUMPRODUCT(ISNUMBER(SEARCH($A10,Drucksachen!$I$2:$I$293))*(Drucksachen!$B$2:$B$293=D$4)) | E10: =SUMPRODUCT(ISNUMBER(SEARCH($A10,Drucksachen!$I$2:$I$293))*(Drucksachen!$B$2:$B$293=E$4)) | F10: =SUMPRODUCT(ISNUMBER(SEARCH($A10,Drucksachen!$I$2:$I$293))*(Drucksachen!$B$2:$B$293=F$4)) | G10: =SUMPRODUCT(ISNUMBER(SEARCH($A10,Drucksachen!$I$2:$I$293))*(Drucksachen!$B$2:$B$293=G$4)) | H10: =SUM(B10:G10) | I10: =SUMPRODUCT(ISNUMBER(SEARCH($A10,Drucksachen!$I$2:$I$293))*(Drucksachen!$G$2:$G$293="Opposition"))
A11: Finanzierung | B11: =SUMPRODUCT(ISNUMBER(SEARCH($A11,Drucksachen!$I$2:$I$293))*(Drucksachen!$B$2:$B$293=B$4)) | C11: =SUMPRODUCT(ISNUMBER(SEARCH($A11,Drucksachen!$I$2:$I$293))*(Drucksachen!$B$2:$B$293=C$4)) | D11: =SUMPRODUCT(ISNUMBER(SEARCH($A11,Drucksachen!$I$2:$I$293))*(Drucksachen!$B$2:$B$293=D$4)) | E11: =SUMPRODUCT(ISNUMBER(SEARCH($A11,Drucksachen!$I$2:$I$293))*(Drucksachen!$B$2:$B$293=E$4)) | F11: =SUMPRODUCT(ISNUMBER(SEARCH($A11,Drucksachen!$I$2:$I$293))*(Drucksachen!$B$2:$B$293=F$4)) | G11: =SUMPRODUCT(ISNUMBER(SEARCH($A11,Drucksachen!$I$2:$I$293))*(Drucksachen!$B$2:$B$293=G$4)) | H11: =SUM(B11:G11) | I11: =SUMPRODUCT(ISNUMBER(SEARCH($A11,Drucksachen!$I$2:$I$293))*(Drucksachen!$G$2:$G$293="Opposition"))
A12: Puenktlichkeit/Qualitaet | B12: =SUMPRODUCT(ISNUMBER(SEARCH($A12,Drucksachen!$I$2:$I$293))*(Drucksachen!$B$2:$B$293=B$4)) | C12: =SUMPRODUCT(ISNUMBER(SEARCH($A12,Drucksachen!$I$2:$I$293))*(Drucksachen!$B$2:$B$293=C$4)) | D12: =SUMPRODUCT(ISNUMBER(SEARCH($A12,Drucksachen!$I$2:$I$293))*(Drucksachen!$B$2:$B$293=D$4)) | E12: =SUMPRODUCT(ISNUMBER(SEARCH($A12,Drucksachen!$I$2:$I$293))*(Drucksachen!$B$2:$B$293=E$4)) | F12: =SUMPRODUCT(ISNUMBER(SEARCH($A12,Drucksachen!$I$2:$I$293))*(Drucksachen!$B$2:$B$293=F$4)) | G12: =SUMPRODUCT(ISNUMBER(SEARCH($A12,Drucksachen!$I$2:$I$293))*(Drucksachen!$B$2:$B$293=G$4)) | H12: =SUM(B12:G12) | I12: =SUMPRODUCT(ISNUMBER(SEARCH($A12,Drucksachen!$I$2:$I$293))*(Drucksachen!$G$2:$G$293="Opposition"))
A13: Barrierefreiheit | B13: =SUMPRODUCT(ISNUMBER(SEARCH($A13,Drucksachen!$I$2:$I$293))*(Drucksachen!$B$2:$B$293=B$4)) | C13: =SUMPRODUCT(ISNUMBER(SEARCH($A13,Drucksachen!$I$2:$I$293))*(Drucksachen!$B$2:$B$293=C$4)) | D13: =SUMPRODUCT(ISNUMBER(SEARCH($A13,Drucksachen!$I$2:$I$293))*(Drucksachen!$B$2:$B$293=D$4)) | E13: =SUMPRODUCT(ISNUMBER(SEARCH($A13,Drucksachen!$I$2:$I$293))*(Drucksachen!$B$2:$B$293=E$4)) | F13: =SUMPRODUCT(ISNUMBER(SEARCH($A13,Drucksachen!$I$2:$I$293))*(Drucksachen!$B$2:$B$293=F$4)) | G13: =SUMPRODUCT(ISNUMBER(SEARCH($A13,Drucksachen!$I$2:$I$293))*(Drucksachen!$B$2:$B$293=G$4)) | H13: =SUM(B13:G13) | I13: =SUMPRODUCT(ISNUMBER(SEARCH($A13,Drucksachen!$I$2:$I$293))*(Drucksachen!$G$2:$G$293="Opposition"))
A14: Deutschlandticket | B14: =SUMPRODUCT(ISNUMBER(SEARCH($A14,Drucksachen!$I$2:$I$293))*(Drucksachen!$B$2:$B$293=B$4)) | C14: =SUMPRODUCT(ISNUMBER(SEARCH($A14,Drucksachen!$I$2:$I$293))*(Drucksachen!$B$2:$B$293=C$4)) | D14: =SUMPRODUCT(ISNUMBER(SEARCH($A14,Drucksachen!$I$2:$I$293))*(Drucksachen!$B$2:$B$293=D$4)) | E14: =SUMPRODUCT(ISNUMBER(SEARCH($A14,Drucksachen!$I$2:$I$293))*(Drucksachen!$B$2:$B$293=E$4)) | F14: =SUMPRODUCT(ISNUMBER(SEARCH($A14,Drucksachen!$I$2:$I$293))*(Drucksachen!$B$2:$B$293=F$4)) | G14: =SUMPRODUCT(ISNUMBER(SEARCH($A14,Drucksachen!$I$2:$I$293))*(Drucksachen!$B$2:$B$293=G$4)) | H14: =SUM(B14:G14) | I14: =SUMPRODUCT(ISNUMBER(SEARCH($A14,Drucksachen!$I$2:$I$293))*(Drucksachen!$G$2:$G$293="Opposition"))
A15: Nahverkehr/SPNV | B15: =SUMPRODUCT(ISNUMBER(SEARCH($A15,Drucksachen!$I$2:$I$293))*(Drucksachen!$B$2:$B$293=B$4)) | C15: =SUMPRODUCT(ISNUMBER(SEARCH($A15,Drucksachen!$I$2:$I$293))*(Drucksachen!$B$2:$B$293=C$4)) | D15: =SUMPRODUCT(ISNUMBER(SEARCH($A15,Drucksachen!$I$2:$I$293))*(Drucksachen!$B$2:$B$293=D$4)) | E15: =SUMPRODUCT(ISNUMBER(SEARCH($A15,Drucksachen!$I$2:$I$293))*(Drucksachen!$B$2:$B$293=E$4)) | F15: =SUMPRODUCT(ISNUMBER(SEARCH($A15,Drucksachen!$I$2:$I$293))*(Drucksachen!$B$2:$B$293=F$4)) | G15: =SUMPRODUCT(ISNUMBER(SEARCH($A15,Drucksachen!$I$2:$I$293))*(Drucksachen!$B$2:$B$293=G$4)) | H15: =SUM(B15:G15) | I15: =SUMPRODUCT(ISNUMBER(SEARCH($A15,Drucksachen!$I$2:$I$293))*(Drucksachen!$G$2:$G$293="Opposition"))
A16: Deutschlandtakt/Fahrplan | B16: =SUMPRODUCT(ISNUMBER(SEARCH($A16,Drucksachen!$I$2:$I$293))*(Drucksachen!$B$2:$B$293=B$4)) | C16: =SUMPRODUCT(ISNUMBER(SEARCH($A16,Drucksachen!$I$2:$I$293))*(Drucksachen!$B$2:$B$293=C$4)) | D16: =SUMPRODUCT(ISNUMBER(SEARCH($A16,Drucksachen!$I$2:$I$293))*(Drucksachen!$B$2:$B$293=D$4)) | E16: =SUMPRODUCT(ISNUMBER(SEARCH($A16,Drucksachen!$I$2:$I$293))*(Drucksachen!$B$2:$B$293=E$4)) | F16: =SUMPRODUCT(ISNUMBER(SEARCH($A16,Drucksachen!$I$2:$I$293))*(Drucksachen!$B$2:$B$293=F$4)) | G16: =SUMPRODUCT(ISNUMBER(SEARCH($A16,Drucksachen!$I$2:$I$293))*(Drucksachen!$B$2:$B$293=G$4)) | H16: =SUM(B16:G16) | I16: =SUMPRODUCT(ISNUMBER(SEARCH($A16,Drucksachen!$I$2:$I$293))*(Drucksachen!$G$2:$G$293="Opposition"))
A17: Personal | B17: =SUMPRODUCT(ISNUMBER(SEARCH($A17,Drucksachen!$I$2:$I$293))*(Drucksachen!$B$2:$B$293=B$4)) | C17: =SUMPRODUCT(ISNUMBER(SEARCH($A17,Drucksachen!$I$2:$I$293))*(Drucksachen!$B$2:$B$293=C$4)) | D17: =SUMPRODUCT(ISNUMBER(SEARCH($A17,Drucksachen!$I$2:$I$293))*(Drucksachen!$B$2:$B$293=D$4)) | E17: =SUMPRODUCT(ISNUMBER(SEARCH($A17,Drucksachen!$I$2:$I$293))*(Drucksachen!$B$2:$B$293=E$4)) | F17: =SUMPRODUCT(ISNUMBER(SEARCH($A17,Drucksachen!$I$2:$I$293))*(Drucksachen!$B$2:$B$293=F$4)) | G17: =SUMPRODUCT(ISNUMBER(SEARCH($A17,Drucksachen!$I$2:$I$293))*(Drucksachen!$B$2:$B$293=G$4)) | H17: =SUM(B17:G17) | I17: =SUMPRODUCT(ISNUMBER(SEARCH($A17,Drucksachen!$I$2:$I$293))*(Drucksachen!$G$2:$G$293="Opposition"))
A18: Gueterverkehr | B18: =SUMPRODUCT(ISNUMBER(SEARCH($A18,Drucksachen!$I$2:$I$293))*(Drucksachen!$B$2:$B$293=B$4)) | C18: =SUMPRODUCT(ISNUMBER(SEARCH($A18,Drucksachen!$I$2:$I$293))*(Drucksachen!$B$2:$B$293=C$4)) | D18: =SUMPRODUCT(ISNUMBER(SEARCH($A18,Drucksachen!$I$2:$I$293))*(Drucksachen!$B$2:$B$293=D$4)) | E18: =SUMPRODUCT(ISNUMBER(SEARCH($A18,Drucksachen!$I$2:$I$293))*(Drucksachen!$B$2:$B$293=E$4)) | F18: =SUMPRODUCT(ISNUMBER(SEARCH($A18,Drucksachen!$I$2:$I$293))*(Drucksachen!$B$2:$B$293=F$4)) | G18: =SUMPRODUCT(ISNUMBER(SEARCH($A18,Drucksachen!$I$2:$I$293))*(Drucksachen!$B$2:$B$293=G$4)) | H18: =SUM(B18:G18) | I18: =SUMPRODUCT(ISNUMBER(SEARCH($A18,Drucksachen!$I$2:$I$293))*(Drucksachen!$G$2:$G$293="Opposition"))
A21: Welche Fraktion bringt welches Thema ein
A22: Nur eigene Initiativen: Kleine Anfrage, Antrag, Entschließungsantrag, Gesetzentwurf. Antworten der Bundesregierung und Beschlussempfehlungen der Ausschuesse bleiben aussen vor, sie haben keinen politischen Urheber. Mehrfachnennung moeglich, eine Drucksache kann mehrere Themen tragen. Die Spalte Schwerpunkt nennt bei Gleichstand die in der Kopfzeile zuerst stehende Fraktion.
A24: Thema | B24: CDU/CSU | C24: Gruene | D24: AfD | E24: Linke | F24: Mehrere Fraktionen | G24: Initiativen gesamt | H24: Schwerpunkt bei
A25: Bahnhoefe | B25: =SUMPRODUCT(ISNUMBER(SEARCH($A25,Drucksachen!$I$2:$I$293))*(Drucksachen!$F$2:$F$293=B$24)*(COUNTIF(Themen!$K$5:$K$8,Drucksachen!$E$2:$E$293)>0)) | C25: =SUMPRODUCT(ISNUMBER(SEARCH($A25,Drucksachen!$I$2:$I$293))*(Drucksachen!$F$2:$F$293=C$24)*(COUNTIF(Themen!$K$5:$K$8,Drucksachen!$E$2:$E$293)>0)) | D25: =SUMPRODUCT(ISNUMBER(SEARCH($A25,Drucksachen!$I$2:$I$293))*(Drucksachen!$F$2:$F$293=D$24)*(COUNTIF(Themen!$K$5:$K$8,Drucksachen!$E$2:$E$293)>0)) | E25: =SUMPRODUCT(ISNUMBER(SEARCH($A25,Drucksachen!$I$2:$I$293))*(Drucksachen!$F$2:$F$293=E$24)*(COUNTIF(Themen!$K$5:$K$8,Drucksachen!$E$2:$E$293)>0)) | F25: =SUMPRODUCT(ISNUMBER(SEARCH($A25,Drucksachen!$I$2:$I$293))*(Drucksachen!$F$2:$F$293=F$24)*(COUNTIF(Themen!$K$5:$K$8,Drucksachen!$E$2:$E$293)>0)) | G25: =SUM(B25:F25) | H25: =IF(G25=0,"",INDEX($B$24:$F$24,MATCH(MAX(B25:F25),B25:F25,0)))
A26: Kriminalitaet | B26: =SUMPRODUCT(ISNUMBER(SEARCH($A26,Drucksachen!$I$2:$I$293))*(Drucksachen!$F$2:$F$293=B$24)*(COUNTIF(Themen!$K$5:$K$8,Drucksachen!$E$2:$E$293)>0)) | C26: =SUMPRODUCT(ISNUMBER(SEARCH($A26,Drucksachen!$I$2:$I$293))*(Drucksachen!$F$2:$F$293=C$24)*(COUNTIF(Themen!$K$5:$K$8,Drucksachen!$E$2:$E$293)>0)) | D26: =SUMPRODUCT(ISNUMBER(SEARCH($A26,Drucksachen!$I$2:$I$293))*(Drucksachen!$F$2:$F$293=D$24)*(COUNTIF(Themen!$K$5:$K$8,Drucksachen!$E$2:$E$293)>0)) | E26: =SUMPRODUCT(ISNUMBER(SEARCH($A26,Drucksachen!$I$2:$I$293))*(Drucksachen!$F$2:$F$293=E$24)*(COUNTIF(Themen!$K$5:$K$8,Drucksachen!$E$2:$E$293)>0)) | F26: =SUMPRODUCT(ISNUMBER(SEARCH($A26,Drucksachen!$I$2:$I$293))*(Drucksachen!$F$2:$F$293=F$24)*(COUNTIF(Themen!$K$5:$K$8,Drucksachen!$E$2:$E$293)>0)) | G26: =SUM(B26:F26) | H26: =IF(G26=0,"",INDEX($B$24:$F$24,MATCH(MAX(B26:F26),B26:F26,0)))
A27: Sonstiges | B27: =SUMPRODUCT(ISNUMBER(SEARCH($A27,Drucksachen!$I$2:$I$293))*(Drucksachen!$F$2:$F$293=B$24)*(COUNTIF(Themen!$K$5:$K$8,Drucksachen!$E$2:$E$293)>0)) | C27: =SUMPRODUCT(ISNUMBER(SEARCH($A27,Drucksachen!$I$2:$I$293))*(Drucksachen!$F$2:$F$293=C$24)*(COUNTIF(Themen!$K$5:$K$8,Drucksachen!$E$2:$E$293)>0)) | D27: =SUMPRODUCT(ISNUMBER(SEARCH($A27,Drucksachen!$I$2:$I$293))*(Drucksachen!$F$2:$F$293=D$24)*(COUNTIF(Themen!$K$5:$K$8,Drucksachen!$E$2:$E$293)>0)) | E27: =SUMPRODUCT(ISNUMBER(SEARCH($A27,Drucksachen!$I$2:$I$293))*(Drucksachen!$F$2:$F$293=E$24)*(COUNTIF(Themen!$K$5:$K$8,Drucksachen!$E$2:$E$293)>0)) | F27: =SUMPRODUCT(ISNUMBER(SEARCH($A27,Drucksachen!$I$2:$I$293))*(Drucksachen!$F$2:$F$293=F$24)*(COUNTIF(Themen!$K$5:$K$8,Drucksachen!$E$2:$E$293)>0)) | G27: =SUM(B27:F27) | H27: =IF(G27=0,"",INDEX($B$24:$F$24,MATCH(MAX(B27:F27),B27:F27,0)))
A28: Infrastruktur/Netz | B28: =SUMPRODUCT(ISNUMBER(SEARCH($A28,Drucksachen!$I$2:$I$293))*(Drucksachen!$F$2:$F$293=B$24)*(COUNTIF(Themen!$K$5:$K$8,Drucksachen!$E$2:$E$293)>0)) | C28: =SUMPRODUCT(ISNUMBER(SEARCH($A28,Drucksachen!$I$2:$I$293))*(Drucksachen!$F$2:$F$293=C$24)*(COUNTIF(Themen!$K$5:$K$8,Drucksachen!$E$2:$E$293)>0)) | D28: =SUMPRODUCT(ISNUMBER(SEARCH($A28,Drucksachen!$I$2:$I$293))*(Drucksachen!$F$2:$F$293=D$24)*(COUNTIF(Themen!$K$5:$K$8,Drucksachen!$E$2:$E$293)>0)) | E28: =SUMPRODUCT(ISNUMBER(SEARCH($A28,Drucksachen!$I$2:$I$293))*(Drucksachen!$F$2:$F$293=E$24)*(COUNTIF(Themen!$K$5:$K$8,Drucksachen!$E$2:$E$293)>0)) | F28: =SUMPRODUCT(ISNUMBER(SEARCH($A28,Drucksachen!$I$2:$I$293))*(Drucksachen!$F$2:$F$293=F$24)*(COUNTIF(Themen!$K$5:$K$8,Drucksachen!$E$2:$E$293)>0)) | G28: =SUM(B28:F28) | H28: =IF(G28=0,"",INDEX($B$24:$F$24,MATCH(MAX(B28:F28),B28:F28,0)))
A29: Konzernstruktur/DB AG | B29: =SUMPRODUCT(ISNUMBER(SEARCH($A29,Drucksachen!$I$2:$I$293))*(Drucksachen!$F$2:$F$293=B$24)*(COUNTIF(Themen!$K$5:$K$8,Drucksachen!$E$2:$E$293)>0)) | C29: =SUMPRODUCT(ISNUMBER(SEARCH($A29,Drucksachen!$I$2:$I$293))*(Drucksachen!$F$2:$F$293=C$24)*(COUNTIF(Themen!$K$5:$K$8,Drucksachen!$E$2:$E$293)>0)) | D29: =SUMPRODUCT(ISNUMBER(SEARCH($A29,Drucksachen!$I$2:$I$293))*(Drucksachen!$F$2:$F$293=D$24)*(COUNTIF(Themen!$K$5:$K$8,Drucksachen!$E$2:$E$293)>0)) | E29: =SUMPRODUCT(ISNUMBER(SEARCH($A29,Drucksachen!$I$2:$I$293))*(Drucksachen!$F$2:$F$293=E$24)*(COUNTIF(Themen!$K$5:$K$8,Drucksachen!$E$2:$E$293)>0)) | F29: =SUMPRODUCT(ISNUMBER(SEARCH($A29,Drucksachen!$I$2:$I$293))*(Drucksachen!$F$2:$F$293=F$24)*(COUNTIF(Themen!$K$5:$K$8,Drucksachen!$E$2:$E$293)>0)) | G29: =SUM(B29:F29) | H29: =IF(G29=0,"",INDEX($B$24:$F$24,MATCH(MAX(B29:F29),B29:F29,0)))
A30: Sicherheit | B30: =SUMPRODUCT(ISNUMBER(SEARCH($A30,Drucksachen!$I$2:$I$293))*(Drucksachen!$F$2:$F$293=B$24)*(COUNTIF(Themen!$K$5:$K$8,Drucksachen!$E$2:$E$293)>0)) | C30: =SUMPRODUCT(ISNUMBER(SEARCH($A30,Drucksachen!$I$2:$I$293))*(Drucksachen!$F$2:$F$293=C$24)*(COUNTIF(Themen!$K$5:$K$8,Drucksachen!$E$2:$E$293)>0)) | D30: =SUMPRODUCT(ISNUMBER(SEARCH($A30,Drucksachen!$I$2:$I$293))*(Drucksachen!$F$2:$F$293=D$24)*(COUNTIF(Themen!$K$5:$K$8,Drucksachen!$E$2:$E$293)>0)) | E30: =SUMPRODUCT(ISNUMBER(SEARCH($A30,Drucksachen!$I$2:$I$293))*(Drucksachen!$F$2:$F$293=E$24)*(COUNTIF(Themen!$K$5:$K$8,Drucksachen!$E$2:$E$293)>0)) | F30: =SUMPRODUCT(ISNUMBER(SEARCH($A30,Drucksachen!$I$2:$I$293))*(Drucksachen!$F$2:$F$293=F$24)*(COUNTIF(Themen!$K$5:$K$8,Drucksachen!$E$2:$E$293)>0)) | G30: =SUM(B30:F30) | H30: =IF(G30=0,"",INDEX($B$24:$F$24,MATCH(MAX(B30:F30),B30:F30,0)))
A31: Finanzierung | B31: =SUMPRODUCT(ISNUMBER(SEARCH($A31,Drucksachen!$I$2:$I$293))*(Drucksachen!$F$2:$F$293=B$24)*(COUNTIF(Themen!$K$5:$K$8,Drucksachen!$E$2:$E$293)>0)) | C31: =SUMPRODUCT(ISNUMBER(SEARCH($A31,Drucksachen!$I$2:$I$293))*(Drucksachen!$F$2:$F$293=C$24)*(COUNTIF(Themen!$K$5:$K$8,Drucksachen!$E$2:$E$293)>0)) | D31: =SUMPRODUCT(ISNUMBER(SEARCH($A31,Drucksachen!$I$2:$I$293))*(Drucksachen!$F$2:$F$293=D$24)*(COUNTIF(Themen!$K$5:$K$8,Drucksachen!$E$2:$E$293)>0)) | E31: =SUMPRODUCT(ISNUMBER(SEARCH($A31,Drucksachen!$I$2:$I$293))*(Drucksachen!$F$2:$F$293=E$24)*(COUNTIF(Themen!$K$5:$K$8,Drucksachen!$E$2:$E$293)>0)) | F31: =SUMPRODUCT(ISNUMBER(SEARCH($A31,Drucksachen!$I$2:$I$293))*(Drucksachen!$F$2:$F$293=F$24)*(COUNTIF(Themen!$K$5:$K$8,Drucksachen!$E$2:$E$293)>0)) | G31: =SUM(B31:F31) | H31: =IF(G31=0,"",INDEX($B$24:$F$24,MATCH(MAX(B31:F31),B31:F31,0)))
A32: Puenktlichkeit/Qualitaet | B32: =SUMPRODUCT(ISNUMBER(SEARCH($A32,Drucksachen!$I$2:$I$293))*(Drucksachen!$F$2:$F$293=B$24)*(COUNTIF(Themen!$K$5:$K$8,Drucksachen!$E$2:$E$293)>0)) | C32: =SUMPRODUCT(ISNUMBER(SEARCH($A32,Drucksachen!$I$2:$I$293))*(Drucksachen!$F$2:$F$293=C$24)*(COUNTIF(Themen!$K$5:$K$8,Drucksachen!$E$2:$E$293)>0)) | D32: =SUMPRODUCT(ISNUMBER(SEARCH($A32,Drucksachen!$I$2:$I$293))*(Drucksachen!$F$2:$F$293=D$24)*(COUNTIF(Themen!$K$5:$K$8,Drucksachen!$E$2:$E$293)>0)) | E32: =SUMPRODUCT(ISNUMBER(SEARCH($A32,Drucksachen!$I$2:$I$293))*(Drucksachen!$F$2:$F$293=E$24)*(COUNTIF(Themen!$K$5:$K$8,Drucksachen!$E$2:$E$293)>0)) | F32: =SUMPRODUCT(ISNUMBER(SEARCH($A32,Drucksachen!$I$2:$I$293))*(Drucksachen!$F$2:$F$293=F$24)*(COUNTIF(Themen!$K$5:$K$8,Drucksachen!$E$2:$E$293)>0)) | G32: =SUM(B32:F32) | H32: =IF(G32=0,"",INDEX($B$24:$F$24,MATCH(MAX(B32:F32),B32:F32,0)))
A33: Barrierefreiheit | B33: =SUMPRODUCT(ISNUMBER(SEARCH($A33,Drucksachen!$I$2:$I$293))*(Drucksachen!$F$2:$F$293=B$24)*(COUNTIF(Themen!$K$5:$K$8,Drucksachen!$E$2:$E$293)>0)) | C33: =SUMPRODUCT(ISNUMBER(SEARCH($A33,Drucksachen!$I$2:$I$293))*(Drucksachen!$F$2:$F$293=C$24)*(COUNTIF(Themen!$K$5:$K$8,Drucksachen!$E$2:$E$293)>0)) | D33: =SUMPRODUCT(ISNUMBER(SEARCH($A33,Drucksachen!$I$2:$I$293))*(Drucksachen!$F$2:$F$293=D$24)*(COUNTIF(Themen!$K$5:$K$8,Drucksachen!$E$2:$E$293)>0)) | E33: =SUMPRODUCT(ISNUMBER(SEARCH($A33,Drucksachen!$I$2:$I$293))*(Drucksachen!$F$2:$F$293=E$24)*(COUNTIF(Themen!$K$5:$K$8,Drucksachen!$E$2:$E$293)>0)) | F33: =SUMPRODUCT(ISNUMBER(SEARCH($A33,Drucksachen!$I$2:$I$293))*(Drucksachen!$F$2:$F$293=F$24)*(COUNTIF(Themen!$K$5:$K$8,Drucksachen!$E$2:$E$293)>0)) | G33: =SUM(B33:F33) | H33: =IF(G33=0,"",INDEX($B$24:$F$24,MATCH(MAX(B33:F33),B33:F33,0)))
A34: Deutschlandticket | B34: =SUMPRODUCT(ISNUMBER(SEARCH($A34,Drucksachen!$I$2:$I$293))*(Drucksachen!$F$2:$F$293=B$24)*(COUNTIF(Themen!$K$5:$K$8,Drucksachen!$E$2:$E$293)>0)) | C34: =SUMPRODUCT(ISNUMBER(SEARCH($A34,Drucksachen!$I$2:$I$293))*(Drucksachen!$F$2:$F$293=C$24)*(COUNTIF(Themen!$K$5:$K$8,Drucksachen!$E$2:$E$293)>0)) | D34: =SUMPRODUCT(ISNUMBER(SEARCH($A34,Drucksachen!$I$2:$I$293))*(Drucksachen!$F$2:$F$293=D$24)*(COUNTIF(Themen!$K$5:$K$8,Drucksachen!$E$2:$E$293)>0)) | E34: =SUMPRODUCT(ISNUMBER(SEARCH($A34,Drucksachen!$I$2:$I$293))*(Drucksachen!$F$2:$F$293=E$24)*(COUNTIF(Themen!$K$5:$K$8,Drucksachen!$E$2:$E$293)>0)) | F34: =SUMPRODUCT(ISNUMBER(SEARCH($A34,Drucksachen!$I$2:$I$293))*(Drucksachen!$F$2:$F$293=F$24)*(COUNTIF(Themen!$K$5:$K$8,Drucksachen!$E$2:$E$293)>0)) | G34: =SUM(B34:F34) | H34: =IF(G34=0,"",INDEX($B$24:$F$24,MATCH(MAX(B34:F34),B34:F34,0)))
A35: Nahverkehr/SPNV | B35: =SUMPRODUCT(ISNUMBER(SEARCH($A35,Drucksachen!$I$2:$I$293))*(Drucksachen!$F$2:$F$293=B$24)*(COUNTIF(Themen!$K$5:$K$8,Drucksachen!$E$2:$E$293)>0)) | C35: =SUMPRODUCT(ISNUMBER(SEARCH($A35,Drucksachen!$I$2:$I$293))*(Drucksachen!$F$2:$F$293=C$24)*(COUNTIF(Themen!$K$5:$K$8,Drucksachen!$E$2:$E$293)>0)) | D35: =SUMPRODUCT(ISNUMBER(SEARCH($A35,Drucksachen!$I$2:$I$293))*(Drucksachen!$F$2:$F$293=D$24)*(COUNTIF(Themen!$K$5:$K$8,Drucksachen!$E$2:$E$293)>0)) | E35: =SUMPRODUCT(ISNUMBER(SEARCH($A35,Drucksachen!$I$2:$I$293))*(Drucksachen!$F$2:$F$293=E$24)*(COUNTIF(Themen!$K$5:$K$8,Drucksachen!$E$2:$E$293)>0)) | F35: =SUMPRODUCT(ISNUMBER(SEARCH($A35,Drucksachen!$I$2:$I$293))*(Drucksachen!$F$2:$F$293=F$24)*(COUNTIF(Themen!$K$5:$K$8,Drucksachen!$E$2:$E$293)>0)) | G35: =SUM(B35:F35) | H35: =IF(G35=0,"",INDEX($B$24:$F$24,MATCH(MAX(B35:F35),B35:F35,0)))
A36: Deutschlandtakt/Fahrplan | B36: =SUMPRODUCT(ISNUMBER(SEARCH($A36,Drucksachen!$I$2:$I$293))*(Drucksachen!$F$2:$F$293=B$24)*(COUNTIF(Themen!$K$5:$K$8,Drucksachen!$E$2:$E$293)>0)) | C36: =SUMPRODUCT(ISNUMBER(SEARCH($A36,Drucksachen!$I$2:$I$293))*(Drucksachen!$F$2:$F$293=C$24)*(COUNTIF(Themen!$K$5:$K$8,Drucksachen!$E$2:$E$293)>0)) | D36: =SUMPRODUCT(ISNUMBER(SEARCH($A36,Drucksachen!$I$2:$I$293))*(Drucksachen!$F$2:$F$293=D$24)*(COUNTIF(Themen!$K$5:$K$8,Drucksachen!$E$2:$E$293)>0)) | E36: =SUMPRODUCT(ISNUMBER(SEARCH($A36,Drucksachen!$I$2:$I$293))*(Drucksachen!$F$2:$F$293=E$24)*(COUNTIF(Themen!$K$5:$K$8,Drucksachen!$E$2:$E$293)>0)) | F36: =SUMPRODUCT(ISNUMBER(SEARCH($A36,Drucksachen!$I$2:$I$293))*(Drucksachen!$F$2:$F$293=F$24)*(COUNTIF(Themen!$K$5:$K$8,Drucksachen!$E$2:$E$293)>0)) | G36: =SUM(B36:F36) | H36: =IF(G36=0,"",INDEX($B$24:$F$24,MATCH(MAX(B36:F36),B36:F36,0)))
... A38: Gueterverkehr | B38: =SUMPRODUCT(ISNUMBER(SEARCH($A38,Drucksachen!$I$2:$I$293))*(Drucksachen!$F$2:$F$293=B$24)*(COUNTIF(Themen!$K$5:$K$8,Drucksachen!$E$2:$E$293)>0)) | C38: =SUMPRODUCT(ISNUMBER(SEARCH($A38,Drucksachen!$I$2:$I$293))*(Drucksachen!$F$2:$F$293=C$24)*(COUNTIF(Themen!$K$5:$K$8,Drucksachen!$E$2:$E$293)>0)) | D38: =SUMPRODUCT(ISNUMBER(SEARCH($A38,Drucksachen!$I$2:$I$293))*(Drucksachen!$F$2:$F$293=D$24)*(COUNTIF(Themen!$K$5:$K$8,Drucksachen!$E$2:$E$293)>0)) | E38: =SUMPRODUCT(ISNUMBER(SEARCH($A38,Drucksachen!$I$2:$I$293))*(Drucksachen!$F$2:$F$293=E$24)*(COUNTIF(Themen!$K$5:$K$8,Drucksachen!$E$2:$E$293)>0)) | F38: =SUMPRODUCT(ISNUMBER(SEARCH($A38,Drucksachen!$I$2:$I$293))*(Drucksachen!$F$2:$F$293=F$24)*(COUNTIF(Themen!$K$5:$K$8,Drucksachen!$E$2:$E$293)>0)) | G38: =SUM(B38:F38) | H38: =IF(G38=0,"",INDEX($B$24:$F$24,MATCH(MAX(B38:F38),B38:F38,0)))
A39: Nennungen gesamt | B39: =SUM(B25:B38) | C39: =SUM(C25:C38) | D39: =SUM(D25:D38) | E39: =SUM(E25:E38) | F39: =SUM(F25:F38) | G39: =SUM(G25:G38)

Sheet Antwortzeiten
A1: Bearbeitungsdauer Kleiner Anfragen
A2: Tage zwischen dem Datum der Kleinen Anfrage und dem Datum der Antwort der Bundesregierung. Zuordnung ueber die im Antworttitel genannte Drucksachennummer; Anfragen ohne auffindbare Antwort bleiben unberuecksichtigt.
A4: Fragende Fraktion | B4: Beantwortete Anfragen | C4: Mittelwert (Tage) | D4: Kuerzeste | E4: Laengste | F4: Gestellte Anfragen gesamt
A5: CDU/CSU | B5: =COUNTIFS(Drucksachen!$P$2:$P$293,$A5,Drucksachen!$K$2:$K$293,">0") | C5: =IF($B5=0,"",IFERROR(AVERAGEIFS(Drucksachen!$K$2:$K$293,Drucksachen!$P$2:$P$293,$A5,Drucksachen!$K$2:$K$293,">0"),"")) | D5: =IF($B5=0,"",IFERROR(_xlfn.MINIFS(Drucksachen!$K$2:$K$293,Drucksachen!$P$2:$P$293,$A5,Drucksachen!$K$2:$K$293,">0"),"")) | E5: =IF($B5=0,"",IFERROR(_xlfn.MAXIFS(Drucksachen!$K$2:$K$293,Drucksachen!$P$2:$P$293,$A5,Drucksachen!$K$2:$K$293,">0"),"")) | F5: =COUNTIFS(Drucksachen!$F$2:$F$293,$A5,Drucksachen!$E$2:$E$293,"Kleine Anfrage")
A6: Gruene | B6: =COUNTIFS(Drucksachen!$P$2:$P$293,$A6,Drucksachen!$K$2:$K$293,">0") | C6: =IF($B6=0,"",IFERROR(AVERAGEIFS(Drucksachen!$K$2:$K$293,Drucksachen!$P$2:$P$293,$A6,Drucksachen!$K$2:$K$293,">0"),"")) | D6: =IF($B6=0,"",IFERROR(_xlfn.MINIFS(Drucksachen!$K$2:$K$293,Drucksachen!$P$2:$P$293,$A6,Drucksachen!$K$2:$K$293,">0"),"")) | E6: =IF($B6=0,"",IFERROR(_xlfn.MAXIFS(Drucksachen!$K$2:$K$293,Drucksachen!$P$2:$P$293,$A6,Drucksachen!$K$2:$K$293,">0"),"")) | F6: =COUNTIFS(Drucksachen!$F$2:$F$293,$A6,Drucksachen!$E$2:$E$293,"Kleine Anfrage")
A7: AfD | B7: =COUNTIFS(Drucksachen!$P$2:$P$293,$A7,Drucksachen!$K$2:$K$293,">0") | C7: =IF($B7=0,"",IFERROR(AVERAGEIFS(Drucksachen!$K$2:$K$293,Drucksachen!$P$2:$P$293,$A7,Drucksachen!$K$2:$K$293,">0"),"")) | D7: =IF($B7=0,"",IFERROR(_xlfn.MINIFS(Drucksachen!$K$2:$K$293,Drucksachen!$P$2:$P$293,$A7,Drucksachen!$K$2:$K$293,">0"),"")) | E7: =IF($B7=0,"",IFERROR(_xlfn.MAXIFS(Drucksachen!$K$2:$K$293,Drucksachen!$P$2:$P$293,$A7,Drucksachen!$K$2:$K$293,">0"),"")) | F7: =COUNTIFS(Drucksachen!$F$2:$F$293,$A7,Drucksachen!$E$2:$E$293,"Kleine Anfrage")
A8: Linke | B8: =COUNTIFS(Drucksachen!$P$2:$P$293,$A8,Drucksachen!$K$2:$K$293,">0") | C8: =IF($B8=0,"",IFERROR(AVERAGEIFS(Drucksachen!$K$2:$K$293,Drucksachen!$P$2:$P$293,$A8,Drucksachen!$K$2:$K$293,">0"),"")) | D8: =IF($B8=0,"",IFERROR(_xlfn.MINIFS(Drucksachen!$K$2:$K$293,Drucksachen!$P$2:$P$293,$A8,Drucksachen!$K$2:$K$293,">0"),"")) | E8: =IF($B8=0,"",IFERROR(_xlfn.MAXIFS(Drucksachen!$K$2:$K$293,Drucksachen!$P$2:$P$293,$A8,Drucksachen!$K$2:$K$293,">0"),"")) | F8: =COUNTIFS(Drucksachen!$F$2:$F$293,$A8,Drucksachen!$E$2:$E$293,"Kleine Anfrage")
A9: Mehrere Fraktionen | B9: =COUNTIFS(Drucksachen!$P$2:$P$293,$A9,Drucksachen!$K$2:$K$293,">0") | C9: =IF($B9=0,"",IFERROR(AVERAGEIFS(Drucksachen!$K$2:$K$293,Drucksachen!$P$2:$P$293,$A9,Drucksachen!$K$2:$K$293,">0"),"")) | D9: =IF($B9=0,"",IFERROR(_xlfn.MINIFS(Drucksachen!$K$2:$K$293,Drucksachen!$P$2:$P$293,$A9,Drucksachen!$K$2:$K$293,">0"),"")) | E9: =IF($B9=0,"",IFERROR(_xlfn.MAXIFS(Drucksachen!$K$2:$K$293,Drucksachen!$P$2:$P$293,$A9,Drucksachen!$K$2:$K$293,">0"),"")) | F9: =COUNTIFS(Drucksachen!$F$2:$F$293,$A9,Drucksachen!$E$2:$E$293,"Kleine Anfrage")

Sheet Abstimmungen
A1: Abstimmungsverhalten der Fraktionen
A2: Quelle: Feld 'beschlussfassung' der Vorgangspositionen. Ueber Kleine Anfragen und deren Antworten wird nicht abgestimmt - erfasst sind nur Antraege, Gesetzentwuerfe, Entschliessungsantraege und Beschlussempfehlungen. Leere Zelle heisst: aus der DIP-Bemerkung nicht eindeutig ableitbar, nicht etwa Abwesenheit.
A4: Datum | B4: Drucksache | C4: Vorlage | D4: Beschluss | E4: Abstimmungsart | F4: CDU/CSU | G4: SPD | H4: Gruene | I4: FDP | J4: AfD | K4: Linke
A5: 46213 | B5: 390/26 | C5: Infrastruktur-Zukunftsgesetz | D5: Zustimmung; Entschließung
A6: 46212 | B6: 21/6922 | C6: Stillstand in der Bahnpolitik überwinden - Strukturreformen umsetzen, Kapazitäten des Schienennetzes verstärken und ein gutes Fernverkehrsangebot sicherstellen | D6: Überweisung
A7: 46212 | B7: 21/6331 | C7: Leistung erbringen, Neutralität wahren - Aufgabenfremde Maßnahmen wie die Regenbogenbeflaggung bei der Deutsche Bahn AG unterlassen | D7: Ablehnung der Vorlage
A8: 46199 | B8: 21/6703 | C8: Infrastruktur-Zukunftsgesetz | D8: Ablehnung des Änderungsantrags
A9: 46199 | B9: 21/4099, 21/6701 | C9: Infrastruktur-Zukunftsgesetz | D9: Annahme in Ausschussfassung
A10: 46199 | B10: 21/4458 | C10: Infrastrukturvorhaben im Schienennetz effektiv beschleunigen | D10: Ablehnung der Vorlage
A11: 46199 | B11: 21/4099, 21/6701 | C11: Infrastruktur-Zukunftsgesetz | D11: Annahme in Ausschussfassung
A12: 46183 | B12: 21/6331 | C12: Leistung erbringen, Neutralität wahren - Aufgabenfremde Maßnahmen wie die Regenbogenbeflaggung bei der Deutsche Bahn AG unterlassen | D12: Überweisung
A13: 46086 | B13: 21/4458 | C13: Infrastrukturvorhaben im Schienennetz effektiv beschleunigen | D13: Überweisung
A14: 46085 | B14: 21/4099 | C14: Infrastruktur-Zukunftsgesetz | D14: Änderung des Überweisungsbeschlusses
A15: 46079 | B15: 21/4099, 21/4301 | C15: Infrastruktur-Zukunftsgesetz | D15: Überweisung
A16: 46052 | B16: 780/25 | C16: Infrastruktur-Zukunftsgesetz | D16: Stellungnahme
... A34: 45834 | B34: 21/335 | C34: Gesetz zur Änderung des Allgemeinen Eisenbahngesetzes und weiterer Gesetze zur Spezifizierung der Flächenbedarfe der Eisenbahn | D34: Ablehnung der Vorlage
A35: 45834 | B35: 21/326, 21/642 | C35: Sechstes Gesetz zur Änderung des Allgemeinen Eisenbahngesetzes | D35: Annahme in Ausschussfassung | E35: Namentliche Abstimmung
A36: 45833 | B36: 21/326 | C36: Sechstes Gesetz zur Änderung des Allgemeinen Eisenbahngesetzes | D36: Änderung des Überweisungsbeschlusses
A37: 45813 | B37: 21/326 | C37: Sechstes Gesetz zur Änderung des Allgemeinen Eisenbahngesetzes | D37: Überweisung
A38: 45813 | B38: 21/335 | C38: Gesetz zur Änderung des Allgemeinen Eisenbahngesetzes und weiterer Gesetze zur Spezifizierung der Flächenbedarfe der Eisenbahn | D38: Überweisung
A39: 45372 | B39: 20/7350 | C39: Schiene in die Zukunft führen - Deutsche Bahn AG neu aufstellen | D39: Ablehnung der Vorlage
A40: 45344 | B40: 20/7197 | C40: Die Deutsche Bahn AG zielgerichtet und wirkungsvoll reformieren | D40: Ablehnung der Vorlage
A41: 45198 | B41: 466/23 | C41: Gesetz zur Stärkung des Klimaschutzes durch eine Beschleunigung des Ausbaus der Schieneninfrastruktur - Klimaschutzbeschleunigungsgesetz Schiene | D41: Einbringung in geänderter Fassung; Bestellung eines Beauftragten
A42: 45113 | B42: 20/5808 | C42: Bundeslagebild zur Kriminalität in Bahnhöfen und Zügen | D42: Ablehnung der Vorlage
A43: 45099 | B43: 20/7350 | C43: Schiene in die Zukunft führen - Deutsche Bahn AG neu aufstellen | D43: Überweisung
A44: 45092 | B44: 20/6988 | C44: Bahn zukunftsfähig aufstellen - Zerschlagung der Deutschen Bahn AG eine Absage erteilen | D44: Überweisung
A45: 45092 | B45: 20/7197 | C45: Die Deutsche Bahn AG zielgerichtet und wirkungsvoll reformieren | D45: Überweisung
A46: 45057 | B46: 20/6721 | C46: Eisenbahn-Investitionen in Westafrika stärker unterstützen - Chancen für die deutsche Bahnindustrie nutzen | D46: Überweisung
A47: 44986 | B47: 20/5808 | C47: Bundeslagebild zur Kriminalität in Bahnhöfen und Zügen | D47: Überweisung
A50: Bilanz je Fraktion
A51: Fraktion | B51: Dafuer | C51: Dagegen | D51: Enthaltung | E51: Abstimmungen gesamt
A52: CDU/CSU | B52: =COUNTIF($F$5:$F$47,"Dafuer") | C52: =COUNTIF($F$5:$F$47,"Dagegen") | D52: =COUNTIF($F$5:$F$47,"Enthaltung") | E52: =SUM(B52:D52)
A53: SPD | B53: =COUNTIF($G$5:$G$47,"Dafuer") | C53: =COUNTIF($G$5:$G$47,"Dagegen") | D53: =COUNTIF($G$5:$G$47,"Enthaltung") | E53: =SUM(B53:D53)
A54: Gruene | B54: =COUNTIF($H$5:$H$47,"Dafuer") | C54: =COUNTIF($H$5:$H$47,"Dagegen") | D54: =COUNTIF($H$5:$H$47,"Enthaltung") | E54: =SUM(B54:D54)
A55: FDP | B55: =COUNTIF($I$5:$I$47,"Dafuer") | C55: =COUNTIF($I$5:$I$47,"Dagegen") | D55: =COUNTIF($I$5:$I$47,"Enthaltung") | E55: =SUM(B55:D55)
A56: AfD | B56: =COUNTIF($J$5:$J$47,"Dafuer") | C56: =COUNTIF($J$5:$J$47,"Dagegen") | D56: =COUNTIF($J$5:$J$47,"Enthaltung") | E56: =SUM(B56:D56)
A57: Linke | B57: =COUNTIF($K$5:$K$47,"Dafuer") | C57: =COUNTIF($K$5:$K$47,"Dagegen") | D57: =COUNTIF($K$5:$K$47,"Enthaltung") | E57: =SUM(B57:D57)

Sheet Profil
A1: Fraktionsprofil: vier messbare Dimensionen
A2: Achtung Interpretation: Das sind Aktivitaetsmasse, kein Qualitaetsurteil. Ob eine Anfrage sachkundig oder blosse Symbolpolitik ist, steht in DIP nicht drin und laesst sich aus Metadaten nicht ableiten. Ausserdem koennen Regierungsfraktionen strukturell kaum Kleine Anfragen stellen - niedrige Werte heissen dort nicht Untaetigkeit.
A4: Kennzahl | B4: CDU/CSU | C4: Gruene | D4: AfD | E4: Linke | F4: Was sie misst | H4: Hilfsraster Themen | I4: CDU/CSU | J4: Gruene | K4: AfD | L4: Linke
A5: Initiativen gesamt | B5: =COUNTIFS(Drucksachen!$F$2:$F$293,I$4,Drucksachen!$E$2:$E$293,"Kleine Anfrage")+COUNTIFS(Drucksachen!$F$2:$F$293,I$4,Drucksachen!$E$2:$E$293,"Antrag")+COUNTIFS(Drucksachen!$F$2:$F$293,I$4,Drucksachen!$E$2:$E$293,"Entschließungsantrag")+COUNTIFS(Drucksachen!$F$2:$F$293,I$4,Drucksachen!$E$2:$E$293,"Gesetzentwurf") | C5: =COUNTIFS(Drucksachen!$F$2:$F$293,J$4,Drucksachen!$E$2:$E$293,"Kleine Anfrage")+COUNTIFS(Drucksachen!$F$2:$F$293,J$4,Drucksachen!$E$2:$E$293,"Antrag")+COUNTIFS(Drucksachen!$F$2:$F$293,J$4,Drucksachen!$E$2:$E$293,"Entschließungsantrag")+COUNTIFS(Drucksachen!$F$2:$F$293,J$4,Drucksachen!$E$2:$E$293,"Gesetzentwurf") | D5: =COUNTIFS(Drucksachen!$F$2:$F$293,K$4,Drucksachen!$E$2:$E$293,"Kleine Anfrage")+COUNTIFS(Drucksachen!$F$2:$F$293,K$4,Drucksachen!$E$2:$E$293,"Antrag")+COUNTIFS(Drucksachen!$F$2:$F$293,K$4,Drucksachen!$E$2:$E$293,"Entschließungsantrag")+COUNTIFS(Drucksachen!$F$2:$F$293,K$4,Drucksachen!$E$2:$E$293,"Gesetzentwurf") | E5: =COUNTIFS(Drucksachen!$F$2:$F$293,L$4,Drucksachen!$E$2:$E$293,"Kleine Anfrage")+COUNTIFS(Drucksachen!$F$2:$F$293,L$4,Drucksachen!$E$2:$E$293,"Antrag")+COUNTIFS(Drucksachen!$F$2:$F$293,L$4,Drucksachen!$E$2:$E$293,"Entschließungsantrag")+COUNTIFS(Drucksachen!$F$2:$F$293,L$4,Drucksachen!$E$2:$E$293,"Gesetzentwurf") | F5: Wie viel eine Fraktion ueberhaupt einbringt | H5: Bahnhoefe | I5: =IF(SUMPRODUCT(ISNUMBER(SEARCH($H5,Drucksachen!$I$2:$I$293))*(Drucksachen!$F$2:$F$293=I$4))>0,1,0) | J5: =IF(SUMPRODUCT(ISNUMBER(SEARCH($H5,Drucksachen!$I$2:$I$293))*(Drucksachen!$F$2:$F$293=J$4))>0,1,0) | K5: =IF(SUMPRODUCT(ISNUMBER(SEARCH($H5,Drucksachen!$I$2:$I$293))*(Drucksachen!$F$2:$F$293=K$4))>0,1,0) | L5: =IF(SUMPRODUCT(ISNUMBER(SEARCH($H5,Drucksachen!$I$2:$I$293))*(Drucksachen!$F$2:$F$293=L$4))>0,1,0)
A6: davon abstimmungsfaehig | B6: =COUNTIFS(Drucksachen!$F$2:$F$293,I$4,Drucksachen!$E$2:$E$293,"Antrag")+COUNTIFS(Drucksachen!$F$2:$F$293,I$4,Drucksachen!$E$2:$E$293,"Entschließungsantrag")+COUNTIFS(Drucksachen!$F$2:$F$293,I$4,Drucksachen!$E$2:$E$293,"Gesetzentwurf") | C6: =COUNTIFS(Drucksachen!$F$2:$F$293,J$4,Drucksachen!$E$2:$E$293,"Antrag")+COUNTIFS(Drucksachen!$F$2:$F$293,J$4,Drucksachen!$E$2:$E$293,"Entschließungsantrag")+COUNTIFS(Drucksachen!$F$2:$F$293,J$4,Drucksachen!$E$2:$E$293,"Gesetzentwurf") | D6: =COUNTIFS(Drucksachen!$F$2:$F$293,K$4,Drucksachen!$E$2:$E$293,"Antrag")+COUNTIFS(Drucksachen!$F$2:$F$293,K$4,Drucksachen!$E$2:$E$293,"Entschließungsantrag")+COUNTIFS(Drucksachen!$F$2:$F$293,K$4,Drucksachen!$E$2:$E$293,"Gesetzentwurf") | E6: =COUNTIFS(Drucksachen!$F$2:$F$293,L$4,Drucksachen!$E$2:$E$293,"Antrag")+COUNTIFS(Drucksachen!$F$2:$F$293,L$4,Drucksachen!$E$2:$E$293,"Entschließungsantrag")+COUNTIFS(Drucksachen!$F$2:$F$293,L$4,Drucksachen!$E$2:$E$293,"Gesetzentwurf") | F6: Gestaltung statt blosser Kontrolle: Antraege und Gesetzentwuerfe | H6: Kriminalitaet | I6: =IF(SUMPRODUCT(ISNUMBER(SEARCH($H6,Drucksachen!$I$2:$I$293))*(Drucksachen!$F$2:$F$293=I$4))>0,1,0) | J6: =IF(SUMPRODUCT(ISNUMBER(SEARCH($H6,Drucksachen!$I$2:$I$293))*(Drucksachen!$F$2:$F$293=J$4))>0,1,0) | K6: =IF(SUMPRODUCT(ISNUMBER(SEARCH($H6,Drucksachen!$I$2:$I$293))*(Drucksachen!$F$2:$F$293=K$4))>0,1,0) | L6: =IF(SUMPRODUCT(ISNUMBER(SEARCH($H6,Drucksachen!$I$2:$I$293))*(Drucksachen!$F$2:$F$293=L$4))>0,1,0)
A7: Themenbreite | B7: =SUM(I$5:I$18) | C7: =SUM(J$5:J$18) | D7: =SUM(K$5:K$18) | E7: =SUM(L$5:L$18) | F7: Wie viele der 14 Sachthemen beruehrt werden | H7: Sonstiges | I7: =IF(SUMPRODUCT(ISNUMBER(SEARCH($H7,Drucksachen!$I$2:$I$293))*(Drucksachen!$F$2:$F$293=I$4))>0,1,0) | J7: =IF(SUMPRODUCT(ISNUMBER(SEARCH($H7,Drucksachen!$I$2:$I$293))*(Drucksachen!$F$2:$F$293=J$4))>0,1,0) | K7: =IF(SUMPRODUCT(ISNUMBER(SEARCH($H7,Drucksachen!$I$2:$I$293))*(Drucksachen!$F$2:$F$293=K$4))>0,1,0) | L7: =IF(SUMPRODUCT(ISNUMBER(SEARCH($H7,Drucksachen!$I$2:$I$293))*(Drucksachen!$F$2:$F$293=L$4))>0,1,0)
A8: Aktive Quartale | B8: =SUM(I$21:I$40) | C8: =SUM(J$21:J$40) | D8: =SUM(K$21:K$40) | E8: =SUM(L$21:L$40) | F8: Beharrlichkeit: Quartale mit Aktivitaet, von 20 | H8: Infrastruktur/Netz | I8: =IF(SUMPRODUCT(ISNUMBER(SEARCH($H8,Drucksachen!$I$2:$I$293))*(Drucksachen!$F$2:$F$293=I$4))>0,1,0) | J8: =IF(SUMPRODUCT(ISNUMBER(SEARCH($H8,Drucksachen!$I$2:$I$293))*(Drucksachen!$F$2:$F$293=J$4))>0,1,0) | K8: =IF(SUMPRODUCT(ISNUMBER(SEARCH($H8,Drucksachen!$I$2:$I$293))*(Drucksachen!$F$2:$F$293=K$4))>0,1,0) | L8: =IF(SUMPRODUCT(ISNUMBER(SEARCH($H8,Drucksachen!$I$2:$I$293))*(Drucksachen!$F$2:$F$293=L$4))>0,1,0)
H9: Konzernstruktur/DB AG | I9: =IF(SUMPRODUCT(ISNUMBER(SEARCH($H9,Drucksachen!$I$2:$I$293))*(Drucksachen!$F$2:$F$293=I$4))>0,1,0) | J9: =IF(SUMPRODUCT(ISNUMBER(SEARCH($H9,Drucksachen!$I$2:$I$293))*(Drucksachen!$F$2:$F$293=J$4))>0,1,0) | K9: =IF(SUMPRODUCT(ISNUMBER(SEARCH($H9,Drucksachen!$I$2:$I$293))*(Drucksachen!$F$2:$F$293=K$4))>0,1,0) | L9: =IF(SUMPRODUCT(ISNUMBER(SEARCH($H9,Drucksachen!$I$2:$I$293))*(Drucksachen!$F$2:$F$293=L$4))>0,1,0)
H10: Sicherheit | I10: =IF(SUMPRODUCT(ISNUMBER(SEARCH($H10,Drucksachen!$I$2:$I$293))*(Drucksachen!$F$2:$F$293=I$4))>0,1,0) | J10: =IF(SUMPRODUCT(ISNUMBER(SEARCH($H10,Drucksachen!$I$2:$I$293))*(Drucksachen!$F$2:$F$293=J$4))>0,1,0) | K10: =IF(SUMPRODUCT(ISNUMBER(SEARCH($H10,Drucksachen!$I$2:$I$293))*(Drucksachen!$F$2:$F$293=K$4))>0,1,0) | L10: =IF(SUMPRODUCT(ISNUMBER(SEARCH($H10,Drucksachen!$I$2:$I$293))*(Drucksachen!$F$2:$F$293=L$4))>0,1,0)
A11: Normiert (Spitzenreiter je Zeile = 100) | H11: Finanzierung | I11: =IF(SUMPRODUCT(ISNUMBER(SEARCH($H11,Drucksachen!$I$2:$I$293))*(Drucksachen!$F$2:$F$293=I$4))>0,1,0) | J11: =IF(SUMPRODUCT(ISNUMBER(SEARCH($H11,Drucksachen!$I$2:$I$293))*(Drucksachen!$F$2:$F$293=J$4))>0,1,0) | K11: =IF(SUMPRODUCT(ISNUMBER(SEARCH($H11,Drucksachen!$I$2:$I$293))*(Drucksachen!$F$2:$F$293=K$4))>0,1,0) | L11: =IF(SUMPRODUCT(ISNUMBER(SEARCH($H11,Drucksachen!$I$2:$I$293))*(Drucksachen!$F$2:$F$293=L$4))>0,1,0)
A12: Kennzahl | B12: CDU/CSU | C12: Gruene | D12: AfD | E12: Linke | H12: Puenktlichkeit/Qualitaet | I12: =IF(SUMPRODUCT(ISNUMBER(SEARCH($H12,Drucksachen!$I$2:$I$293))*(Drucksachen!$F$2:$F$293=I$4))>0,1,0) | J12: =IF(SUMPRODUCT(ISNUMBER(SEARCH($H12,Drucksachen!$I$2:$I$293))*(Drucksachen!$F$2:$F$293=J$4))>0,1,0) | K12: =IF(SUMPRODUCT(ISNUMBER(SEARCH($H12,Drucksachen!$I$2:$I$293))*(Drucksachen!$F$2:$F$293=K$4))>0,1,0) | L12: =IF(SUMPRODUCT(ISNUMBER(SEARCH($H12,Drucksachen!$I$2:$I$293))*(Drucksachen!$F$2:$F$293=L$4))>0,1,0)
A13: Initiativen gesamt | B13: =IFERROR(ROUND(B5/MAX($B$5:$E$5)*100,0),0) | C13: =IFERROR(ROUND(C5/MAX($B$5:$E$5)*100,0),0) | D13: =IFERROR(ROUND(D5/MAX($B$5:$E$5)*100,0),0) | E13: =IFERROR(ROUND(E5/MAX($B$5:$E$5)*100,0),0) | H13: Barrierefreiheit | I13: =IF(SUMPRODUCT(ISNUMBER(SEARCH($H13,Drucksachen!$I$2:$I$293))*(Drucksachen!$F$2:$F$293=I$4))>0,1,0) | J13: =IF(SUMPRODUCT(ISNUMBER(SEARCH($H13,Drucksachen!$I$2:$I$293))*(Drucksachen!$F$2:$F$293=J$4))>0,1,0) | K13: =IF(SUMPRODUCT(ISNUMBER(SEARCH($H13,Drucksachen!$I$2:$I$293))*(Drucksachen!$F$2:$F$293=K$4))>0,1,0) | L13: =IF(SUMPRODUCT(ISNUMBER(SEARCH($H13,Drucksachen!$I$2:$I$293))*(Drucksachen!$F$2:$F$293=L$4))>0,1,0)
A14: davon abstimmungsfaehig | B14: =IFERROR(ROUND(B6/MAX($B$6:$E$6)*100,0),0) | C14: =IFERROR(ROUND(C6/MAX($B$6:$E$6)*100,0),0) | D14: =IFERROR(ROUND(D6/MAX($B$6:$E$6)*100,0),0) | E14: =IFERROR(ROUND(E6/MAX($B$6:$E$6)*100,0),0) | H14: Deutschlandticket | I14: =IF(SUMPRODUCT(ISNUMBER(SEARCH($H14,Drucksachen!$I$2:$I$293))*(Drucksachen!$F$2:$F$293=I$4))>0,1,0) | J14: =IF(SUMPRODUCT(ISNUMBER(SEARCH($H14,Drucksachen!$I$2:$I$293))*(Drucksachen!$F$2:$F$293=J$4))>0,1,0) | K14: =IF(SUMPRODUCT(ISNUMBER(SEARCH($H14,Drucksachen!$I$2:$I$293))*(Drucksachen!$F$2:$F$293=K$4))>0,1,0) | L14: =IF(SUMPRODUCT(ISNUMBER(SEARCH($H14,Drucksachen!$I$2:$I$293))*(Drucksachen!$F$2:$F$293=L$4))>0,1,0)
A15: Themenbreite | B15: =IFERROR(ROUND(B7/MAX($B$7:$E$7)*100,0),0) | C15: =IFERROR(ROUND(C7/MAX($B$7:$E$7)*100,0),0) | D15: =IFERROR(ROUND(D7/MAX($B$7:$E$7)*100,0),0) | E15: =IFERROR(ROUND(E7/MAX($B$7:$E$7)*100,0),0) | H15: Nahverkehr/SPNV | I15: =IF(SUMPRODUCT(ISNUMBER(SEARCH($H15,Drucksachen!$I$2:$I$293))*(Drucksachen!$F$2:$F$293=I$4))>0,1,0) | J15: =IF(SUMPRODUCT(ISNUMBER(SEARCH($H15,Drucksachen!$I$2:$I$293))*(Drucksachen!$F$2:$F$293=J$4))>0,1,0) | K15: =IF(SUMPRODUCT(ISNUMBER(SEARCH($H15,Drucksachen!$I$2:$I$293))*(Drucksachen!$F$2:$F$293=K$4))>0,1,0) | L15: =IF(SUMPRODUCT(ISNUMBER(SEARCH($H15,Drucksachen!$I$2:$I$293))*(Drucksachen!$F$2:$F$293=L$4))>0,1,0)
A16: Aktive Quartale | B16: =IFERROR(ROUND(B8/MAX($B$8:$E$8)*100,0),0) | C16: =IFERROR(ROUND(C8/MAX($B$8:$E$8)*100,0),0) | D16: =IFERROR(ROUND(D8/MAX($B$8:$E$8)*100,0),0) | E16: =IFERROR(ROUND(E8/MAX($B$8:$E$8)*100,0),0) | H16: Deutschlandtakt/Fahrplan | I16: =IF(SUMPRODUCT(ISNUMBER(SEARCH($H16,Drucksachen!$I$2:$I$293))*(Drucksachen!$F$2:$F$293=I$4))>0,1,0) | J16: =IF(SUMPRODUCT(ISNUMBER(SEARCH($H16,Drucksachen!$I$2:$I$293))*(Drucksachen!$F$2:$F$293=J$4))>0,1,0) | K16: =IF(SUMPRODUCT(ISNUMBER(SEARCH($H16,Drucksachen!$I$2:$I$293))*(Drucksachen!$F$2:$F$293=K$4))>0,1,0) | L16: =IF(SUMPRODUCT(ISNUMBER(SEARCH($H16,Drucksachen!$I$2:$I$293))*(Drucksachen!$F$2:$F$293=L$4))>0,1,0)
H17: Personal | I17: =IF(SUMPRODUCT(ISNUMBER(SEARCH($H17,Drucksachen!$I$2:$I$293))*(Drucksachen!$F$2:$F$293=I$4))>0,1,0) | J17: =IF(SUMPRODUCT(ISNUMBER(SEARCH($H17,Drucksachen!$I$2:$I$293))*(Drucksachen!$F$2:$F$293=J$4))>0,1,0) | K17: =IF(SUMPRODUCT(ISNUMBER(SEARCH($H17,Drucksachen!$I$2:$I$293))*(Drucksachen!$F$2:$F$293=K$4))>0,1,0) | L17: =IF(SUMPRODUCT(ISNUMBER(SEARCH($H17,Drucksachen!$I$2:$I$293))*(Drucksachen!$F$2:$F$293=L$4))>0,1,0)
H18: Gueterverkehr | I18: =IF(SUMPRODUCT(ISNUMBER(SEARCH($H18,Drucksachen!$I$2:$I$293))*(Drucksachen!$F$2:$F$293=I$4))>0,1,0) | J18: =IF(SUMPRODUCT(ISNUMBER(SEARCH($H18,Drucksachen!$I$2:$I$293))*(Drucksachen!$F$2:$F$293=J$4))>0,1,0) | K18: =IF(SUMPRODUCT(ISNUMBER(SEARCH($H18,Drucksachen!$I$2:$I$293))*(Drucksachen!$F$2:$F$293=K$4))>0,1,0) | L18: =IF(SUMPRODUCT(ISNUMBER(SEARCH($H18,Drucksachen!$I$2:$I$293))*(Drucksachen!$F$2:$F$293=L$4))>0,1,0)
H20: Hilfsraster Quartale
H21: 2021-Q4 | I21: =IF(COUNTIFS(Drucksachen!$C$2:$C$293,$H21,Drucksachen!$F$2:$F$293,I$4)>0,1,0) | J21: =IF(COUNTIFS(Drucksachen!$C$2:$C$293,$H21,Drucksachen!$F$2:$F$293,J$4)>0,1,0) | K21: =IF(COUNTIFS(Drucksachen!$C$2:$C$293,$H21,Drucksachen!$F$2:$F$293,K$4)>0,1,0) | L21: =IF(COUNTIFS(Drucksachen!$C$2:$C$293,$H21,Drucksachen!$F$2:$F$293,L$4)>0,1,0)
H22: 2022-Q1 | I22: =IF(COUNTIFS(Drucksachen!$C$2:$C$293,$H22,Drucksachen!$F$2:$F$293,I$4)>0,1,0) | J22: =IF(COUNTIFS(Drucksachen!$C$2:$C$293,$H22,Drucksachen!$F$2:$F$293,J$4)>0,1,0) | K22: =IF(COUNTIFS(Drucksachen!$C$2:$C$293,$H22,Drucksachen!$F$2:$F$293,K$4)>0,1,0) | L22: =IF(COUNTIFS(Drucksachen!$C$2:$C$293,$H22,Drucksachen!$F$2:$F$293,L$4)>0,1,0)
H23: 2022-Q2 | I23: =IF(COUNTIFS(Drucksachen!$C$2:$C$293,$H23,Drucksachen!$F$2:$F$293,I$4)>0,1,0) | J23: =IF(COUNTIFS(Drucksachen!$C$2:$C$293,$H23,Drucksachen!$F$2:$F$293,J$4)>0,1,0) | K23: =IF(COUNTIFS(Drucksachen!$C$2:$C$293,$H23,Drucksachen!$F$2:$F$293,K$4)>0,1,0) | L23: =IF(COUNTIFS(Drucksachen!$C$2:$C$293,$H23,Drucksachen!$F$2:$F$293,L$4)>0,1,0)
H24: 2022-Q3 | I24: =IF(COUNTIFS(Drucksachen!$C$2:$C$293,$H24,Drucksachen!$F$2:$F$293,I$4)>0,1,0) | J24: =IF(COUNTIFS(Drucksachen!$C$2:$C$293,$H24,Drucksachen!$F$2:$F$293,J$4)>0,1,0) | K24: =IF(COUNTIFS(Drucksachen!$C$2:$C$293,$H24,Drucksachen!$F$2:$F$293,K$4)>0,1,0) | L24: =IF(COUNTIFS(Drucksachen!$C$2:$C$293,$H24,Drucksachen!$F$2:$F$293,L$4)>0,1,0)
H25: 2022-Q4 | I25: =IF(COUNTIFS(Drucksachen!$C$2:$C$293,$H25,Drucksachen!$F$2:$F$293,I$4)>0,1,0) | J25: =IF(COUNTIFS(Drucksachen!$C$2:$C$293,$H25,Drucksachen!$F$2:$F$293,J$4)>0,1,0) | K25: =IF(COUNTIFS(Drucksachen!$C$2:$C$293,$H25,Drucksachen!$F$2:$F$293,K$4)>0,1,0) | L25: =IF(COUNTIFS(Drucksachen!$C$2:$C$293,$H25,Drucksachen!$F$2:$F$293,L$4)>0,1,0)
H26: 2023-Q1 | I26: =IF(COUNTIFS(Drucksachen!$C$2:$C$293,$H26,Drucksachen!$F$2:$F$293,I$4)>0,1,0) | J26: =IF(COUNTIFS(Drucksachen!$C$2:$C$293,$H26,Drucksachen!$F$2:$F$293,J$4)>0,1,0) | K26: =IF(COUNTIFS(Drucksachen!$C$2:$C$293,$H26,Drucksachen!$F$2:$F$293,K$4)>0,1,0) | L26: =IF(COUNTIFS(Drucksachen!$C$2:$C$293,$H26,Drucksachen!$F$2:$F$293,L$4)>0,1,0)
H27: 2023-Q2 | I27: =IF(COUNTIFS(Drucksachen!$C$2:$C$293,$H27,Drucksachen!$F$2:$F$293,I$4)>0,1,0) | J27: =IF(COUNTIFS(Drucksachen!$C$2:$C$293,$H27,Drucksachen!$F$2:$F$293,J$4)>0,1,0) | K27: =IF(COUNTIFS(Drucksachen!$C$2:$C$293,$H27,Drucksachen!$F$2:$F$293,K$4)>0,1,0) | L27: =IF(COUNTIFS(Drucksachen!$C$2:$C$293,$H27,Drucksachen!$F$2:$F$293,L$4)>0,1,0)
H28: 2023-Q3 | I28: =IF(COUNTIFS(Drucksachen!$C$2:$C$293,$H28,Drucksachen!$F$2:$F$293,I$4)>0,1,0) | J28: =IF(COUNTIFS(Drucksachen!$C$2:$C$293,$H28,Drucksachen!$F$2:$F$293,J$4)>0,1,0) | K28: =IF(COUNTIFS(Drucksachen!$C$2:$C$293,$H28,Drucksachen!$F$2:$F$293,K$4)>0,1,0) | L28: =IF(COUNTIFS(Drucksachen!$C$2:$C$293,$H28,Drucksachen!$F$2:$F$293,L$4)>0,1,0)
H29: 2023-Q4 | I29: =IF(COUNTIFS(Drucksachen!$C$2:$C$293,$H29,Drucksachen!$F$2:$F$293,I$4)>0,1,0) | J29: =IF(COUNTIFS(Drucksachen!$C$2:$C$293,$H29,Drucksachen!$F$2:$F$293,J$4)>0,1,0) | K29: =IF(COUNTIFS(Drucksachen!$C$2:$C$293,$H29,Drucksachen!$F$2:$F$293,K$4)>0,1,0) | L29: =IF(COUNTIFS(Drucksachen!$C$2:$C$293,$H29,Drucksachen!$F$2:$F$293,L$4)>0,1,0)
H30: 2024-Q1 | I30: =IF(COUNTIFS(Drucksachen!$C$2:$C$293,$H30,Drucksachen!$F$2:$F$293,I$4)>0,1,0) | J30: =IF(COUNTIFS(Drucksachen!$C$2:$C$293,$H30,Drucksachen!$F$2:$F$293,J$4)>0,1,0) | K30: =IF(COUNTIFS(Drucksachen!$C$2:$C$293,$H30,Drucksachen!$F$2:$F$293,K$4)>0,1,0) | L30: =IF(COUNTIFS(Drucksachen!$C$2:$C$293,$H30,Drucksachen!$F$2:$F$293,L$4)>0,1,0)
H31: 2024-Q2 | I31: =IF(COUNTIFS(Drucksachen!$C$2:$C$293,$H31,Drucksachen!$F$2:$F$293,I$4)>0,1,0) | J31: =IF(COUNTIFS(Drucksachen!$C$2:$C$293,$H31,Drucksachen!$F$2:$F$293,J$4)>0,1,0) | K31: =IF(COUNTIFS(Drucksachen!$C$2:$C$293,$H31,Drucksachen!$F$2:$F$293,K$4)>0,1,0) | L31: =IF(COUNTIFS(Drucksachen!$C$2:$C$293,$H31,Drucksachen!$F$2:$F$293,L$4)>0,1,0)
H32: 2024-Q3 | I32: =IF(COUNTIFS(Drucksachen!$C$2:$C$293,$H32,Drucksachen!$F$2:$F$293,I$4)>0,1,0) | J32: =IF(COUNTIFS(Drucksachen!$C$2:$C$293,$H32,Drucksachen!$F$2:$F$293,J$4)>0,1,0) | K32: =IF(COUNTIFS(Drucksachen!$C$2:$C$293,$H32,Drucksachen!$F$2:$F$293,K$4)>0,1,0) | L32: =IF(COUNTIFS(Drucksachen!$C$2:$C$293,$H32,Drucksachen!$F$2:$F$293,L$4)>0,1,0)
... H40: 2026-Q3 | I40: =IF(COUNTIFS(Drucksachen!$C$2:$C$293,$H40,Drucksachen!$F$2:$F$293,I$4)>0,1,0) | J40: =IF(COUNTIFS(Drucksachen!$C$2:$C$293,$H40,Drucksachen!$F$2:$F$293,J$4)>0,1,0) | K40: =IF(COUNTIFS(Drucksachen!$C$2:$C$293,$H40,Drucksachen!$F$2:$F$293,K$4)>0,1,0) | L40: =IF(COUNTIFS(Drucksachen!$C$2:$C$293,$H40,Drucksachen!$F$2:$F$293,L$4)>0,1,0)

Sheet Bewertung
A1: Bewertung: wem ist die Schiene wichtig
A2: Zwei Verzerrungen, die dieses Blatt NICHT herausrechnen kann. Erstens: Oppositionsfraktionen koennen keine Gesetze durchbringen, fuer sie ist der abgelehnte Antrag oft das einzige verfuegbare Mittel. Zweitens: Regierungsfraktionen brauchen gar keine Antraege, sie machen Politik ueber das Ministerium und sind in DIP deshalb strukturell unsichtbar. Ein niedriger Wert heisst dort nicht Desinteresse. Vergleiche deshalb nur innerhalb derselben Rolle, die Spalte steht unten dabei.
A4: Schritt 1: gezaehlt, ohne Wertung
A5: Zaehlung | B5: CDU/CSU | C5: Gruene | D5: AfD | E5: Linke | F5: Bezugsgroesse | H5: Hilfsraster | I5: CDU/CSU | J5: Gruene | K5: AfD | L5: Linke
A6: Eigene Initiativen | B6: =COUNTIFS(Drucksachen!$F$2:$F$293,B$5,Drucksachen!$E$2:$E$293,"Kleine Anfrage")+COUNTIFS(Drucksachen!$F$2:$F$293,B$5,Drucksachen!$E$2:$E$293,"Antrag")+COUNTIFS(Drucksachen!$F$2:$F$293,B$5,Drucksachen!$E$2:$E$293,"Entschließungsantrag")+COUNTIFS(Drucksachen!$F$2:$F$293,B$5,Drucksachen!$E$2:$E$293,"Gesetzentwurf") | C6: =COUNTIFS(Drucksachen!$F$2:$F$293,C$5,Drucksachen!$E$2:$E$293,"Kleine Anfrage")+COUNTIFS(Drucksachen!$F$2:$F$293,C$5,Drucksachen!$E$2:$E$293,"Antrag")+COUNTIFS(Drucksachen!$F$2:$F$293,C$5,Drucksachen!$E$2:$E$293,"Entschließungsantrag")+COUNTIFS(Drucksachen!$F$2:$F$293,C$5,Drucksachen!$E$2:$E$293,"Gesetzentwurf") | D6: =COUNTIFS(Drucksachen!$F$2:$F$293,D$5,Drucksachen!$E$2:$E$293,"Kleine Anfrage")+COUNTIFS(Drucksachen!$F$2:$F$293,D$5,Drucksachen!$E$2:$E$293,"Antrag")+COUNTIFS(Drucksachen!$F$2:$F$293,D$5,Drucksachen!$E$2:$E$293,"Entschließungsantrag")+COUNTIFS(Drucksachen!$F$2:$F$293,D$5,Drucksachen!$E$2:$E$293,"Gesetzentwurf") | E6: =COUNTIFS(Drucksachen!$F$2:$F$293,E$5,Drucksachen!$E$2:$E$293,"Kleine Anfrage")+COUNTIFS(Drucksachen!$F$2:$F$293,E$5,Drucksachen!$E$2:$E$293,"Antrag")+COUNTIFS(Drucksachen!$F$2:$F$293,E$5,Drucksachen!$E$2:$E$293,"Entschließungsantrag")+COUNTIFS(Drucksachen!$F$2:$F$293,E$5,Drucksachen!$E$2:$E$293,"Gesetzentwurf") | F6: Anzahl | H6: Bahnhoefe | I6: =IF(SUMPRODUCT(ISNUMBER(SEARCH($H6,Drucksachen!$I$2:$I$293))*(Drucksachen!$F$2:$F$293=I$5)*(COUNTIF(Themen!$K$5:$K$8,Drucksachen!$E$2:$E$293)>0))>0,1,0) | J6: =IF(SUMPRODUCT(ISNUMBER(SEARCH($H6,Drucksachen!$I$2:$I$293))*(Drucksachen!$F$2:$F$293=J$5)*(COUNTIF(Themen!$K$5:$K$8,Drucksachen!$E$2:$E$293)>0))>0,1,0) | K6: =IF(SUMPRODUCT(ISNUMBER(SEARCH($H6,Drucksachen!$I$2:$I$293))*(Drucksachen!$F$2:$F$293=K$5)*(COUNTIF(Themen!$K$5:$K$8,Drucksachen!$E$2:$E$293)>0))>0,1,0) | L6: =IF(SUMPRODUCT(ISNUMBER(SEARCH($H6,Drucksachen!$I$2:$I$293))*(Drucksachen!$F$2:$F$293=L$5)*(COUNTIF(Themen!$K$5:$K$8,Drucksachen!$E$2:$E$293)>0))>0,1,0)
A7: davon Antraege und Gesetzentwuerfe | B7: =COUNTIFS(Drucksachen!$F$2:$F$293,B$5,Drucksachen!$E$2:$E$293,"Antrag")+COUNTIFS(Drucksachen!$F$2:$F$293,B$5,Drucksachen!$E$2:$E$293,"Entschließungsantrag")+COUNTIFS(Drucksachen!$F$2:$F$293,B$5,Drucksachen!$E$2:$E$293,"Gesetzentwurf") | C7: =COUNTIFS(Drucksachen!$F$2:$F$293,C$5,Drucksachen!$E$2:$E$293,"Antrag")+COUNTIFS(Drucksachen!$F$2:$F$293,C$5,Drucksachen!$E$2:$E$293,"Entschließungsantrag")+COUNTIFS(Drucksachen!$F$2:$F$293,C$5,Drucksachen!$E$2:$E$293,"Gesetzentwurf") | D7: =COUNTIFS(Drucksachen!$F$2:$F$293,D$5,Drucksachen!$E$2:$E$293,"Antrag")+COUNTIFS(Drucksachen!$F$2:$F$293,D$5,Drucksachen!$E$2:$E$293,"Entschließungsantrag")+COUNTIFS(Drucksachen!$F$2:$F$293,D$5,Drucksachen!$E$2:$E$293,"Gesetzentwurf") | E7: =COUNTIFS(Drucksachen!$F$2:$F$293,E$5,Drucksachen!$E$2:$E$293,"Antrag")+COUNTIFS(Drucksachen!$F$2:$F$293,E$5,Drucksachen!$E$2:$E$293,"Entschließungsantrag")+COUNTIFS(Drucksachen!$F$2:$F$293,E$5,Drucksachen!$E$2:$E$293,"Gesetzentwurf") | F7: Anzahl | H7: Kriminalitaet | I7: =IF(SUMPRODUCT(ISNUMBER(SEARCH($H7,Drucksachen!$I$2:$I$293))*(Drucksachen!$F$2:$F$293=I$5)*(COUNTIF(Themen!$K$5:$K$8,Drucksachen!$E$2:$E$293)>0))>0,1,0) | J7: =IF(SUMPRODUCT(ISNUMBER(SEARCH($H7,Drucksachen!$I$2:$I$293))*(Drucksachen!$F$2:$F$293=J$5)*(COUNTIF(Themen!$K$5:$K$8,Drucksachen!$E$2:$E$293)>0))>0,1,0) | K7: =IF(SUMPRODUCT(ISNUMBER(SEARCH($H7,Drucksachen!$I$2:$I$293))*(Drucksachen!$F$2:$F$293=K$5)*(COUNTIF(Themen!$K$5:$K$8,Drucksachen!$E$2:$E$293)>0))>0,1,0) | L7: =IF(SUMPRODUCT(ISNUMBER(SEARCH($H7,Drucksachen!$I$2:$I$293))*(Drucksachen!$F$2:$F$293=L$5)*(COUNTIF(Themen!$K$5:$K$8,Drucksachen!$E$2:$E$293)>0))>0,1,0)
A8: davon zur Abstimmung gelangt | B8: =COUNTIFS(Drucksachen!$F$2:$F$293,B$5,Drucksachen!$E$2:$E$293,"Antrag",Drucksachen!$R$2:$R$293,1)+COUNTIFS(Drucksachen!$F$2:$F$293,B$5,Drucksachen!$E$2:$E$293,"Entschließungsantrag",Drucksachen!$R$2:$R$293,1)+COUNTIFS(Drucksachen!$F$2:$F$293,B$5,Drucksachen!$E$2:$E$293,"Gesetzentwurf",Drucksachen!$R$2:$R$293,1) | C8: =COUNTIFS(Drucksachen!$F$2:$F$293,C$5,Drucksachen!$E$2:$E$293,"Antrag",Drucksachen!$R$2:$R$293,1)+COUNTIFS(Drucksachen!$F$2:$F$293,C$5,Drucksachen!$E$2:$E$293,"Entschließungsantrag",Drucksachen!$R$2:$R$293,1)+COUNTIFS(Drucksachen!$F$2:$F$293,C$5,Drucksachen!$E$2:$E$293,"Gesetzentwurf",Drucksachen!$R$2:$R$293,1) | D8: =COUNTIFS(Drucksachen!$F$2:$F$293,D$5,Drucksachen!$E$2:$E$293,"Antrag",Drucksachen!$R$2:$R$293,1)+COUNTIFS(Drucksachen!$F$2:$F$293,D$5,Drucksachen!$E$2:$E$293,"Entschließungsantrag",Drucksachen!$R$2:$R$293,1)+COUNTIFS(Drucksachen!$F$2:$F$293,D$5,Drucksachen!$E$2:$E$293,"Gesetzentwurf",Drucksachen!$R$2:$R$293,1) | E8: =COUNTIFS(Drucksachen!$F$2:$F$293,E$5,Drucksachen!$E$2:$E$293,"Antrag",Drucksachen!$R$2:$R$293,1)+COUNTIFS(Drucksachen!$F$2:$F$293,E$5,Drucksachen!$E$2:$E$293,"Entschließungsantrag",Drucksachen!$R$2:$R$293,1)+COUNTIFS(Drucksachen!$F$2:$F$293,E$5,Drucksachen!$E$2:$E$293,"Gesetzentwurf",Drucksachen!$R$2:$R$293,1) | F8: Anzahl | H8: Sonstiges | I8: =IF(SUMPRODUCT(ISNUMBER(SEARCH($H8,Drucksachen!$I$2:$I$293))*(Drucksachen!$F$2:$F$293=I$5)*(COUNTIF(Themen!$K$5:$K$8,Drucksachen!$E$2:$E$293)>0))>0,1,0) | J8: =IF(SUMPRODUCT(ISNUMBER(SEARCH($H8,Drucksachen!$I$2:$I$293))*(Drucksachen!$F$2:$F$293=J$5)*(COUNTIF(Themen!$K$5:$K$8,Drucksachen!$E$2:$E$293)>0))>0,1,0) | K8: =IF(SUMPRODUCT(ISNUMBER(SEARCH($H8,Drucksachen!$I$2:$I$293))*(Drucksachen!$F$2:$F$293=K$5)*(COUNTIF(Themen!$K$5:$K$8,Drucksachen!$E$2:$E$293)>0))>0,1,0) | L8: =IF(SUMPRODUCT(ISNUMBER(SEARCH($H8,Drucksachen!$I$2:$I$293))*(Drucksachen!$F$2:$F$293=L$5)*(COUNTIF(Themen!$K$5:$K$8,Drucksachen!$E$2:$E$293)>0))>0,1,0)
A9: davon Teil einer Serie | B9: =COUNTIFS(Drucksachen!$F$2:$F$293,B$5,Drucksachen!$E$2:$E$293,"Kleine Anfrage",Drucksachen!$Q$2:$Q$293,"<>")+COUNTIFS(Drucksachen!$F$2:$F$293,B$5,Drucksachen!$E$2:$E$293,"Antrag",Drucksachen!$Q$2:$Q$293,"<>")+COUNTIFS(Drucksachen!$F$2:$F$293,B$5,Drucksachen!$E$2:$E$293,"Entschließungsantrag",Drucksachen!$Q$2:$Q$293,"<>")+COUNTIFS(Drucksachen!$F$2:$F$293,B$5,Drucksachen!$E$2:$E$293,"Gesetzentwurf",Drucksachen!$Q$2:$Q$293,"<>") | C9: =COUNTIFS(Drucksachen!$F$2:$F$293,C$5,Drucksachen!$E$2:$E$293,"Kleine Anfrage",Drucksachen!$Q$2:$Q$293,"<>")+COUNTIFS(Drucksachen!$F$2:$F$293,C$5,Drucksachen!$E$2:$E$293,"Antrag",Drucksachen!$Q$2:$Q$293,"<>")+COUNTIFS(Drucksachen!$F$2:$F$293,C$5,Drucksachen!$E$2:$E$293,"Entschließungsantrag",Drucksachen!$Q$2:$Q$293,"<>")+COUNTIFS(Drucksachen!$F$2:$F$293,C$5,Drucksachen!$E$2:$E$293,"Gesetzentwurf",Drucksachen!$Q$2:$Q$293,"<>") | D9: =COUNTIFS(Drucksachen!$F$2:$F$293,D$5,Drucksachen!$E$2:$E$293,"Kleine Anfrage",Drucksachen!$Q$2:$Q$293,"<>")+COUNTIFS(Drucksachen!$F$2:$F$293,D$5,Drucksachen!$E$2:$E$293,"Antrag",Drucksachen!$Q$2:$Q$293,"<>")+COUNTIFS(Drucksachen!$F$2:$F$293,D$5,Drucksachen!$E$2:$E$293,"Entschließungsantrag",Drucksachen!$Q$2:$Q$293,"<>")+COUNTIFS(Drucksachen!$F$2:$F$293,D$5,Drucksachen!$E$2:$E$293,"Gesetzentwurf",Drucksachen!$Q$2:$Q$293,"<>") | E9: =COUNTIFS(Drucksachen!$F$2:$F$293,E$5,Drucksachen!$E$2:$E$293,"Kleine Anfrage",Drucksachen!$Q$2:$Q$293,"<>")+COUNTIFS(Drucksachen!$F$2:$F$293,E$5,Drucksachen!$E$2:$E$293,"Antrag",Drucksachen!$Q$2:$Q$293,"<>")+COUNTIFS(Drucksachen!$F$2:$F$293,E$5,Drucksachen!$E$2:$E$293,"Entschließungsantrag",Drucksachen!$Q$2:$Q$293,"<>")+COUNTIFS(Drucksachen!$F$2:$F$293,E$5,Drucksachen!$E$2:$E$293,"Gesetzentwurf",Drucksachen!$Q$2:$Q$293,"<>") | F9: Anzahl | H9: Infrastruktur/Netz | I9: =IF(SUMPRODUCT(ISNUMBER(SEARCH($H9,Drucksachen!$I$2:$I$293))*(Drucksachen!$F$2:$F$293=I$5)*(COUNTIF(Themen!$K$5:$K$8,Drucksachen!$E$2:$E$293)>0))>0,1,0) | J9: =IF(SUMPRODUCT(ISNUMBER(SEARCH($H9,Drucksachen!$I$2:$I$293))*(Drucksachen!$F$2:$F$293=J$5)*(COUNTIF(Themen!$K$5:$K$8,Drucksachen!$E$2:$E$293)>0))>0,1,0) | K9: =IF(SUMPRODUCT(ISNUMBER(SEARCH($H9,Drucksachen!$I$2:$I$293))*(Drucksachen!$F$2:$F$293=K$5)*(COUNTIF(Themen!$K$5:$K$8,Drucksachen!$E$2:$E$293)>0))>0,1,0) | L9: =IF(SUMPRODUCT(ISNUMBER(SEARCH($H9,Drucksachen!$I$2:$I$293))*(Drucksachen!$F$2:$F$293=L$5)*(COUNTIF(Themen!$K$5:$K$8,Drucksachen!$E$2:$E$293)>0))>0,1,0)
A10: davon im Halbjahr vor einer Bundestagswahl | B10: =COUNTIFS(Drucksachen!$F$2:$F$293,B$5,Drucksachen!$A$2:$A$293,">="&DATE(2025,2,23)-183,Drucksachen!$A$2:$A$293,"<="&DATE(2025,2,23)) | C10: =COUNTIFS(Drucksachen!$F$2:$F$293,C$5,Drucksachen!$A$2:$A$293,">="&DATE(2025,2,23)-183,Drucksachen!$A$2:$A$293,"<="&DATE(2025,2,23)) | D10: =COUNTIFS(Drucksachen!$F$2:$F$293,D$5,Drucksachen!$A$2:$A$293,">="&DATE(2025,2,23)-183,Drucksachen!$A$2:$A$293,"<="&DATE(2025,2,23)) | E10: =COUNTIFS(Drucksachen!$F$2:$F$293,E$5,Drucksachen!$A$2:$A$293,">="&DATE(2025,2,23)-183,Drucksachen!$A$2:$A$293,"<="&DATE(2025,2,23)) | F10: Anzahl, 1 Termin(e) im Bestand | H10: Konzernstruktur/DB AG | I10: =IF(SUMPRODUCT(ISNUMBER(SEARCH($H10,Drucksachen!$I$2:$I$293))*(Drucksachen!$F$2:$F$293=I$5)*(COUNTIF(Themen!$K$5:$K$8,Drucksachen!$E$2:$E$293)>0))>0,1,0) | J10: =IF(SUMPRODUCT(ISNUMBER(SEARCH($H10,Drucksachen!$I$2:$I$293))*(Drucksachen!$F$2:$F$293=J$5)*(COUNTIF(Themen!$K$5:$K$8,Drucksachen!$E$2:$E$293)>0))>0,1,0) | K10: =IF(SUMPRODUCT(ISNUMBER(SEARCH($H10,Drucksachen!$I$2:$I$293))*(Drucksachen!$F$2:$F$293=K$5)*(COUNTIF(Themen!$K$5:$K$8,Drucksachen!$E$2:$E$293)>0))>0,1,0) | L10: =IF(SUMPRODUCT(ISNUMBER(SEARCH($H10,Drucksachen!$I$2:$I$293))*(Drucksachen!$F$2:$F$293=L$5)*(COUNTIF(Themen!$K$5:$K$8,Drucksachen!$E$2:$E$293)>0))>0,1,0)
A11: beruehrte Sachthemen | B11: =SUM(I$6:I$19) | C11: =SUM(J$6:J$19) | D11: =SUM(K$6:K$19) | E11: =SUM(L$6:L$19) | F11: von 14 | H11: Sicherheit | I11: =IF(SUMPRODUCT(ISNUMBER(SEARCH($H11,Drucksachen!$I$2:$I$293))*(Drucksachen!$F$2:$F$293=I$5)*(COUNTIF(Themen!$K$5:$K$8,Drucksachen!$E$2:$E$293)>0))>0,1,0) | J11: =IF(SUMPRODUCT(ISNUMBER(SEARCH($H11,Drucksachen!$I$2:$I$293))*(Drucksachen!$F$2:$F$293=J$5)*(COUNTIF(Themen!$K$5:$K$8,Drucksachen!$E$2:$E$293)>0))>0,1,0) | K11: =IF(SUMPRODUCT(ISNUMBER(SEARCH($H11,Drucksachen!$I$2:$I$293))*(Drucksachen!$F$2:$F$293=K$5)*(COUNTIF(Themen!$K$5:$K$8,Drucksachen!$E$2:$E$293)>0))>0,1,0) | L11: =IF(SUMPRODUCT(ISNUMBER(SEARCH($H11,Drucksachen!$I$2:$I$293))*(Drucksachen!$F$2:$F$293=L$5)*(COUNTIF(Themen!$K$5:$K$8,Drucksachen!$E$2:$E$293)>0))>0,1,0)
A12: Quartale mit eigener Aktivitaet | B12: =SUM(I$21:I$40) | C12: =SUM(J$21:J$40) | D12: =SUM(K$21:K$40) | E12: =SUM(L$21:L$40) | F12: von 20 | H12: Finanzierung | I12: =IF(SUMPRODUCT(ISNUMBER(SEARCH($H12,Drucksachen!$I$2:$I$293))*(Drucksachen!$F$2:$F$293=I$5)*(COUNTIF(Themen!$K$5:$K$8,Drucksachen!$E$2:$E$293)>0))>0,1,0) | J12: =IF(SUMPRODUCT(ISNUMBER(SEARCH($H12,Drucksachen!$I$2:$I$293))*(Drucksachen!$F$2:$F$293=J$5)*(COUNTIF(Themen!$K$5:$K$8,Drucksachen!$E$2:$E$293)>0))>0,1,0) | K12: =IF(SUMPRODUCT(ISNUMBER(SEARCH($H12,Drucksachen!$I$2:$I$293))*(Drucksachen!$F$2:$F$293=K$5)*(COUNTIF(Themen!$K$5:$K$8,Drucksachen!$E$2:$E$293)>0))>0,1,0) | L12: =IF(SUMPRODUCT(ISNUMBER(SEARCH($H12,Drucksachen!$I$2:$I$293))*(Drucksachen!$F$2:$F$293=L$5)*(COUNTIF(Themen!$K$5:$K$8,Drucksachen!$E$2:$E$293)>0))>0,1,0)
H13: Puenktlichkeit/Qualitaet | I13: =IF(SUMPRODUCT(ISNUMBER(SEARCH($H13,Drucksachen!$I$2:$I$293))*(Drucksachen!$F$2:$F$293=I$5)*(COUNTIF(Themen!$K$5:$K$8,Drucksachen!$E$2:$E$293)>0))>0,1,0) | J13: =IF(SUMPRODUCT(ISNUMBER(SEARCH($H13,Drucksachen!$I$2:$I$293))*(Drucksachen!$F$2:$F$293=J$5)*(COUNTIF(Themen!$K$5:$K$8,Drucksachen!$E$2:$E$293)>0))>0,1,0) | K13: =IF(SUMPRODUCT(ISNUMBER(SEARCH($H13,Drucksachen!$I$2:$I$293))*(Drucksachen!$F$2:$F$293=K$5)*(COUNTIF(Themen!$K$5:$K$8,Drucksachen!$E$2:$E$293)>0))>0,1,0) | L13: =IF(SUMPRODUCT(ISNUMBER(SEARCH($H13,Drucksachen!$I$2:$I$293))*(Drucksachen!$F$2:$F$293=L$5)*(COUNTIF(Themen!$K$5:$K$8,Drucksachen!$E$2:$E$293)>0))>0,1,0)
A14: Schritt 2: Indikatoren, je Zeile Spitzenreiter = 100 | H14: Barrierefreiheit | I14: =IF(SUMPRODUCT(ISNUMBER(SEARCH($H14,Drucksachen!$I$2:$I$293))*(Drucksachen!$F$2:$F$293=I$5)*(COUNTIF(Themen!$K$5:$K$8,Drucksachen!$E$2:$E$293)>0))>0,1,0) | J14: =IF(SUMPRODUCT(ISNUMBER(SEARCH($H14,Drucksachen!$I$2:$I$293))*(Drucksachen!$F$2:$F$293=J$5)*(COUNTIF(Themen!$K$5:$K$8,Drucksachen!$E$2:$E$293)>0))>0,1,0) | K14: =IF(SUMPRODUCT(ISNUMBER(SEARCH($H14,Drucksachen!$I$2:$I$293))*(Drucksachen!$F$2:$F$293=K$5)*(COUNTIF(Themen!$K$5:$K$8,Drucksachen!$E$2:$E$293)>0))>0,1,0) | L14: =IF(SUMPRODUCT(ISNUMBER(SEARCH($H14,Drucksachen!$I$2:$I$293))*(Drucksachen!$F$2:$F$293=L$5)*(COUNTIF(Themen!$K$5:$K$8,Drucksachen!$E$2:$E$293)>0))>0,1,0)
A15: Die gelben Zellen sind deine. Aendere die Gewichte und der Score unten rechnet sich neu. Negative Gewichte sind erlaubt, wenn du einen Indikator als Minuspunkt verstehst. | H15: Deutschlandticket | I15: =IF(SUMPRODUCT(ISNUMBER(SEARCH($H15,Drucksachen!$I$2:$I$293))*(Drucksachen!$F$2:$F$293=I$5)*(COUNTIF(Themen!$K$5:$K$8,Drucksachen!$E$2:$E$293)>0))>0,1,0) | J15: =IF(SUMPRODUCT(ISNUMBER(SEARCH($H15,Drucksachen!$I$2:$I$293))*(Drucksachen!$F$2:$F$293=J$5)*(COUNTIF(Themen!$K$5:$K$8,Drucksachen!$E$2:$E$293)>0))>0,1,0) | K15: =IF(SUMPRODUCT(ISNUMBER(SEARCH($H15,Drucksachen!$I$2:$I$293))*(Drucksachen!$F$2:$F$293=K$5)*(COUNTIF(Themen!$K$5:$K$8,Drucksachen!$E$2:$E$293)>0))>0,1,0) | L15: =IF(SUMPRODUCT(ISNUMBER(SEARCH($H15,Drucksachen!$I$2:$I$293))*(Drucksachen!$F$2:$F$293=L$5)*(COUNTIF(Themen!$K$5:$K$8,Drucksachen!$E$2:$E$293)>0))>0,1,0)
H16: Nahverkehr/SPNV | I16: =IF(SUMPRODUCT(ISNUMBER(SEARCH($H16,Drucksachen!$I$2:$I$293))*(Drucksachen!$F$2:$F$293=I$5)*(COUNTIF(Themen!$K$5:$K$8,Drucksachen!$E$2:$E$293)>0))>0,1,0) | J16: =IF(SUMPRODUCT(ISNUMBER(SEARCH($H16,Drucksachen!$I$2:$I$293))*(Drucksachen!$F$2:$F$293=J$5)*(COUNTIF(Themen!$K$5:$K$8,Drucksachen!$E$2:$E$293)>0))>0,1,0) | K16: =IF(SUMPRODUCT(ISNUMBER(SEARCH($H16,Drucksachen!$I$2:$I$293))*(Drucksachen!$F$2:$F$293=K$5)*(COUNTIF(Themen!$K$5:$K$8,Drucksachen!$E$2:$E$293)>0))>0,1,0) | L16: =IF(SUMPRODUCT(ISNUMBER(SEARCH($H16,Drucksachen!$I$2:$I$293))*(Drucksachen!$F$2:$F$293=L$5)*(COUNTIF(Themen!$K$5:$K$8,Drucksachen!$E$2:$E$293)>0))>0,1,0)
A17: Indikator | B17: Gewicht | C17: CDU/CSU | D17: Gruene | E17: AfD | F17: Linke | G17: Was er misst | H17: Deutschlandtakt/Fahrplan | I17: =IF(SUMPRODUCT(ISNUMBER(SEARCH($H17,Drucksachen!$I$2:$I$293))*(Drucksachen!$F$2:$F$293=I$5)*(COUNTIF(Themen!$K$5:$K$8,Drucksachen!$E$2:$E$293)>0))>0,1,0) | J17: =IF(SUMPRODUCT(ISNUMBER(SEARCH($H17,Drucksachen!$I$2:$I$293))*(Drucksachen!$F$2:$F$293=J$5)*(COUNTIF(Themen!$K$5:$K$8,Drucksachen!$E$2:$E$293)>0))>0,1,0) | K17: =IF(SUMPRODUCT(ISNUMBER(SEARCH($H17,Drucksachen!$I$2:$I$293))*(Drucksachen!$F$2:$F$293=K$5)*(COUNTIF(Themen!$K$5:$K$8,Drucksachen!$E$2:$E$293)>0))>0,1,0) | L17: =IF(SUMPRODUCT(ISNUMBER(SEARCH($H17,Drucksachen!$I$2:$I$293))*(Drucksachen!$F$2:$F$293=L$5)*(COUNTIF(Themen!$K$5:$K$8,Drucksachen!$E$2:$E$293)>0))>0,1,0)
A18: Aktivitaet | B18: 10 | C18: =IFERROR(ROUND((B6)/MAX(B6,C6,D6,E6)*100,0),0) | D18: =IFERROR(ROUND((C6)/MAX(B6,C6,D6,E6)*100,0),0) | E18: =IFERROR(ROUND((D6)/MAX(B6,C6,D6,E6)*100,0),0) | F18: =IFERROR(ROUND((E6)/MAX(B6,C6,D6,E6)*100,0),0) | G18: Menge der eigenen Initiativen. Sagt nichts ueber Gehalt | H18: Personal | I18: =IF(SUMPRODUCT(ISNUMBER(SEARCH($H18,Drucksachen!$I$2:$I$293))*(Drucksachen!$F$2:$F$293=I$5)*(COUNTIF(Themen!$K$5:$K$8,Drucksachen!$E$2:$E$293)>0))>0,1,0) | J18: =IF(SUMPRODUCT(ISNUMBER(SEARCH($H18,Drucksachen!$I$2:$I$293))*(Drucksachen!$F$2:$F$293=J$5)*(COUNTIF(Themen!$K$5:$K$8,Drucksachen!$E$2:$E$293)>0))>0,1,0) | K18: =IF(SUMPRODUCT(ISNUMBER(SEARCH($H18,Drucksachen!$I$2:$I$293))*(Drucksachen!$F$2:$F$293=K$5)*(COUNTIF(Themen!$K$5:$K$8,Drucksachen!$E$2:$E$293)>0))>0,1,0) | L18: =IF(SUMPRODUCT(ISNUMBER(SEARCH($H18,Drucksachen!$I$2:$I$293))*(Drucksachen!$F$2:$F$293=L$5)*(COUNTIF(Themen!$K$5:$K$8,Drucksachen!$E$2:$E$293)>0))>0,1,0)
A19: Gestaltungsanteil | B19: 25 | C19: =IFERROR(ROUND((IFERROR(B7/B6*100,0))/MAX(IFERROR(B7/B6*100,0),IFERROR(C7/C6*100,0),IFERROR(D7/D6*100,0),IFERROR(E7/E6*100,0))*100,0),0) | D19: =IFERROR(ROUND((IFERROR(C7/C6*100,0))/MAX(IFERROR(B7/B6*100,0),IFERROR(C7/C6*100,0),IFERROR(D7/D6*100,0),IFERROR(E7/E6*100,0))*100,0),0) | E19: =IFERROR(ROUND((IFERROR(D7/D6*100,0))/MAX(IFERROR(B7/B6*100,0),IFERROR(C7/C6*100,0),IFERROR(D7/D6*100,0),IFERROR(E7/E6*100,0))*100,0),0) | F19: =IFERROR(ROUND((IFERROR(E7/E6*100,0))/MAX(IFERROR(B7/B6*100,0),IFERROR(C7/C6*100,0),IFERROR(D7/D6*100,0),IFERROR(E7/E6*100,0))*100,0),0) | G19: Antrag und Gesetzentwurf statt nur Nachfragen | H19: Gueterverkehr | I19: =IF(SUMPRODUCT(ISNUMBER(SEARCH($H19,Drucksachen!$I$2:$I$293))*(Drucksachen!$F$2:$F$293=I$5)*(COUNTIF(Themen!$K$5:$K$8,Drucksachen!$E$2:$E$293)>0))>0,1,0) | J19: =IF(SUMPRODUCT(ISNUMBER(SEARCH($H19,Drucksachen!$I$2:$I$293))*(Drucksachen!$F$2:$F$293=J$5)*(COUNTIF(Themen!$K$5:$K$8,Drucksachen!$E$2:$E$293)>0))>0,1,0) | K19: =IF(SUMPRODUCT(ISNUMBER(SEARCH($H19,Drucksachen!$I$2:$I$293))*(Drucksachen!$F$2:$F$293=K$5)*(COUNTIF(Themen!$K$5:$K$8,Drucksachen!$E$2:$E$293)>0))>0,1,0) | L19: =IF(SUMPRODUCT(ISNUMBER(SEARCH($H19,Drucksachen!$I$2:$I$293))*(Drucksachen!$F$2:$F$293=L$5)*(COUNTIF(Themen!$K$5:$K$8,Drucksachen!$E$2:$E$293)>0))>0,1,0)
A20: Themenbreite | B20: 20 | C20: =IFERROR(ROUND((B11)/MAX(B11,C11,D11,E11)*100,0),0) | D20: =IFERROR(ROUND((C11)/MAX(B11,C11,D11,E11)*100,0),0) | E20: =IFERROR(ROUND((D11)/MAX(B11,C11,D11,E11)*100,0),0) | F20: =IFERROR(ROUND((E11)/MAX(B11,C11,D11,E11)*100,0),0) | G20: Ganze Bahnpolitik oder ein Steckenpferd. Haengt an der Menge
A21: Beharrlichkeit | B21: 15 | C21: =IFERROR(ROUND((B12)/MAX(B12,C12,D12,E12)*100,0),0) | D21: =IFERROR(ROUND((C12)/MAX(B12,C12,D12,E12)*100,0),0) | E21: =IFERROR(ROUND((D12)/MAX(B12,C12,D12,E12)*100,0),0) | F21: =IFERROR(ROUND((E12)/MAX(B12,C12,D12,E12)*100,0),0) | G21: Dauerhaft dran oder nur zu Anlaessen | H21: 2021-Q4 | I21: =IF(COUNTIFS(Drucksachen!$C$2:$C$293,$H21,Drucksachen!$F$2:$F$293,I$5,Drucksachen!$E$2:$E$293,"Kleine Anfrage")+COUNTIFS(Drucksachen!$C$2:$C$293,$H21,Drucksachen!$F$2:$F$293,I$5,Drucksachen!$E$2:$E$293,"Antrag")>0,1,0) | J21: =IF(COUNTIFS(Drucksachen!$C$2:$C$293,$H21,Drucksachen!$F$2:$F$293,J$5,Drucksachen!$E$2:$E$293,"Kleine Anfrage")+COUNTIFS(Drucksachen!$C$2:$C$293,$H21,Drucksachen!$F$2:$F$293,J$5,Drucksachen!$E$2:$E$293,"Antrag")>0,1,0) | K21: =IF(COUNTIFS(Drucksachen!$C$2:$C$293,$H21,Drucksachen!$F$2:$F$293,K$5,Drucksachen!$E$2:$E$293,"Kleine Anfrage")+COUNTIFS(Drucksachen!$C$2:$C$293,$H21,Drucksachen!$F$2:$F$293,K$5,Drucksachen!$E$2:$E$293,"Antrag")>0,1,0) | L21: =IF(COUNTIFS(Drucksachen!$C$2:$C$293,$H21,Drucksachen!$F$2:$F$293,L$5,Drucksachen!$E$2:$E$293,"Kleine Anfrage")+COUNTIFS(Drucksachen!$C$2:$C$293,$H21,Drucksachen!$F$2:$F$293,L$5,Drucksachen!$E$2:$E$293,"Antrag")>0,1,0)
A22: Durchsetzungsversuch | B22: 10 | C22: =IFERROR(ROUND((IFERROR(B8/B7*100,0))/MAX(IFERROR(B8/B7*100,0),IFERROR(C8/C7*100,0),IFERROR(D8/D7*100,0),IFERROR(E8/E7*100,0))*100,0),0) | D22: =IFERROR(ROUND((IFERROR(C8/C7*100,0))/MAX(IFERROR(B8/B7*100,0),IFERROR(C8/C7*100,0),IFERROR(D8/D7*100,0),IFERROR(E8/E7*100,0))*100,0),0) | E22: =IFERROR(ROUND((IFERROR(D8/D7*100,0))/MAX(IFERROR(B8/B7*100,0),IFERROR(C8/C7*100,0),IFERROR(D8/D7*100,0),IFERROR(E8/E7*100,0))*100,0),0) | F22: =IFERROR(ROUND((IFERROR(E8/E7*100,0))/MAX(IFERROR(B8/B7*100,0),IFERROR(C8/C7*100,0),IFERROR(D8/D7*100,0),IFERROR(E8/E7*100,0))*100,0),0) | G22: Anteil mit Sachentscheidung, Ueberweisung zaehlt nicht | H22: 2022-Q1 | I22: =IF(COUNTIFS(Drucksachen!$C$2:$C$293,$H22,Drucksachen!$F$2:$F$293,I$5,Drucksachen!$E$2:$E$293,"Kleine Anfrage")+COUNTIFS(Drucksachen!$C$2:$C$293,$H22,Drucksachen!$F$2:$F$293,I$5,Drucksachen!$E$2:$E$293,"Antrag")>0,1,0) | J22: =IF(COUNTIFS(Drucksachen!$C$2:$C$293,$H22,Drucksachen!$F$2:$F$293,J$5,Drucksachen!$E$2:$E$293,"Kleine Anfrage")+COUNTIFS(Drucksachen!$C$2:$C$293,$H22,Drucksachen!$F$2:$F$293,J$5,Drucksachen!$E$2:$E$293,"Antrag")>0,1,0) | K22: =IF(COUNTIFS(Drucksachen!$C$2:$C$293,$H22,Drucksachen!$F$2:$F$293,K$5,Drucksachen!$E$2:$E$293,"Kleine Anfrage")+COUNTIFS(Drucksachen!$C$2:$C$293,$H22,Drucksachen!$F$2:$F$293,K$5,Drucksachen!$E$2:$E$293,"Antrag")>0,1,0) | L22: =IF(COUNTIFS(Drucksachen!$C$2:$C$293,$H22,Drucksachen!$F$2:$F$293,L$5,Drucksachen!$E$2:$E$293,"Kleine Anfrage")+COUNTIFS(Drucksachen!$C$2:$C$293,$H22,Drucksachen!$F$2:$F$293,L$5,Drucksachen!$E$2:$E$293,"Antrag")>0,1,0)
A23: Eigenstaendigkeit | B23: 10 | C23: =IFERROR(ROUND((100-IFERROR(B9/B6*100,0))/MAX(100-IFERROR(B9/B6*100,0),100-IFERROR(C9/C6*100,0),100-IFERROR(D9/D6*100,0),100-IFERROR(E9/E6*100,0))*100,0),0) | D23: =IFERROR(ROUND((100-IFERROR(C9/C6*100,0))/MAX(100-IFERROR(B9/B6*100,0),100-IFERROR(C9/C6*100,0),100-IFERROR(D9/D6*100,0),100-IFERROR(E9/E6*100,0))*100,0),0) | E23: =IFERROR(ROUND((100-IFERROR(D9/D6*100,0))/MAX(100-IFERROR(B9/B6*100,0),100-IFERROR(C9/C6*100,0),100-IFERROR(D9/D6*100,0),100-IFERROR(E9/E6*100,0))*100,0),0) | F23: =IFERROR(ROUND((100-IFERROR(E9/E6*100,0))/MAX(100-IFERROR(B9/B6*100,0),100-IFERROR(C9/C6*100,0),100-IFERROR(D9/D6*100,0),100-IFERROR(E9/E6*100,0))*100,0),0) | G23: Gegenteil von Serienanfragen im festen Takt | H23: 2022-Q2 | I23: =IF(COUNTIFS(Drucksachen!$C$2:$C$293,$H23,Drucksachen!$F$2:$F$293,I$5,Drucksachen!$E$2:$E$293,"Kleine Anfrage")+COUNTIFS(Drucksachen!$C$2:$C$293,$H23,Drucksachen!$F$2:$F$293,I$5,Drucksachen!$E$2:$E$293,"Antrag")>0,1,0) | J23: =IF(COUNTIFS(Drucksachen!$C$2:$C$293,$H23,Drucksachen!$F$2:$F$293,J$5,Drucksachen!$E$2:$E$293,"Kleine Anfrage")+COUNTIFS(Drucksachen!$C$2:$C$293,$H23,Drucksachen!$F$2:$F$293,J$5,Drucksachen!$E$2:$E$293,"Antrag")>0,1,0) | K23: =IF(COUNTIFS(Drucksachen!$C$2:$C$293,$H23,Drucksachen!$F$2:$F$293,K$5,Drucksachen!$E$2:$E$293,"Kleine Anfrage")+COUNTIFS(Drucksachen!$C$2:$C$293,$H23,Drucksachen!$F$2:$F$293,K$5,Drucksachen!$E$2:$E$293,"Antrag")>0,1,0) | L23: =IF(COUNTIFS(Drucksachen!$C$2:$C$293,$H23,Drucksachen!$F$2:$F$293,L$5,Drucksachen!$E$2:$E$293,"Kleine Anfrage")+COUNTIFS(Drucksachen!$C$2:$C$293,$H23,Drucksachen!$F$2:$F$293,L$5,Drucksachen!$E$2:$E$293,"Antrag")>0,1,0)
A24: Unabhaengigkeit vom Wahltermin | B24: 10 | C24: =IFERROR(ROUND((100-IFERROR(B10/B6*100,0))/MAX(100-IFERROR(B10/B6*100,0),100-IFERROR(C10/C6*100,0),100-IFERROR(D10/D6*100,0),100-IFERROR(E10/E6*100,0))*100,0),0) | D24: =IFERROR(ROUND((100-IFERROR(C10/C6*100,0))/MAX(100-IFERROR(B10/B6*100,0),100-IFERROR(C10/C6*100,0),100-IFERROR(D10/D6*100,0),100-IFERROR(E10/E6*100,0))*100,0),0) | E24: =IFERROR(ROUND((100-IFERROR(D10/D6*100,0))/MAX(100-IFERROR(B10/B6*100,0),100-IFERROR(C10/C6*100,0),100-IFERROR(D10/D6*100,0),100-IFERROR(E10/E6*100,0))*100,0),0) | F24: =IFERROR(ROUND((100-IFERROR(E10/E6*100,0))/MAX(100-IFERROR(B10/B6*100,0),100-IFERROR(C10/C6*100,0),100-IFERROR(D10/D6*100,0),100-IFERROR(E10/E6*100,0))*100,0),0) | G24: Arbeitet auch fern vom Wahlkampf | H24: 2022-Q3 | I24: =IF(COUNTIFS(Drucksachen!$C$2:$C$293,$H24,Drucksachen!$F$2:$F$293,I$5,Drucksachen!$E$2:$E$293,"Kleine Anfrage")+COUNTIFS(Drucksachen!$C$2:$C$293,$H24,Drucksachen!$F$2:$F$293,I$5,Drucksachen!$E$2:$E$293,"Antrag")>0,1,0) | J24: =IF(COUNTIFS(Drucksachen!$C$2:$C$293,$H24,Drucksachen!$F$2:$F$293,J$5,Drucksachen!$E$2:$E$293,"Kleine Anfrage")+COUNTIFS(Drucksachen!$C$2:$C$293,$H24,Drucksachen!$F$2:$F$293,J$5,Drucksachen!$E$2:$E$293,"Antrag")>0,1,0) | K24: =IF(COUNTIFS(Drucksachen!$C$2:$C$293,$H24,Drucksachen!$F$2:$F$293,K$5,Drucksachen!$E$2:$E$293,"Kleine Anfrage")+COUNTIFS(Drucksachen!$C$2:$C$293,$H24,Drucksachen!$F$2:$F$293,K$5,Drucksachen!$E$2:$E$293,"Antrag")>0,1,0) | L24: =IF(COUNTIFS(Drucksachen!$C$2:$C$293,$H24,Drucksachen!$F$2:$F$293,L$5,Drucksachen!$E$2:$E$293,"Kleine Anfrage")+COUNTIFS(Drucksachen!$C$2:$C$293,$H24,Drucksachen!$F$2:$F$293,L$5,Drucksachen!$E$2:$E$293,"Antrag")>0,1,0)
A25: Summe der Gewichte | B25: =SUM(B18:B24) | H25: 2022-Q4 | I25: =IF(COUNTIFS(Drucksachen!$C$2:$C$293,$H25,Drucksachen!$F$2:$F$293,I$5,Drucksachen!$E$2:$E$293,"Kleine Anfrage")+COUNTIFS(Drucksachen!$C$2:$C$293,$H25,Drucksachen!$F$2:$F$293,I$5,Drucksachen!$E$2:$E$293,"Antrag")>0,1,0) | J25: =IF(COUNTIFS(Drucksachen!$C$2:$C$293,$H25,Drucksachen!$F$2:$F$293,J$5,Drucksachen!$E$2:$E$293,"Kleine Anfrage")+COUNTIFS(Drucksachen!$C$2:$C$293,$H25,Drucksachen!$F$2:$F$293,J$5,Drucksachen!$E$2:$E$293,"Antrag")>0,1,0) | K25: =IF(COUNTIFS(Drucksachen!$C$2:$C$293,$H25,Drucksachen!$F$2:$F$293,K$5,Drucksachen!$E$2:$E$293,"Kleine Anfrage")+COUNTIFS(Drucksachen!$C$2:$C$293,$H25,Drucksachen!$F$2:$F$293,K$5,Drucksachen!$E$2:$E$293,"Antrag")>0,1,0) | L25: =IF(COUNTIFS(Drucksachen!$C$2:$C$293,$H25,Drucksachen!$F$2:$F$293,L$5,Drucksachen!$E$2:$E$293,"Kleine Anfrage")+COUNTIFS(Drucksachen!$C$2:$C$293,$H25,Drucksachen!$F$2:$F$293,L$5,Drucksachen!$E$2:$E$293,"Antrag")>0,1,0)
H26: 2023-Q1 | I26: =IF(COUNTIFS(Drucksachen!$C$2:$C$293,$H26,Drucksachen!$F$2:$F$293,I$5,Drucksachen!$E$2:$E$293,"Kleine Anfrage")+COUNTIFS(Drucksachen!$C$2:$C$293,$H26,Drucksachen!$F$2:$F$293,I$5,Drucksachen!$E$2:$E$293,"Antrag")>0,1,0) | J26: =IF(COUNTIFS(Drucksachen!$C$2:$C$293,$H26,Drucksachen!$F$2:$F$293,J$5,Drucksachen!$E$2:$E$293,"Kleine Anfrage")+COUNTIFS(Drucksachen!$C$2:$C$293,$H26,Drucksachen!$F$2:$F$293,J$5,Drucksachen!$E$2:$E$293,"Antrag")>0,1,0) | K26: =IF(COUNTIFS(Drucksachen!$C$2:$C$293,$H26,Drucksachen!$F$2:$F$293,K$5,Drucksachen!$E$2:$E$293,"Kleine Anfrage")+COUNTIFS(Drucksachen!$C$2:$C$293,$H26,Drucksachen!$F$2:$F$293,K$5,Drucksachen!$E$2:$E$293,"Antrag")>0,1,0) | L26: =IF(COUNTIFS(Drucksachen!$C$2:$C$293,$H26,Drucksachen!$F$2:$F$293,L$5,Drucksachen!$E$2:$E$293,"Kleine Anfrage")+COUNTIFS(Drucksachen!$C$2:$C$293,$H26,Drucksachen!$F$2:$F$293,L$5,Drucksachen!$E$2:$E$293,"Antrag")>0,1,0)
A27: Schritt 3: Ergebnis | H27: 2023-Q2 | I27: =IF(COUNTIFS(Drucksachen!$C$2:$C$293,$H27,Drucksachen!$F$2:$F$293,I$5,Drucksachen!$E$2:$E$293,"Kleine Anfrage")+COUNTIFS(Drucksachen!$C$2:$C$293,$H27,Drucksachen!$F$2:$F$293,I$5,Drucksachen!$E$2:$E$293,"Antrag")>0,1,0) | J27: =IF(COUNTIFS(Drucksachen!$C$2:$C$293,$H27,Drucksachen!$F$2:$F$293,J$5,Drucksachen!$E$2:$E$293,"Kleine Anfrage")+COUNTIFS(Drucksachen!$C$2:$C$293,$H27,Drucksachen!$F$2:$F$293,J$5,Drucksachen!$E$2:$E$293,"Antrag")>0,1,0) | K27: =IF(COUNTIFS(Drucksachen!$C$2:$C$293,$H27,Drucksachen!$F$2:$F$293,K$5,Drucksachen!$E$2:$E$293,"Kleine Anfrage")+COUNTIFS(Drucksachen!$C$2:$C$293,$H27,Drucksachen!$F$2:$F$293,K$5,Drucksachen!$E$2:$E$293,"Antrag")>0,1,0) | L27: =IF(COUNTIFS(Drucksachen!$C$2:$C$293,$H27,Drucksachen!$F$2:$F$293,L$5,Drucksachen!$E$2:$E$293,"Kleine Anfrage")+COUNTIFS(Drucksachen!$C$2:$C$293,$H27,Drucksachen!$F$2:$F$293,L$5,Drucksachen!$E$2:$E$293,"Antrag")>0,1,0)
A28: Fraktion | B28: Score | C28: Rolle ab WP 21 | D28: Initiativen gesamt | E28: Belastbarkeit | H28: 2023-Q3 | I28: =IF(COUNTIFS(Drucksachen!$C$2:$C$293,$H28,Drucksachen!$F$2:$F$293,I$5,Drucksachen!$E$2:$E$293,"Kleine Anfrage")+COUNTIFS(Drucksachen!$C$2:$C$293,$H28,Drucksachen!$F$2:$F$293,I$5,Drucksachen!$E$2:$E$293,"Antrag")>0,1,0) | J28: =IF(COUNTIFS(Drucksachen!$C$2:$C$293,$H28,Drucksachen!$F$2:$F$293,J$5,Drucksachen!$E$2:$E$293,"Kleine Anfrage")+COUNTIFS(Drucksachen!$C$2:$C$293,$H28,Drucksachen!$F$2:$F$293,J$5,Drucksachen!$E$2:$E$293,"Antrag")>0,1,0) | K28: =IF(COUNTIFS(Drucksachen!$C$2:$C$293,$H28,Drucksachen!$F$2:$F$293,K$5,Drucksachen!$E$2:$E$293,"Kleine Anfrage")+COUNTIFS(Drucksachen!$C$2:$C$293,$H28,Drucksachen!$F$2:$F$293,K$5,Drucksachen!$E$2:$E$293,"Antrag")>0,1,0) | L28: =IF(COUNTIFS(Drucksachen!$C$2:$C$293,$H28,Drucksachen!$F$2:$F$293,L$5,Drucksachen!$E$2:$E$293,"Kleine Anfrage")+COUNTIFS(Drucksachen!$C$2:$C$293,$H28,Drucksachen!$F$2:$F$293,L$5,Drucksachen!$E$2:$E$293,"Antrag")>0,1,0)
A29: CDU/CSU | B29: =IFERROR(SUMPRODUCT($B$18:$B$24,C$18:C$24)/SUMPRODUCT(ABS($B$18:$B$24)),0) | C29: Regierungsfraktion | D29: =B6 | E29: =IF(D29<10,"zu duenn fuer eine Aussage",IF(D29<25,"schmale Basis","belastbar")) | H29: 2023-Q4 | I29: =IF(COUNTIFS(Drucksachen!$C$2:$C$293,$H29,Drucksachen!$F$2:$F$293,I$5,Drucksachen!$E$2:$E$293,"Kleine Anfrage")+COUNTIFS(Drucksachen!$C$2:$C$293,$H29,Drucksachen!$F$2:$F$293,I$5,Drucksachen!$E$2:$E$293,"Antrag")>0,1,0) | J29: =IF(COUNTIFS(Drucksachen!$C$2:$C$293,$H29,Drucksachen!$F$2:$F$293,J$5,Drucksachen!$E$2:$E$293,"Kleine Anfrage")+COUNTIFS(Drucksachen!$C$2:$C$293,$H29,Drucksachen!$F$2:$F$293,J$5,Drucksachen!$E$2:$E$293,"Antrag")>0,1,0) | K29: =IF(COUNTIFS(Drucksachen!$C$2:$C$293,$H29,Drucksachen!$F$2:$F$293,K$5,Drucksachen!$E$2:$E$293,"Kleine Anfrage")+COUNTIFS(Drucksachen!$C$2:$C$293,$H29,Drucksachen!$F$2:$F$293,K$5,Drucksachen!$E$2:$E$293,"Antrag")>0,1,0) | L29: =IF(COUNTIFS(Drucksachen!$C$2:$C$293,$H29,Drucksachen!$F$2:$F$293,L$5,Drucksachen!$E$2:$E$293,"Kleine Anfrage")+COUNTIFS(Drucksachen!$C$2:$C$293,$H29,Drucksachen!$F$2:$F$293,L$5,Drucksachen!$E$2:$E$293,"Antrag")>0,1,0)
A30: Gruene | B30: =IFERROR(SUMPRODUCT($B$18:$B$24,D$18:D$24)/SUMPRODUCT(ABS($B$18:$B$24)),0) | C30: Opposition | D30: =C6 | E30: =IF(D30<10,"zu duenn fuer eine Aussage",IF(D30<25,"schmale Basis","belastbar")) | H30: 2024-Q1 | I30: =IF(COUNTIFS(Drucksachen!$C$2:$C$293,$H30,Drucksachen!$F$2:$F$293,I$5,Drucksachen!$E$2:$E$293,"Kleine Anfrage")+COUNTIFS(Drucksachen!$C$2:$C$293,$H30,Drucksachen!$F$2:$F$293,I$5,Drucksachen!$E$2:$E$293,"Antrag")>0,1,0) | J30: =IF(COUNTIFS(Drucksachen!$C$2:$C$293,$H30,Drucksachen!$F$2:$F$293,J$5,Drucksachen!$E$2:$E$293,"Kleine Anfrage")+COUNTIFS(Drucksachen!$C$2:$C$293,$H30,Drucksachen!$F$2:$F$293,J$5,Drucksachen!$E$2:$E$293,"Antrag")>0,1,0) | K30: =IF(COUNTIFS(Drucksachen!$C$2:$C$293,$H30,Drucksachen!$F$2:$F$293,K$5,Drucksachen!$E$2:$E$293,"Kleine Anfrage")+COUNTIFS(Drucksachen!$C$2:$C$293,$H30,Drucksachen!$F$2:$F$293,K$5,Drucksachen!$E$2:$E$293,"Antrag")>0,1,0) | L30: =IF(COUNTIFS(Drucksachen!$C$2:$C$293,$H30,Drucksachen!$F$2:$F$293,L$5,Drucksachen!$E$2:$E$293,"Kleine Anfrage")+COUNTIFS(Drucksachen!$C$2:$C$293,$H30,Drucksachen!$F$2:$F$293,L$5,Drucksachen!$E$2:$E$293,"Antrag")>0,1,0)
A31: AfD | B31: =IFERROR(SUMPRODUCT($B$18:$B$24,E$18:E$24)/SUMPRODUCT(ABS($B$18:$B$24)),0) | C31: Opposition | D31: =D6 | E31: =IF(D31<10,"zu duenn fuer eine Aussage",IF(D31<25,"schmale Basis","belastbar")) | H31: 2024-Q2 | I31: =IF(COUNTIFS(Drucksachen!$C$2:$C$293,$H31,Drucksachen!$F$2:$F$293,I$5,Drucksachen!$E$2:$E$293,"Kleine Anfrage")+COUNTIFS(Drucksachen!$C$2:$C$293,$H31,Drucksachen!$F$2:$F$293,I$5,Drucksachen!$E$2:$E$293,"Antrag")>0,1,0) | J31: =IF(COUNTIFS(Drucksachen!$C$2:$C$293,$H31,Drucksachen!$F$2:$F$293,J$5,Drucksachen!$E$2:$E$293,"Kleine Anfrage")+COUNTIFS(Drucksachen!$C$2:$C$293,$H31,Drucksachen!$F$2:$F$293,J$5,Drucksachen!$E$2:$E$293,"Antrag")>0,1,0) | K31: =IF(COUNTIFS(Drucksachen!$C$2:$C$293,$H31,Drucksachen!$F$2:$F$293,K$5,Drucksachen!$E$2:$E$293,"Kleine Anfrage")+COUNTIFS(Drucksachen!$C$2:$C$293,$H31,Drucksachen!$F$2:$F$293,K$5,Drucksachen!$E$2:$E$293,"Antrag")>0,1,0) | L31: =IF(COUNTIFS(Drucksachen!$C$2:$C$293,$H31,Drucksachen!$F$2:$F$293,L$5,Drucksachen!$E$2:$E$293,"Kleine Anfrage")+COUNTIFS(Drucksachen!$C$2:$C$293,$H31,Drucksachen!$F$2:$F$293,L$5,Drucksachen!$E$2:$E$293,"Antrag")>0,1,0)
A32: Linke | B32: =IFERROR(SUMPRODUCT($B$18:$B$24,F$18:F$24)/SUMPRODUCT(ABS($B$18:$B$24)),0) | C32: Opposition | D32: =E6 | E32: =IF(D32<10,"zu duenn fuer eine Aussage",IF(D32<25,"schmale Basis","belastbar")) | H32: 2024-Q3 | I32: =IF(COUNTIFS(Drucksachen!$C$2:$C$293,$H32,Drucksachen!$F$2:$F$293,I$5,Drucksachen!$E$2:$E$293,"Kleine Anfrage")+COUNTIFS(Drucksachen!$C$2:$C$293,$H32,Drucksachen!$F$2:$F$293,I$5,Drucksachen!$E$2:$E$293,"Antrag")>0,1,0) | J32: =IF(COUNTIFS(Drucksachen!$C$2:$C$293,$H32,Drucksachen!$F$2:$F$293,J$5,Drucksachen!$E$2:$E$293,"Kleine Anfrage")+COUNTIFS(Drucksachen!$C$2:$C$293,$H32,Drucksachen!$F$2:$F$293,J$5,Drucksachen!$E$2:$E$293,"Antrag")>0,1,0) | K32: =IF(COUNTIFS(Drucksachen!$C$2:$C$293,$H32,Drucksachen!$F$2:$F$293,K$5,Drucksachen!$E$2:$E$293,"Kleine Anfrage")+COUNTIFS(Drucksachen!$C$2:$C$293,$H32,Drucksachen!$F$2:$F$293,K$5,Drucksachen!$E$2:$E$293,"Antrag")>0,1,0) | L32: =IF(COUNTIFS(Drucksachen!$C$2:$C$293,$H32,Drucksachen!$F$2:$F$293,L$5,Drucksachen!$E$2:$E$293,"Kleine Anfrage")+COUNTIFS(Drucksachen!$C$2:$C$293,$H32,Drucksachen!$F$2:$F$293,L$5,Drucksachen!$E$2:$E$293,"Antrag")>0,1,0)
H33: 2024-Q4 | I33: =IF(COUNTIFS(Drucksachen!$C$2:$C$293,$H33,Drucksachen!$F$2:$F$293,I$5,Drucksachen!$E$2:$E$293,"Kleine Anfrage")+COUNTIFS(Drucksachen!$C$2:$C$293,$H33,Drucksachen!$F$2:$F$293,I$5,Drucksachen!$E$2:$E$293,"Antrag")>0,1,0) | J33: =IF(COUNTIFS(Drucksachen!$C$2:$C$293,$H33,Drucksachen!$F$2:$F$293,J$5,Drucksachen!$E$2:$E$293,"Kleine Anfrage")+COUNTIFS(Drucksachen!$C$2:$C$293,$H33,Drucksachen!$F$2:$F$293,J$5,Drucksachen!$E$2:$E$293,"Antrag")>0,1,0) | K33: =IF(COUNTIFS(Drucksachen!$C$2:$C$293,$H33,Drucksachen!$F$2:$F$293,K$5,Drucksachen!$E$2:$E$293,"Kleine Anfrage")+COUNTIFS(Drucksachen!$C$2:$C$293,$H33,Drucksachen!$F$2:$F$293,K$5,Drucksachen!$E$2:$E$293,"Antrag")>0,1,0) | L33: =IF(COUNTIFS(Drucksachen!$C$2:$C$293,$H33,Drucksachen!$F$2:$F$293,L$5,Drucksachen!$E$2:$E$293,"Kleine Anfrage")+COUNTIFS(Drucksachen!$C$2:$C$293,$H33,Drucksachen!$F$2:$F$293,L$5,Drucksachen!$E$2:$E$293,"Antrag")>0,1,0)
A34: Der Score ist relativ, nicht absolut: 100 heisst nur, dass eine Fraktion in allen Indikatoren die beste der hier verglichenen ist. Er sagt nichts darueber, ob das objektiv viel oder wenig ist. | H34: 2025-Q1 | I34: =IF(COUNTIFS(Drucksachen!$C$2:$C$293,$H34,Drucksachen!$F$2:$F$293,I$5,Drucksachen!$E$2:$E$293,"Kleine Anfrage")+COUNTIFS(Drucksachen!$C$2:$C$293,$H34,Drucksachen!$F$2:$F$293,I$5,Drucksachen!$E$2:$E$293,"Antrag")>0,1,0) | J34: =IF(COUNTIFS(Drucksachen!$C$2:$C$293,$H34,Drucksachen!$F$2:$F$293,J$5,Drucksachen!$E$2:$E$293,"Kleine Anfrage")+COUNTIFS(Drucksachen!$C$2:$C$293,$H34,Drucksachen!$F$2:$F$293,J$5,Drucksachen!$E$2:$E$293,"Antrag")>0,1,0) | K34: =IF(COUNTIFS(Drucksachen!$C$2:$C$293,$H34,Drucksachen!$F$2:$F$293,K$5,Drucksachen!$E$2:$E$293,"Kleine Anfrage")+COUNTIFS(Drucksachen!$C$2:$C$293,$H34,Drucksachen!$F$2:$F$293,K$5,Drucksachen!$E$2:$E$293,"Antrag")>0,1,0) | L34: =IF(COUNTIFS(Drucksachen!$C$2:$C$293,$H34,Drucksachen!$F$2:$F$293,L$5,Drucksachen!$E$2:$E$293,"Kleine Anfrage")+COUNTIFS(Drucksachen!$C$2:$C$293,$H34,Drucksachen!$F$2:$F$293,L$5,Drucksachen!$E$2:$E$293,"Antrag")>0,1,0)
H35: 2025-Q2 | I35: =IF(COUNTIFS(Drucksachen!$C$2:$C$293,$H35,Drucksachen!$F$2:$F$293,I$5,Drucksachen!$E$2:$E$293,"Kleine Anfrage")+COUNTIFS(Drucksachen!$C$2:$C$293,$H35,Drucksachen!$F$2:$F$293,I$5,Drucksachen!$E$2:$E$293,"Antrag")>0,1,0) | J35: =IF(COUNTIFS(Drucksachen!$C$2:$C$293,$H35,Drucksachen!$F$2:$F$293,J$5,Drucksachen!$E$2:$E$293,"Kleine Anfrage")+COUNTIFS(Drucksachen!$C$2:$C$293,$H35,Drucksachen!$F$2:$F$293,J$5,Drucksachen!$E$2:$E$293,"Antrag")>0,1,0) | K35: =IF(COUNTIFS(Drucksachen!$C$2:$C$293,$H35,Drucksachen!$F$2:$F$293,K$5,Drucksachen!$E$2:$E$293,"Kleine Anfrage")+COUNTIFS(Drucksachen!$C$2:$C$293,$H35,Drucksachen!$F$2:$F$293,K$5,Drucksachen!$E$2:$E$293,"Antrag")>0,1,0) | L35: =IF(COUNTIFS(Drucksachen!$C$2:$C$293,$H35,Drucksachen!$F$2:$F$293,L$5,Drucksachen!$E$2:$E$293,"Kleine Anfrage")+COUNTIFS(Drucksachen!$C$2:$C$293,$H35,Drucksachen!$F$2:$F$293,L$5,Drucksachen!$E$2:$E$293,"Antrag")>0,1,0)
H36: 2025-Q3 | I36: =IF(COUNTIFS(Drucksachen!$C$2:$C$293,$H36,Drucksachen!$F$2:$F$293,I$5,Drucksachen!$E$2:$E$293,"Kleine Anfrage")+COUNTIFS(Drucksachen!$C$2:$C$293,$H36,Drucksachen!$F$2:$F$293,I$5,Drucksachen!$E$2:$E$293,"Antrag")>0,1,0) | J36: =IF(COUNTIFS(Drucksachen!$C$2:$C$293,$H36,Drucksachen!$F$2:$F$293,J$5,Drucksachen!$E$2:$E$293,"Kleine Anfrage")+COUNTIFS(Drucksachen!$C$2:$C$293,$H36,Drucksachen!$F$2:$F$293,J$5,Drucksachen!$E$2:$E$293,"Antrag")>0,1,0) | K36: =IF(COUNTIFS(Drucksachen!$C$2:$C$293,$H36,Drucksachen!$F$2:$F$293,K$5,Drucksachen!$E$2:$E$293,"Kleine Anfrage")+COUNTIFS(Drucksachen!$C$2:$C$293,$H36,Drucksachen!$F$2:$F$293,K$5,Drucksachen!$E$2:$E$293,"Antrag")>0,1,0) | L36: =IF(COUNTIFS(Drucksachen!$C$2:$C$293,$H36,Drucksachen!$F$2:$F$293,L$5,Drucksachen!$E$2:$E$293,"Kleine Anfrage")+COUNTIFS(Drucksachen!$C$2:$C$293,$H36,Drucksachen!$F$2:$F$293,L$5,Drucksachen!$E$2:$E$293,"Antrag")>0,1,0)
H37: 2025-Q4 | I37: =IF(COUNTIFS(Drucksachen!$C$2:$C$293,$H37,Drucksachen!$F$2:$F$293,I$5,Drucksachen!$E$2:$E$293,"Kleine Anfrage")+COUNTIFS(Drucksachen!$C$2:$C$293,$H37,Drucksachen!$F$2:$F$293,I$5,Drucksachen!$E$2:$E$293,"Antrag")>0,1,0) | J37: =IF(COUNTIFS(Drucksachen!$C$2:$C$293,$H37,Drucksachen!$F$2:$F$293,J$5,Drucksachen!$E$2:$E$293,"Kleine Anfrage")+COUNTIFS(Drucksachen!$C$2:$C$293,$H37,Drucksachen!$F$2:$F$293,J$5,Drucksachen!$E$2:$E$293,"Antrag")>0,1,0) | K37: =IF(COUNTIFS(Drucksachen!$C$2:$C$293,$H37,Drucksachen!$F$2:$F$293,K$5,Drucksachen!$E$2:$E$293,"Kleine Anfrage")+COUNTIFS(Drucksachen!$C$2:$C$293,$H37,Drucksachen!$F$2:$F$293,K$5,Drucksachen!$E$2:$E$293,"Antrag")>0,1,0) | L37: =IF(COUNTIFS(Drucksachen!$C$2:$C$293,$H37,Drucksachen!$F$2:$F$293,L$5,Drucksachen!$E$2:$E$293,"Kleine Anfrage")+COUNTIFS(Drucksachen!$C$2:$C$293,$H37,Drucksachen!$F$2:$F$293,L$5,Drucksachen!$E$2:$E$293,"Antrag")>0,1,0)
H38: 2026-Q1 | I38: =IF(COUNTIFS(Drucksachen!$C$2:$C$293,$H38,Drucksachen!$F$2:$F$293,I$5,Drucksachen!$E$2:$E$293,"Kleine Anfrage")+COUNTIFS(Drucksachen!$C$2:$C$293,$H38,Drucksachen!$F$2:$F$293,I$5,Drucksachen!$E$2:$E$293,"Antrag")>0,1,0) | J38: =IF(COUNTIFS(Drucksachen!$C$2:$C$293,$H38,Drucksachen!$F$2:$F$293,J$5,Drucksachen!$E$2:$E$293,"Kleine Anfrage")+COUNTIFS(Drucksachen!$C$2:$C$293,$H38,Drucksachen!$F$2:$F$293,J$5,Drucksachen!$E$2:$E$293,"Antrag")>0,1,0) | K38: =IF(COUNTIFS(Drucksachen!$C$2:$C$293,$H38,Drucksachen!$F$2:$F$293,K$5,Drucksachen!$E$2:$E$293,"Kleine Anfrage")+COUNTIFS(Drucksachen!$C$2:$C$293,$H38,Drucksachen!$F$2:$F$293,K$5,Drucksachen!$E$2:$E$293,"Antrag")>0,1,0) | L38: =IF(COUNTIFS(Drucksachen!$C$2:$C$293,$H38,Drucksachen!$F$2:$F$293,L$5,Drucksachen!$E$2:$E$293,"Kleine Anfrage")+COUNTIFS(Drucksachen!$C$2:$C$293,$H38,Drucksachen!$F$2:$F$293,L$5,Drucksachen!$E$2:$E$293,"Antrag")>0,1,0)
H39: 2026-Q2 | I39: =IF(COUNTIFS(Drucksachen!$C$2:$C$293,$H39,Drucksachen!$F$2:$F$293,I$5,Drucksachen!$E$2:$E$293,"Kleine Anfrage")+COUNTIFS(Drucksachen!$C$2:$C$293,$H39,Drucksachen!$F$2:$F$293,I$5,Drucksachen!$E$2:$E$293,"Antrag")>0,1,0) | J39: =IF(COUNTIFS(Drucksachen!$C$2:$C$293,$H39,Drucksachen!$F$2:$F$293,J$5,Drucksachen!$E$2:$E$293,"Kleine Anfrage")+COUNTIFS(Drucksachen!$C$2:$C$293,$H39,Drucksachen!$F$2:$F$293,J$5,Drucksachen!$E$2:$E$293,"Antrag")>0,1,0) | K39: =IF(COUNTIFS(Drucksachen!$C$2:$C$293,$H39,Drucksachen!$F$2:$F$293,K$5,Drucksachen!$E$2:$E$293,"Kleine Anfrage")+COUNTIFS(Drucksachen!$C$2:$C$293,$H39,Drucksachen!$F$2:$F$293,K$5,Drucksachen!$E$2:$E$293,"Antrag")>0,1,0) | L39: =IF(COUNTIFS(Drucksachen!$C$2:$C$293,$H39,Drucksachen!$F$2:$F$293,L$5,Drucksachen!$E$2:$E$293,"Kleine Anfrage")+COUNTIFS(Drucksachen!$C$2:$C$293,$H39,Drucksachen!$F$2:$F$293,L$5,Drucksachen!$E$2:$E$293,"Antrag")>0,1,0)
H40: 2026-Q3 | I40: =IF(COUNTIFS(Drucksachen!$C$2:$C$293,$H40,Drucksachen!$F$2:$F$293,I$5,Drucksachen!$E$2:$E$293,"Kleine Anfrage")+COUNTIFS(Drucksachen!$C$2:$C$293,$H40,Drucksachen!$F$2:$F$293,I$5,Drucksachen!$E$2:$E$293,"Antrag")>0,1,0) | J40: =IF(COUNTIFS(Drucksachen!$C$2:$C$293,$H40,Drucksachen!$F$2:$F$293,J$5,Drucksachen!$E$2:$E$293,"Kleine Anfrage")+COUNTIFS(Drucksachen!$C$2:$C$293,$H40,Drucksachen!$F$2:$F$293,J$5,Drucksachen!$E$2:$E$293,"Antrag")>0,1,0) | K40: =IF(COUNTIFS(Drucksachen!$C$2:$C$293,$H40,Drucksachen!$F$2:$F$293,K$5,Drucksachen!$E$2:$E$293,"Kleine Anfrage")+COUNTIFS(Drucksachen!$C$2:$C$293,$H40,Drucksachen!$F$2:$F$293,K$5,Drucksachen!$E$2:$E$293,"Antrag")>0,1,0) | L40: =IF(COUNTIFS(Drucksachen!$C$2:$C$293,$H40,Drucksachen!$F$2:$F$293,L$5,Drucksachen!$E$2:$E$293,"Kleine Anfrage")+COUNTIFS(Drucksachen!$C$2:$C$293,$H40,Drucksachen!$F$2:$F$293,L$5,Drucksachen!$E$2:$E$293,"Antrag")>0,1,0)
